Workbook

Sheet Инструкция
A1: ОТЧЁТ ПО КАЧЕСТВУ ДАННЫХ ───────────────────────── ЧТО ЭТО Результат очистки 4 исходных таблиц: Товары, Поставщики, Продажи, Клиенты. СТРУКТУРА • *_исходные — сырые данные • *_очищенные — после нормализации • Справочники — категории, единицы, статусы • Итоговый_отчет — сводка и графики ГЛАВНЫЕ НАХОДКИ • 130 клиентов с некорректным email • 16 поставщиков с неправильным ИНН • 3 товара с розницей ниже закупки КАК ОБНОВИТЬ Данные тянутся формулами из *_исходные. Итоговый_отчет пересчитывается автоматически. Остались вопросы? Пишите: https://t.me/niyaz_gimadiev

Sheet Товары_исходные
A1: Артикул | B1: Наименование | C1: Категория | D1: Производитель | E1: Цена_закупки | F1: Цена_розница | G1: Единица_измерения
A2: №АРТ-001/24 | B2: Смартфон Apple iPhone 15 | C2: Смартфоны | D2: Apple | E2: 45 000,50 | F2: 79 990,00 | G2: шт
A3: АРТ_002 | B3: смартфон APPLE IPHONE 15 | C3: Телефоны | D3: Apple | E3: 44 500,00 | F3: 78 500,00 | G3: штука
A4: 003/24 | B4: Смартфон Apple iPhone 15 (Черный) | C4: Мобильные телефоны | D4: APPLE | E4: 43 800,00 | F4: 77 700 | G4: штуки
A5: №АРТ-004 | B5: Ноутбук ASUS ROG Zephyrus | C5: Ноутбуки | D5: ASUS | E5: 85 000 | F5: 129 999.99 | G5: шт.
A6: АРТ_005 | B6: ноутбук ASUS ROG Zephyrus | C6: Лэптопы | D6: asus | E6: 84 500,50 | F6: 128 500,00 | G6: шт
A7: 006-24 | B7: Ноутбук ASUS ROG Zephyrus (G14) | C7: Ноутбуки | D7: ASUS | E7: 86 000 | F7: 131 000 | G7: штука
A8: №АРТ-007 | B8: Смартфон Samsung Galaxy S24 | C8: Смартфоны | D8: Samsung | E8: 39 999,99 | F8: 69 999,00 | G8: шт.
A9: АРТ_008 | B9: смартфон SAMSUNG GALAXY S24 | C9: Телефоны | D9: SAMSUNG | E9: 39 500 | F9: 68 900 | G9: штуки
A10: 009/24 | B10: Смартфон Samsung Galaxy S24 (Синий) | C10: Мобильные телефоны | D10: Samsung | E10: 40 200 | F10: 70 500 | G10: шт
A11: №АРТ-010 | B11: Планшет iPad Pro 12.9 | C11: Планшеты | D11: Apple | E11: 55 000 | F11: 89 900 | G11: шт.
A12: АРТ_011 | B12: планшет APPLE IPAD PRO 12.9 | C12: Планшеты | D12: apple | E12: 54 500 | F12: 88 500 | G12: штука
... A502: 501/24 | B502: Клавиатура Logitech POP Keys (Pink) | C502: Аксессуары | D502: LOGITECH | E502: 4 000 | F502: 6 800 | G502: шт

Sheet Товары_очищенные
A1: Артикул | B1: Наименование | C1: Категория | D1: Производитель | E1: Цена_закупки | F1: Цена_розница | G1: Единица_измерения | H1: Проверка_цены | I1: Проверка_уникальности
A2: ="АРТ-"&LEFT(SUBSTITUTE(SUBSTITUTE(SUBSTITUTE(SUBSTITUTE('Товары_исходные'!A2,"№",""),"АРТ-",""),"АРТ_",""),"/","-"),3) -> АРТ-001 | B2: =PROPER(TRIM(IFERROR(LEFT('Товары_исходные'!B2,FIND("(",'Товары_исходные'!B2)-1),'Товары_исходные'!B2))) -> Смартфон Apple Iphone 15 | C2: =IFERROR(VLOOKUP('Товары_исходные'!C2,Справочники!$A$2:$B$50,2,FALSE),'Товары_исходные'!C2) -> Смартфоны | D2: =PROPER(TRIM('Товары_исходные'!D2)) -> Apple | E2: =IFERROR(VALUE(IF(AND(ISNUMBER(FIND(",",'Товары_исходные'!E2)),ISNUMBER(FIND(".",'Товары_исходные'!E2))),SUBSTITUTE(SUBSTITUTE(SUBSTITUTE(SUBSTITUTE('Товары_исходные'!E2," ",""),"руб.",""),"руб",""),",",""),SUBSTITUTE(SUBSTITUTE(SUBSTITUTE(SUBSTITUTE('Товары_исходные'!E2," ",""),"руб.",""),"руб",""),",","."))),0) -> 45000.5 | F2: =IFERROR(VALUE(IF(AND(ISNUMBER(FIND(",",'Товары_исходные'!F2)),ISNUMBER(FIND(".",'Товары_исходные'!F2))),SUBSTITUTE(SUBSTITUTE(SUBSTITUTE(SUBSTITUTE('Товары_исходные'!F2," ",""),"руб.",""),"руб",""),",",""),SUBSTITUTE(SUBSTITUTE(SUBSTITUTE(SUBSTITUTE('Товары_исходные'!F2," ",""),"руб.",""),"руб",""),",","."))),0) -> 79990 | G2: =IFERROR(VLOOKUP('Товары_исходные'!G2,Справочники!$D$2:$E$50,2,FALSE),"шт.") -> шт. | H2: =IF(F2>=E2,"OK","Розница ниже закупки") -> OK | I2: =IF(COUNTIF($A$2:$A$502,A2)=1,"OK","Дубликат") -> OK
A3: ="АРТ-"&LEFT(SUBSTITUTE(SUBSTITUTE(SUBSTITUTE(SUBSTITUTE(Товары_исходные!A3,"№",""),"АРТ-",""),"АРТ_",""),"/","-"),3) -> АРТ-002 | B3: =PROPER(TRIM(IFERROR(LEFT(Товары_исходные!B3,FIND("(",Товары_исходные!B3)-1),Товары_исходные!B3))) -> Смартфон Apple Iphone 15 | C3: =IFERROR(VLOOKUP(Товары_исходные!C3,Справочники!$A$2:$B$50,2,FALSE),Товары_исходные!C3) -> Смартфоны | D3: =PROPER(TRIM(Товары_исходные!D3)) -> Apple | E3: =IFERROR(VALUE(IF(AND(ISNUMBER(FIND(",",Товары_исходные!E3)),ISNUMBER(FIND(".",Товары_исходные!E3))),SUBSTITUTE(SUBSTITUTE(SUBSTITUTE(SUBSTITUTE(Товары_исходные!E3," ",""),"руб.",""),"руб",""),",",""),SUBSTITUTE(SUBSTITUTE(SUBSTITUTE(SUBSTITUTE(Товары_исходные!E3," ",""),"руб.",""),"руб",""),",","."))),0) -> 44500 | F3: =IFERROR(VALUE(IF(AND(ISNUMBER(FIND(",",Товары_исходные!F3)),ISNUMBER(FIND(".",Товары_исходные!F3))),SUBSTITUTE(SUBSTITUTE(SUBSTITUTE(SUBSTITUTE(Товары_исходные!F3," ",""),"руб.",""),"руб",""),",",""),SUBSTITUTE(SUBSTITUTE(SUBSTITUTE(SUBSTITUTE(Товары_исходные!F3," ",""),"руб.",""),"руб",""),",","."))),0) -> 78500 | G3: =IFERROR(VLOOKUP(Товары_исходные!G3,Справочники!$D$2:$E$50,2,FALSE),"шт.") -> шт. | H3: =IF(F3>=E3,"OK","Розница ниже закупки") -> OK | I3: =IF(COUNTIF($A$2:$A$502,A3)=1,"OK","Дубликат") -> OK
A4: ="АРТ-"&LEFT(SUBSTITUTE(SUBSTITUTE(SUBSTITUTE(SUBSTITUTE(Товары_исходные!A4,"№",""),"АРТ-",""),"АРТ_",""),"/","-"),3) -> АРТ-003 | B4: =PROPER(TRIM(IFERROR(LEFT(Товары_исходные!B4,FIND("(",Товары_исходные!B4)-1),Товары_исходные!B4))) -> Смартфон Apple Iphone 15 | C4: =IFERROR(VLOOKUP(Товары_исходные!C4,Справочники!$A$2:$B$50,2,FALSE),Товары_исходные!C4) -> Смартфоны | D4: =PROPER(TRIM(Товары_исходные!D4)) -> Apple | E4: =IFERROR(VALUE(IF(AND(ISNUMBER(FIND(",",Товары_исходные!E4)),ISNUMBER(FIND(".",Товары_исходные!E4))),SUBSTITUTE(SUBSTITUTE(SUBSTITUTE(SUBSTITUTE(Товары_исходные!E4," ",""),"руб.",""),"руб",""),",",""),SUBSTITUTE(SUBSTITUTE(SUBSTITUTE(SUBSTITUTE(Товары_исходные!E4," ",""),"руб.",""),"руб",""),",","."))),0) -> 43800 | F4: =IFERROR(VALUE(IF(AND(ISNUMBER(FIND(",",Товары_исходные!F4)),ISNUMBER(FIND(".",Товары_исходные!F4))),SUBSTITUTE(SUBSTITUTE(SUBSTITUTE(SUBSTITUTE(Товары_исходные!F4," ",""),"руб.",""),"руб",""),",",""),SUBSTITUTE(SUBSTITUTE(SUBSTITUTE(SUBSTITUTE(Товары_исходные!F4," ",""),"руб.",""),"руб",""),",","."))),0) -> 77700 | G4: =IFERROR(VLOOKUP(Товары_исходные!G4,Справочники!$D$2:$E$50,2,FALSE),"шт.") -> шт. | H4: =IF(F4>=E4,"OK","Розница ниже закупки") -> OK | I4: =IF(COUNTIF($A$2:$A$502,A4)=1,"OK","Дубликат") -> OK
A5: ="АРТ-"&LEFT(SUBSTITUTE(SUBSTITUTE(SUBSTITUTE(SUBSTITUTE(Товары_исходные!A5,"№",""),"АРТ-",""),"АРТ_",""),"/","-"),3) -> АРТ-004 | B5: =PROPER(TRIM(IFERROR(LEFT(Товары_исходные!B5,FIND("(",Товары_исходные!B5)-1),Товары_исходные!B5))) -> Ноутбук Asus Rog Zephyrus | C5: =IFERROR(VLOOKUP(Товары_исходные!C5,Справочники!$A$2:$B$50,2,FALSE),Товары_исходные!C5) -> Ноутбуки | D5: =PROPER(TRIM(Товары_исходные!D5)) -> Asus | E5: =IFERROR(VALUE(IF(AND(ISNUMBER(FIND(",",Товары_исходные!E5)),ISNUMBER(FIND(".",Товары_исходные!E5))),SUBSTITUTE(SUBSTITUTE(SUBSTITUTE(SUBSTITUTE(Товары_исходные!E5," ",""),"руб.",""),"руб",""),",",""),SUBSTITUTE(SUBSTITUTE(SUBSTITUTE(SUBSTITUTE(Товары_исходные!E5," ",""),"руб.",""),"руб",""),",","."))),0) -> 85000 | F5: =IFERROR(VALUE(IF(AND(ISNUMBER(FIND(",",Товары_исходные!F5)),ISNUMBER(FIND(".",Товары_исходные!F5))),SUBSTITUTE(SUBSTITUTE(SUBSTITUTE(SUBSTITUTE(Товары_исходные!F5," ",""),"руб.",""),"руб",""),",",""),SUBSTITUTE(SUBSTITUTE(SUBSTITUTE(SUBSTITUTE(Товары_исходные!F5," ",""),"руб.",""),"руб",""),",","."))),0) -> 129999.99 | G5: =IFERROR(VLOOKUP(Товары_исходные!G5,Справочники!$D$2:$E$50,2,FALSE),"шт.") -> шт. | H5: =IF(F5>=E5,"OK","Розница ниже закупки") -> OK | I5: =IF(COUNTIF($A$2:$A$502,A5)=1,"OK","Дубликат") -> OK
A6: ="АРТ-"&LEFT(SUBSTITUTE(SUBSTITUTE(SUBSTITUTE(SUBSTITUTE(Товары_исходные!A6,"№",""),"АРТ-",""),"АРТ_",""),"/","-"),3) -> АРТ-005 | B6: =PROPER(TRIM(IFERROR(LEFT(Товары_исходные!B6,FIND("(",Товары_исходные!B6)-1),Товары_исходные!B6))) -> Ноутбук Asus Rog Zephyrus | C6: =IFERROR(VLOOKUP(Товары_исходные!C6,Справочники!$A$2:$B$50,2,FALSE),Товары_исходные!C6) -> Ноутбуки | D6: =PROPER(TRIM(Товары_исходные!D6)) -> Asus | E6: =IFERROR(VALUE(IF(AND(ISNUMBER(FIND(",",Товары_исходные!E6)),ISNUMBER(FIND(".",Товары_исходные!E6))),SUBSTITUTE(SUBSTITUTE(SUBSTITUTE(SUBSTITUTE(Товары_исходные!E6," ",""),"руб.",""),"руб",""),",",""),SUBSTITUTE(SUBSTITUTE(SUBSTITUTE(SUBSTITUTE(Товары_исходные!E6," ",""),"руб.",""),"руб",""),",","."))),0) -> 84500.5 | F6: =IFERROR(VALUE(IF(AND(ISNUMBER(FIND(",",Товары_исходные!F6)),ISNUMBER(FIND(".",Товары_исходные!F6))),SUBSTITUTE(SUBSTITUTE(SUBSTITUTE(SUBSTITUTE(Товары_исходные!F6," ",""),"руб.",""),"руб",""),",",""),SUBSTITUTE(SUBSTITUTE(SUBSTITUTE(SUBSTITUTE(Товары_исходные!F6," ",""),"руб.",""),"руб",""),",","."))),0) -> 128500 | G6: =IFERROR(VLOOKUP(Товары_исходные!G6,Справочники!$D$2:$E$50,2,FALSE),"шт.") -> шт. | H6: =IF(F6>=E6,"OK","Розница ниже закупки") -> OK | I6: =IF(COUNTIF($A$2:$A$502,A6)=1,"OK","Дубликат") -> OK
A7: ="АРТ-"&LEFT(SUBSTITUTE(SUBSTITUTE(SUBSTITUTE(SUBSTITUTE(Товары_исходные!A7,"№",""),"АРТ-",""),"АРТ_",""),"/","-"),3) -> АРТ-006 | B7: =PROPER(TRIM(IFERROR(LEFT(Товары_исходные!B7,FIND("(",Товары_исходные!B7)-1),Товары_исходные!B7))) -> Ноутбук Asus Rog Zephyrus | C7: =IFERROR(VLOOKUP(Товары_исходные!C7,Справочники!$A$2:$B$50,2,FALSE),Товары_исходные!C7) -> Ноутбуки | D7: =PROPER(TRIM(Товары_исходные!D7)) -> Asus | E7: =IFERROR(VALUE(IF(AND(ISNUMBER(FIND(",",Товары_исходные!E7)),ISNUMBER(FIND(".",Товары_исходные!E7))),SUBSTITUTE(SUBSTITUTE(SUBSTITUTE(SUBSTITUTE(Товары_исходные!E7," ",""),"руб.",""),"руб",""),",",""),SUBSTITUTE(SUBSTITUTE(SUBSTITUTE(SUBSTITUTE(Товары_исходные!E7," ",""),"руб.",""),"руб",""),",","."))),0) -> 86000 | F7: =IFERROR(VALUE(IF(AND(ISNUMBER(FIND(",",Товары_исходные!F7)),ISNUMBER(FIND(".",Товары_исходные!F7))),SUBSTITUTE(SUBSTITUTE(SUBSTITUTE(SUBSTITUTE(Товары_исходные!F7," ",""),"руб.",""),"руб",""),",",""),SUBSTITUTE(SUBSTITUTE(SUBSTITUTE(SUBSTITUTE(Товары_исходные!F7," ",""),"руб.",""),"руб",""),",","."))),0) -> 131000 | G7: =IFERROR(VLOOKUP(Товары_исходные!G7,Справочники!$D$2:$E$50,2,FALSE),"шт.") -> шт. | H7: =IF(F7>=E7,"OK","Розница ниже закупки") -> OK | I7: =IF(COUNTIF($A$2:$A$502,A7)=1,"OK","Дубликат") -> OK
A8: ="АРТ-"&LEFT(SUBSTITUTE(SUBSTITUTE(SUBSTITUTE(SUBSTITUTE(Товары_исходные!A8,"№",""),"АРТ-",""),"АРТ_",""),"/","-"),3) -> АРТ-007 | B8: =PROPER(TRIM(IFERROR(LEFT(Товары_исходные!B8,FIND("(",Товары_исходные!B8)-1),Товары_исходные!B8))) -> Смартфон Samsung Galaxy S24 | C8: =IFERROR(VLOOKUP(Товары_исходные!C8,Справочники!$A$2:$B$50,2,FALSE),Товары_исходные!C8) -> Смартфоны | D8: =PROPER(TRIM(Товары_исходные!D8)) -> Samsung | E8: =IFERROR(VALUE(IF(AND(ISNUMBER(FIND(",",Товары_исходные!E8)),ISNUMBER(FIND(".",Товары_исходные!E8))),SUBSTITUTE(SUBSTITUTE(SUBSTITUTE(SUBSTITUTE(Товары_исходные!E8," ",""),"руб.",""),"руб",""),",",""),SUBSTITUTE(SUBSTITUTE(SUBSTITUTE(SUBSTITUTE(Товары_исходные!E8," ",""),"руб.",""),"руб",""),",","."))),0) -> 39999.99 | F8: =IFERROR(VALUE(IF(AND(ISNUMBER(FIND(",",Товары_исходные!F8)),ISNUMBER(FIND(".",Товары_исходные!F8))),SUBSTITUTE(SUBSTITUTE(SUBSTITUTE(SUBSTITUTE(Товары_исходные!F8," ",""),"руб.",""),"руб",""),",",""),SUBSTITUTE(SUBSTITUTE(SUBSTITUTE(SUBSTITUTE(Товары_исходные!F8," ",""),"руб.",""),"руб",""),",","."))),0) -> 69999 | G8: =IFERROR(VLOOKUP(Товары_исходные!G8,Справочники!$D$2:$E$50,2,FALSE),"шт.") -> шт. | H8: =IF(F8>=E8,"OK","Розница ниже закупки") -> OK | I8: =IF(COUNTIF($A$2:$A$502,A8)=1,"OK","Дубликат") -> OK
A9: ="АРТ-"&LEFT(SUBSTITUTE(SUBSTITUTE(SUBSTITUTE(SUBSTITUTE(Товары_исходные!A9,"№",""),"АРТ-",""),"АРТ_",""),"/","-"),3) -> АРТ-008 | B9: =PROPER(TRIM(IFERROR(LEFT(Товары_исходные!B9,FIND("(",Товары_исходные!B9)-1),Товары_исходные!B9))) -> Смартфон Samsung Galaxy S24 | C9: =IFERROR(VLOOKUP(Товары_исходные!C9,Справочники!$A$2:$B$50,2,FALSE),Товары_исходные!C9) -> Смартфоны | D9: =PROPER(TRIM(Товары_исходные!D9)) -> Samsung | E9: =IFERROR(VALUE(IF(AND(ISNUMBER(FIND(",",Товары_исходные!E9)),ISNUMBER(FIND(".",Товары_исходные!E9))),SUBSTITUTE(SUBSTITUTE(SUBSTITUTE(SUBSTITUTE(Товары_исходные!E9," ",""),"руб.",""),"руб",""),",",""),SUBSTITUTE(SUBSTITUTE(SUBSTITUTE(SUBSTITUTE(Товары_исходные!E9," ",""),"руб.",""),"руб",""),",","."))),0) -> 39500 | F9: =IFERROR(VALUE(IF(AND(ISNUMBER(FIND(",",Товары_исходные!F9)),ISNUMBER(FIND(".",Товары_исходные!F9))),SUBSTITUTE(SUBSTITUTE(SUBSTITUTE(SUBSTITUTE(Товары_исходные!F9," ",""),"руб.",""),"руб",""),",",""),SUBSTITUTE(SUBSTITUTE(SUBSTITUTE(SUBSTITUTE(Товары_исходные!F9," ",""),"руб.",""),"руб",""),",","."))),0) -> 68900 | G9: =IFERROR(VLOOKUP(Товары_исходные!G9,Справочники!$D$2:$E$50,2,FALSE),"шт.") -> шт. | H9: =IF(F9>=E9,"OK","Розница ниже закупки") -> OK | I9: =IF(COUNTIF($A$2:$A$502,A9)=1,"OK","Дубликат") -> OK
A10: ="АРТ-"&LEFT(SUBSTITUTE(SUBSTITUTE(SUBSTITUTE(SUBSTITUTE('Товары_исходные'!A10,"№",""),"АРТ-",""),"АРТ_",""),"/","-"),3) -> АРТ-009 | B10: =PROPER(TRIM(IFERROR(LEFT('Товары_исходные'!B10,FIND("(",'Товары_исходные'!B10)-1),'Товары_исходные'!B10))) -> Смартфон Samsung Galaxy S24 | C10: =IFERROR(VLOOKUP('Товары_исходные'!C10,Справочники!$A$2:$B$50,2,FALSE),'Товары_исходные'!C10) -> Смартфоны | D10: =PROPER(TRIM('Товары_исходные'!D10)) -> Samsung | E10: =IFERROR(VALUE(IF(AND(ISNUMBER(FIND(",",'Товары_исходные'!E10)),ISNUMBER(FIND(".",'Товары_исходные'!E10))),SUBSTITUTE(SUBSTITUTE(SUBSTITUTE(SUBSTITUTE('Товары_исходные'!E10," ",""),"руб.",""),"руб",""),",",""),SUBSTITUTE(SUBSTITUTE(SUBSTITUTE(SUBSTITUTE('Товары_исходные'!E10," ",""),"руб.",""),"руб",""),",","."))),0) -> 40200 | F10: =IFERROR(VALUE(IF(AND(ISNUMBER(FIND(",",'Товары_исходные'!F10)),ISNUMBER(FIND(".",'Товары_исходные'!F10))),SUBSTITUTE(SUBSTITUTE(SUBSTITUTE(SUBSTITUTE('Товары_исходные'!F10," ",""),"руб.",""),"руб",""),",",""),SUBSTITUTE(SUBSTITUTE(SUBSTITUTE(SUBSTITUTE('Товары_исходные'!F10," ",""),"руб.",""),"руб",""),",","."))),0) -> 70500 | G10: =IFERROR(VLOOKUP('Товары_исходные'!G10,Справочники!$D$2:$E$50,2,FALSE),"шт.") -> шт. | H10: =IF(F10>=E10,"OK","Розница ниже закупки") -> OK | I10: =IF(COUNTIF($A$2:$A$502,A10)=1,"OK","Дубликат") -> OK
A11: ="АРТ-"&LEFT(SUBSTITUTE(SUBSTITUTE(SUBSTITUTE(SUBSTITUTE(Товары_исходные!A11,"№",""),"АРТ-",""),"АРТ_",""),"/","-"),3) -> АРТ-010 | B11: =PROPER(TRIM(IFERROR(LEFT(Товары_исходные!B11,FIND("(",Товары_исходные!B11)-1),Товары_исходные!B11))) -> Планшет Ipad Pro 12.9 | C11: =IFERROR(VLOOKUP(Товары_исходные!C11,Справочники!$A$2:$B$50,2,FALSE),Товары_исходные!C11) -> Планшеты | D11: =PROPER(TRIM(Товары_исходные!D11)) -> Apple | E11: =IFERROR(VALUE(IF(AND(ISNUMBER(FIND(",",Товары_исходные!E11)),ISNUMBER(FIND(".",Товары_исходные!E11))),SUBSTITUTE(SUBSTITUTE(SUBSTITUTE(SUBSTITUTE(Товары_исходные!E11," ",""),"руб.",""),"руб",""),",",""),SUBSTITUTE(SUBSTITUTE(SUBSTITUTE(SUBSTITUTE(Товары_исходные!E11," ",""),"руб.",""),"руб",""),",","."))),0) -> 55000 | F11: =IFERROR(VALUE(IF(AND(ISNUMBER(FIND(",",Товары_исходные!F11)),ISNUMBER(FIND(".",Товары_исходные!F11))),SUBSTITUTE(SUBSTITUTE(SUBSTITUTE(SUBSTITUTE(Товары_исходные!F11," ",""),"руб.",""),"руб",""),",",""),SUBSTITUTE(SUBSTITUTE(SUBSTITUTE(SUBSTITUTE(Товары_исходные!F11," ",""),"руб.",""),"руб",""),",","."))),0) -> 89900 | G11: =IFERROR(VLOOKUP(Товары_исходные!G11,Справочники!$D$2:$E$50,2,FALSE),"шт.") -> шт. | H11: =IF(F11>=E11,"OK","Розница ниже закупки") -> OK | I11: =IF(COUNTIF($A$2:$A$502,A11)=1,"OK","Дубликат") -> OK
A12: ="АРТ-"&LEFT(SUBSTITUTE(SUBSTITUTE(SUBSTITUTE(SUBSTITUTE(Товары_исходные!A12,"№",""),"АРТ-",""),"АРТ_",""),"/","-"),3) -> АРТ-011 | B12: =PROPER(TRIM(IFERROR(LEFT(Товары_исходные!B12,FIND("(",Товары_исходные!B12)-1),Товары_исходные!B12))) -> Планшет Apple Ipad Pro 12.9 | C12: =IFERROR(VLOOKUP(Товары_исходные!C12,Справочники!$A$2:$B$50,2,FALSE),Товары_исходные!C12) -> Планшеты | D12: =PROPER(TRIM(Товары_исходные!D12)) -> Apple | E12: =IFERROR(VALUE(IF(AND(ISNUMBER(FIND(",",Товары_исходные!E12)),ISNUMBER(FIND(".",Товары_исходные!E12))),SUBSTITUTE(SUBSTITUTE(SUBSTITUTE(SUBSTITUTE(Товары_исходные!E12," ",""),"руб.",""),"руб",""),",",""),SUBSTITUTE(SUBSTITUTE(SUBSTITUTE(SUBSTITUTE(Товары_исходные!E12," ",""),"руб.",""),"руб",""),",","."))),0) -> 54500 | F12: =IFERROR(VALUE(IF(AND(ISNUMBER(FIND(",",Товары_исходные!F12)),ISNUMBER(FIND(".",Товары_исходные!F12))),SUBSTITUTE(SUBSTITUTE(SUBSTITUTE(SUBSTITUTE(Товары_исходные!F12," ",""),"руб.",""),"руб",""),",",""),SUBSTITUTE(SUBSTITUTE(SUBSTITUTE(SUBSTITUTE(Товары_исходные!F12," ",""),"руб.",""),"руб",""),",","."))),0) -> 88500 | G12: =IFERROR(VLOOKUP(Товары_исходные!G12,Справочники!$D$2:$E$50,2,FALSE),"шт.") -> шт. | H12: =IF(F12>=E12,"OK","Розница ниже закупки") -> OK | I12: =IF(COUNTIF($A$2:$A$502,A12)=1,"OK","Дубликат") -> OK
A13: ="АРТ-"&LEFT(SUBSTITUTE(SUBSTITUTE(SUBSTITUTE(SUBSTITUTE(Товары_исходные!A13,"№",""),"АРТ-",""),"АРТ_",""),"/","-"),3) -> АРТ-012 | B13: =PROPER(TRIM(IFERROR(LEFT(Товары_исходные!B13,FIND("(",Товары_исходные!B13)-1),Товары_исходные!B13))) -> Планшет Apple Ipad Pro 12.9 | C13: =IFERROR(VLOOKUP(Товары_исходные!C13,Справочники!$A$2:$B$50,2,FALSE),Товары_исходные!C13) -> Планшеты | D13: =PROPER(TRIM(Товары_исходные!D13)) -> Apple | E13: =IFERROR(VALUE(IF(AND(ISNUMBER(FIND(",",Товары_исходные!E13)),ISNUMBER(FIND(".",Товары_исходные!E13))),SUBSTITUTE(SUBSTITUTE(SUBSTITUTE(SUBSTITUTE(Товары_исходные!E13," ",""),"руб.",""),"руб",""),",",""),SUBSTITUTE(SUBSTITUTE(SUBSTITUTE(SUBSTITUTE(Товары_исходные!E13," ",""),"руб.",""),"руб",""),",","."))),0) -> 56000 | F13: =IFERROR(VALUE(IF(AND(ISNUMBER(FIND(",",Товары_исходные!F13)),ISNUMBER(FIND(".",Товары_исходные!F13))),SUBSTITUTE(SUBSTITUTE(SUBSTITUTE(SUBSTITUTE(Товары_исходные!F13," ",""),"руб.",""),"руб",""),",",""),SUBSTITUTE(SUBSTITUTE(SUBSTITUTE(SUBSTITUTE(Товары_исходные!F13," ",""),"руб.",""),"руб",""),",","."))),0) -> 91000 | G13: =IFERROR(VLOOKUP(Товары_исходные!G13,Справочники!$D$2:$E$50,2,FALSE),"шт.") -> шт. | H13: =IF(F13>=E13,"OK","Розница ниже закупки") -> OK | I13: =IF(COUNTIF($A$2:$A$502,A13)=1,"OK","Дубликат") -> OK
A14: ="АРТ-"&LEFT(SUBSTITUTE(SUBSTITUTE(SUBSTITUTE(SUBSTITUTE(Товары_исходные!A14,"№",""),"АРТ-",""),"АРТ_",""),"/","-"),3) -> АРТ-013 | B14: =PROPER(TRIM(IFERROR(LEFT(Товары_исходные!B14,FIND("(",Товары_исходные!B14)-1),Товары_исходные!B14))) -> Телевизор Lg Oled65C3 | C14: =IFERROR(VLOOKUP(Товары_исходные!C14,Справочники!$A$2:$B$50,2,FALSE),Товары_исходные!C14) -> Телевизоры | D14: =PROPER(TRIM(Товары_исходные!D14)) -> Lg | E14: =IFERROR(VALUE(IF(AND(ISNUMBER(FIND(",",Товары_исходные!E14)),ISNUMBER(FIND(".",Товары_исходные!E14))),SUBSTITUTE(SUBSTITUTE(SUBSTITUTE(SUBSTITUTE(Товары_исходные!E14," ",""),"руб.",""),"руб",""),",",""),SUBSTITUTE(SUBSTITUTE(SUBSTITUTE(SUBSTITUTE(Товары_исходные!E14," ",""),"руб.",""),"руб",""),",","."))),0) -> 95000 | F14: =IFERROR(VALUE(IF(AND(ISNUMBER(FIND(",",Товары_исходные!F14)),ISNUMBER(FIND(".",Товары_исходные!F14))),SUBSTITUTE(SUBSTITUTE(SUBSTITUTE(SUBSTITUTE(Товары_исходные!F14," ",""),"руб.",""),"руб",""),",",""),SUBSTITUTE(SUBSTITUTE(SUBSTITUTE(SUBSTITUTE(Товары_исходные!F14," ",""),"руб.",""),"руб",""),",","."))),0) -> 149999 | G14: =IFERROR(VLOOKUP(Товары_исходные!G14,Справочники!$D$2:$E$50,2,FALSE),"шт.") -> шт. | H14: =IF(F14>=E14,"OK","Розница ниже закупки") -> OK | I14: =IF(COUNTIF($A$2:$A$502,A14)=1,"OK","Дубликат") -> OK
A15: ="АРТ-"&LEFT(SUBSTITUTE(SUBSTITUTE(SUBSTITUTE(SUBSTITUTE(Товары_исходные!A15,"№",""),"АРТ-",""),"АРТ_",""),"/","-"),3) -> АРТ-014 | B15: =PROPER(TRIM(IFERROR(LEFT(Товары_исходные!B15,FIND("(",Товары_исходные!B15)-1),Товары_исходные!B15))) -> Телевизор Lg Oled65C3 | C15: =IFERROR(VLOOKUP(Товары_исходные!C15,Справочники!$A$2:$B$50,2,FALSE),Товары_исходные!C15) -> Телевизоры | D15: =PROPER(TRIM(Товары_исходные!D15)) -> Lg | E15: =IFERROR(VALUE(IF(AND(ISNUMBER(FIND(",",Товары_исходные!E15)),ISNUMBER(FIND(".",Товары_исходные!E15))),SUBSTITUTE(SUBSTITUTE(SUBSTITUTE(SUBSTITUTE(Товары_исходные!E15," ",""),"руб.",""),"руб",""),",",""),SUBSTITUTE(SUBSTITUTE(SUBSTITUTE(SUBSTITUTE(Товары_исходные!E15," ",""),"руб.",""),"руб",""),",","."))),0) -> 93500 | F15: =IFERROR(VALUE(IF(AND(ISNUMBER(FIND(",",Товары_исходные!F15)),ISNUMBER(FIND(".",Товары_исходные!F15))),SUBSTITUTE(SUBSTITUTE(SUBSTITUTE(SUBSTITUTE(Товары_исходные!F15," ",""),"руб.",""),"руб",""),",",""),SUBSTITUTE(SUBSTITUTE(SUBSTITUTE(SUBSTITUTE(Товары_исходные!F15," ",""),"руб.",""),"руб",""),",","."))),0) -> 147500 | G15: =IFERROR(VLOOKUP(Товары_исходные!G15,Справочники!$D$2:$E$50,2,FALSE),"шт.") -> шт. | H15: =IF(F15>=E15,"OK","Розница ниже закупки") -> OK | I15: =IF(COUNTIF($A$2:$A$502,A15)=1,"OK","Дубликат") -> OK
A16: ="АРТ-"&LEFT(SUBSTITUTE(SUBSTITUTE(SUBSTITUTE(SUBSTITUTE(Товары_исходные!A16,"№",""),"АРТ-",""),"АРТ_",""),"/","-"),3) -> АРТ-015 | B16: =PROPER(TRIM(IFERROR(LEFT(Товары_исходные!B16,FIND("(",Товары_исходные!B16)-1),Товары_исходные!B16))) -> Телевизор Lg Oled65C3 | C16: =IFERROR(VLOOKUP(Товары_исходные!C16,Справочники!$A$2:$B$50,2,FALSE),Товары_исходные!C16) -> Телевизоры | D16: =PROPER(TRIM(Товары_исходные!D16)) -> Lg | E16: =IFERROR(VALUE(IF(AND(ISNUMBER(FIND(",",Товары_исходные!E16)),ISNUMBER(FIND(".",Товары_исходные!E16))),SUBSTITUTE(SUBSTITUTE(SUBSTITUTE(SUBSTITUTE(Товары_исходные!E16," ",""),"руб.",""),"руб",""),",",""),SUBSTITUTE(SUBSTITUTE(SUBSTITUTE(SUBSTITUTE(Товары_исходные!E16," ",""),"руб.",""),"руб",""),",","."))),0) -> 96500 | F16: =IFERROR(VALUE(IF(AND(ISNUMBER(FIND(",",Товары_исходные!F16)),ISNUMBER(FIND(".",Товары_исходные!F16))),SUBSTITUTE(SUBSTITUTE(SUBSTITUTE(SUBSTITUTE(Товары_исходные!F16," ",""),"руб.",""),"руб",""),",",""),SUBSTITUTE(SUBSTITUTE(SUBSTITUTE(SUBSTITUTE(Товары_исходные!F16," ",""),"руб.",""),"руб",""),",","."))),0) -> 151000 | G16: =IFERROR(VLOOKUP(Товары_исходные!G16,Справочники!$D$2:$E$50,2,FALSE),"шт.") -> шт. | H16: =IF(F16>=E16,"OK","Розница ниже закупки") -> OK | I16: =IF(COUNTIF($A$2:$A$502,A16)=1,"OK","Дубликат") -> OK
A17: ="АРТ-"&LEFT(SUBSTITUTE(SUBSTITUTE(SUBSTITUTE(SUBSTITUTE(Товары_исходные!A17,"№",""),"АРТ-",""),"АРТ_",""),"/","-"),3) -> АРТ-016 | B17: =PROPER(TRIM(IFERROR(LEFT(Товары_исходные!B17,FIND("(",Товары_исходные!B17)-1),Товары_исходные!B17))) -> Наушники Sony Wh-1000Xm5 | C17: =IFERROR(VLOOKUP(Товары_исходные!C17,Справочники!$A$2:$B$50,2,FALSE),Товары_исходные!C17) -> Наушники | D17: =PROPER(TRIM(Товары_исходные!D17)) -> Sony | E17: =IFERROR(VALUE(IF(AND(ISNUMBER(FIND(",",Товары_исходные!E17)),ISNUMBER(FIND(".",Товары_исходные!E17))),SUBSTITUTE(SUBSTITUTE(SUBSTITUTE(SUBSTITUTE(Товары_исходные!E17," ",""),"руб.",""),"руб",""),",",""),SUBSTITUTE(SUBSTITUTE(SUBSTITUTE(SUBSTITUTE(Товары_исходные!E17," ",""),"руб.",""),"руб",""),",","."))),0) -> 18000 | F17: =IFERROR(VALUE(IF(AND(ISNUMBER(FIND(",",Товары_исходные!F17)),ISNUMBER(FIND(".",Товары_исходные!F17))),SUBSTITUTE(SUBSTITUTE(SUBSTITUTE(SUBSTITUTE(Товары_исходные!F17," ",""),"руб.",""),"руб",""),",",""),SUBSTITUTE(SUBSTITUTE(SUBSTITUTE(SUBSTITUTE(Товары_исходные!F17," ",""),"руб.",""),"руб",""),",","."))),0) -> 29990 | G17: =IFERROR(VLOOKUP(Товары_исходные!G17,Справочники!$D$2:$E$50,2,FALSE),"шт.") -> шт. | H17: =IF(F17>=E17,"OK","Розница ниже закупки") -> OK | I17: =IF(COUNTIF($A$2:$A$502,A17)=1,"OK","Дубликат") -> OK
A18: ="АРТ-"&LEFT(SUBSTITUTE(SUBSTITUTE(SUBSTITUTE(SUBSTITUTE(Товары_исходные!A18,"№",""),"АРТ-",""),"АРТ_",""),"/","-"),3) -> АРТ-017 | B18: =PROPER(TRIM(IFERROR(LEFT(Товары_исходные!B18,FIND("(",Товары_исходные!B18)-1),Товары_исходные!B18))) -> Наушники Sony Wh-1000Xm5 | C18: =IFERROR(VLOOKUP(Товары_исходные!C18,Справочники!$A$2:$B$50,2,FALSE),Товары_исходные!C18) -> Наушники | D18: =PROPER(TRIM(Товары_исходные!D18)) -> Sony | E18: =IFERROR(VALUE(IF(AND(ISNUMBER(FIND(",",Товары_исходные!E18)),ISNUMBER(FIND(".",Товары_исходные!E18))),SUBSTITUTE(SUBSTITUTE(SUBSTITUTE(SUBSTITUTE(Товары_исходные!E18," ",""),"руб.",""),"руб",""),",",""),SUBSTITUTE(SUBSTITUTE(SUBSTITUTE(SUBSTITUTE(Товары_исходные!E18," ",""),"руб.",""),"руб",""),",","."))),0) -> 17500 | F18: =IFERROR(VALUE(IF(AND(ISNUMBER(FIND(",",Товары_исходные!F18)),ISNUMBER(FIND(".",Товары_исходные!F18))),SUBSTITUTE(SUBSTITUTE(SUBSTITUTE(SUBSTITUTE(Товары_исходные!F18," ",""),"руб.",""),"руб",""),",",""),SUBSTITUTE(SUBSTITUTE(SUBSTITUTE(SUBSTITUTE(Товары_исходные!F18," ",""),"руб.",""),"руб",""),",","."))),0) -> 28900 | G18: =IFERROR(VLOOKUP(Товары_исходные!G18,Справочники!$D$2:$E$50,2,FALSE),"шт.") -> шт. | H18: =IF(F18>=E18,"OK","Розница ниже закупки") -> OK | I18: =IF(COUNTIF($A$2:$A$502,A18)=1,"OK","Дубликат") -> OK
A19: ="АРТ-"&LEFT(SUBSTITUTE(SUBSTITUTE(SUBSTITUTE(SUBSTITUTE(Товары_исходные!A19,"№",""),"АРТ-",""),"АРТ_",""),"/","-"),3) -> АРТ-018 | B19: =PROPER(TRIM(IFERROR(LEFT(Товары_исходные!B19,FIND("(",Товары_исходные!B19)-1),Товары_исходные!B19))) -> Наушники Sony Wh-1000Xm5 | C19: =IFERROR(VLOOKUP(Товары_исходные!C19,Справочники!$A$2:$B$50,2,FALSE),Товары_исходные!C19) -> Наушники | D19: =PROPER(TRIM(Товары_исходные!D19)) -> Sony | E19: =IFERROR(VALUE(IF(AND(ISNUMBER(FIND(",",Товары_исходные!E19)),ISNUMBER(FIND(".",Товары_исходные!E19))),SUBSTITUTE(SUBSTITUTE(SUBSTITUTE(SUBSTITUTE(Товары_исходные!E19," ",""),"руб.",""),"руб",""),",",""),SUBSTITUTE(SUBSTITUTE(SUBSTITUTE(SUBSTITUTE(Товары_исходные!E19," ",""),"руб.",""),"руб",""),",","."))),0) -> 18500 | F19: =IFERROR(VALUE(IF(AND(ISNUMBER(FIND(",",Товары_исходные!F19)),ISNUMBER(FIND(".",Товары_исходные!F19))),SUBSTITUTE(SUBSTITUTE(SUBSTITUTE(SUBSTITUTE(Товары_исходные!F19," ",""),"руб.",""),"руб",""),",",""),SUBSTITUTE(SUBSTITUTE(SUBSTITUTE(SUBSTITUTE(Товары_исходные!F19," ",""),"руб.",""),"руб",""),",","."))),0) -> 30500 | G19: =IFERROR(VLOOKUP(Товары_исходные!G19,Справочники!$D$2:$E$50,2,FALSE),"шт.") -> шт. | H19: =IF(F19>=E19,"OK","Розница ниже закупки") -> OK | I19: =IF(COUNTIF($A$2:$A$502,A19)=1,"OK","Дубликат") -> OK
A20: ="АРТ-"&LEFT(SUBSTITUTE(SUBSTITUTE(SUBSTITUTE(SUBSTITUTE(Товары_исходные!A20,"№",""),"АРТ-",""),"АРТ_",""),"/","-"),3) -> АРТ-019 | B20: =PROPER(TRIM(IFERROR(LEFT(Товары_исходные!B20,FIND("(",Товары_исходные!B20)-1),Товары_исходные!B20))) -> Ноутбук Lenovo Thinkpad X1 | C20: =IFERROR(VLOOKUP(Товары_исходные!C20,Справочники!$A$2:$B$50,2,FALSE),Товары_исходные!C20) -> Ноутбуки | D20: =PROPER(TRIM(Товары_исходные!D20)) -> Lenovo | E20: =IFERROR(VALUE(IF(AND(ISNUMBER(FIND(",",Товары_исходные!E20)),ISNUMBER(FIND(".",Товары_исходные!E20))),SUBSTITUTE(SUBSTITUTE(SUBSTITUTE(SUBSTITUTE(Товары_исходные!E20," ",""),"руб.",""),"руб",""),",",""),SUBSTITUTE(SUBSTITUTE(SUBSTITUTE(SUBSTITUTE(Товары_исходные!E20," ",""),"руб.",""),"руб",""),",","."))),0) -> 90000 | F20: =IFERROR(VALUE(IF(AND(ISNUMBER(FIND(",",Товары_исходные!F20)),ISNUMBER(FIND(".",Товары_исходные!F20))),SUBSTITUTE(SUBSTITUTE(SUBSTITUTE(SUBSTITUTE(Товары_исходные!F20," ",""),"руб.",""),"руб",""),",",""),SUBSTITUTE(SUBSTITUTE(SUBSTITUTE(SUBSTITUTE(Товары_исходные!F20," ",""),"руб.",""),"руб",""),",","."))),0) -> 135000 | G20: =IFERROR(VLOOKUP(Товары_исходные!G20,Справочники!$D$2:$E$50,2,FALSE),"шт.") -> шт. | H20: =IF(F20>=E20,"OK","Розница ниже закупки") -> OK | I20: =IF(COUNTIF($A$2:$A$502,A20)=1,"OK","Дубликат") -> OK
A21: ="АРТ-"&LEFT(SUBSTITUTE(SUBSTITUTE(SUBSTITUTE(SUBSTITUTE(Товары_исходные!A21,"№",""),"АРТ-",""),"АРТ_",""),"/","-"),3) -> АРТ-020 | B21: =PROPER(TRIM(IFERROR(LEFT(Товары_исходные!B21,FIND("(",Товары_исходные!B21)-1),Товары_исходные!B21))) -> Ноутбук Lenovo Thinkpad X1 | C21: =IFERROR(VLOOKUP(Товары_исходные!C21,Справочники!$A$2:$B$50,2,FALSE),Товары_исходные!C21) -> Ноутбуки | D21: =PROPER(TRIM(Товары_исходные!D21)) -> Lenovo | E21: =IFERROR(VALUE(IF(AND(ISNUMBER(FIND(",",Товары_исходные!E21)),ISNUMBER(FIND(".",Товары_исходные!E21))),SUBSTITUTE(SUBSTITUTE(SUBSTITUTE(SUBSTITUTE(Товары_исходные!E21," ",""),"руб.",""),"руб",""),",",""),SUBSTITUTE(SUBSTITUTE(SUBSTITUTE(SUBSTITUTE(Товары_исходные!E21," ",""),"руб.",""),"руб",""),",","."))),0) -> 89000 | F21: =IFERROR(VALUE(IF(AND(ISNUMBER(FIND(",",Товары_исходные!F21)),ISNUMBER(FIND(".",Товары_исходные!F21))),SUBSTITUTE(SUBSTITUTE(SUBSTITUTE(SUBSTITUTE(Товары_исходные!F21," ",""),"руб.",""),"руб",""),",",""),SUBSTITUTE(SUBSTITUTE(SUBSTITUTE(SUBSTITUTE(Товары_исходные!F21," ",""),"руб.",""),"руб",""),",","."))),0) -> 133500 | G21: =IFERROR(VLOOKUP(Товары_исходные!G21,Справочники!$D$2:$E$50,2,FALSE),"шт.") -> шт. | H21: =IF(F21>=E21,"OK","Розница ниже закупки") -> OK | I21: =IF(COUNTIF($A$2:$A$502,A21)=1,"OK","Дубликат") -> OK
A22: ="АРТ-"&LEFT(SUBSTITUTE(SUBSTITUTE(SUBSTITUTE(SUBSTITUTE(Товары_исходные!A22,"№",""),"АРТ-",""),"АРТ_",""),"/","-"),3) -> АРТ-021 | B22: =PROPER(TRIM(IFERROR(LEFT(Товары_исходные!B22,FIND("(",Товары_исходные!B22)-1),Товары_исходные!B22))) -> Ноутбук Lenovo Thinkpad X1 | C22: =IFERROR(VLOOKUP(Товары_исходные!C22,Справочники!$A$2:$B$50,2,FALSE),Товары_исходные!C22) -> Ноутбуки | D22: =PROPER(TRIM(Товары_исходные!D22)) -> Lenovo | E22: =IFERROR(VALUE(IF(AND(ISNUMBER(FIND(",",Товары_исходные!E22)),ISNUMBER(FIND(".",Товары_исходные!E22))),SUBSTITUTE(SUBSTITUTE(SUBSTITUTE(SUBSTITUTE(Товары_исходные!E22," ",""),"руб.",""),"руб",""),",",""),SUBSTITUTE(SUBSTITUTE(SUBSTITUTE(SUBSTITUTE(Товары_исходные!E22," ",""),"руб.",""),"руб",""),",","."))),0) -> 91500 | F22: =IFERROR(VALUE(IF(AND(ISNUMBER(FIND(",",Товары_исходные!F22)),ISNUMBER(FIND(".",Товары_исходные!F22))),SUBSTITUTE(SUBSTITUTE(SUBSTITUTE(SUBSTITUTE(Товары_исходные!F22," ",""),"руб.",""),"руб",""),",",""),SUBSTITUTE(SUBSTITUTE(SUBSTITUTE(SUBSTITUTE(Товары_исходные!F22," ",""),"руб.",""),"руб",""),",","."))),0) -> 137000 | G22: =IFERROR(VLOOKUP(Товары_исходные!G22,Справочники!$D$2:$E$50,2,FALSE),"шт.") -> шт. | H22: =IF(F22>=E22,"OK","Розница ниже закупки") -> OK | I22: =IF(COUNTIF($A$2:$A$502,A22)=1,"OK","Дубликат") -> OK
... A99: ="АРТ-"&LEFT(SUBSTITUTE(SUBSTITUTE(SUBSTITUTE(SUBSTITUTE(Товары_исходные!A99,"№",""),"АРТ-",""),"АРТ_",""),"/","-"),3) -> АРТ-098 | B99: =PROPER(TRIM(IFERROR(LEFT(Товары_исходные!B99,FIND("(",Товары_исходные!B99)-1),Товары_исходные!B99))) -> Мышь Razer Deathadder V3 | C99: =IFERROR(VLOOKUP(Товары_исходные!C99,Справочники!$A$2:$B$50,2,FALSE),Товары_исходные!C99) -> Аксессуары | D99: =PROPER(TRIM(Товары_исходные!D99)) -> Razer | E99: =IFERROR(VALUE(IF(AND(ISNUMBER(FIND(",",Товары_исходные!E99)),ISNUMBER(FIND(".",Товары_исходные!E99))),SUBSTITUTE(SUBSTITUTE(SUBSTITUTE(SUBSTITUTE(Товары_исходные!E99," ",""),"руб.",""),"руб",""),",",""),SUBSTITUTE(SUBSTITUTE(SUBSTITUTE(SUBSTITUTE(Товары_исходные!E99," ",""),"руб.",""),"руб",""),",","."))),0) -> 3200 | F99: =IFERROR(VALUE(IF(AND(ISNUMBER(FIND(",",Товары_исходные!F99)),ISNUMBER(FIND(".",Товары_исходные!F99))),SUBSTITUTE(SUBSTITUTE(SUBSTITUTE(SUBSTITUTE(Товары_исходные!F99," ",""),"руб.",""),"руб",""),",",""),SUBSTITUTE(SUBSTITUTE(SUBSTITUTE(SUBSTITUTE(Товары_исходные!F99," ",""),"руб.",""),"руб",""),",","."))),0) -> 6500 | G99: =IFERROR(VLOOKUP(Товары_исходные!G99,Справочники!$D$2:$E$50,2,FALSE),"шт.") -> шт. | H99: =IF(F99>=E99,"OK","Розница ниже закупки") -> OK | I99: =IF(COUNTIF($A$2:$A$502,A99)=1,"OK","Дубликат") -> OK
A100: ="АРТ-"&LEFT(SUBSTITUTE(SUBSTITUTE(SUBSTITUTE(SUBSTITUTE('Товары_исходные'!A100,"№",""),"АРТ-",""),"АРТ_",""),"/","-"),3) -> АРТ-099 | B100: =PROPER(TRIM(IFERROR(LEFT('Товары_исходные'!B100,FIND("(",'Товары_исходные'!B100)-1),'Товары_исходные'!B100))) -> Мышь Razer Deathadder V3 | C100: =IFERROR(VLOOKUP('Товары_исходные'!C100,Справочники!$A$2:$B$50,2,FALSE),'Товары_исходные'!C100) -> Аксессуары | D100: =PROPER(TRIM('Товары_исходные'!D100)) -> Razer | E100: =IFERROR(VALUE(IF(AND(ISNUMBER(FIND(",",'Товары_исходные'!E100)),ISNUMBER(FIND(".",'Товары_исходные'!E100))),SUBSTITUTE(SUBSTITUTE(SUBSTITUTE(SUBSTITUTE('Товары_исходные'!E100," ",""),"руб.",""),"руб",""),",",""),SUBSTITUTE(SUBSTITUTE(SUBSTITUTE(SUBSTITUTE('Товары_исходные'!E100," ",""),"руб.",""),"руб",""),",","."))),0) -> 3800 | F100: =IFERROR(VALUE(IF(AND(ISNUMBER(FIND(",",'Товары_исходные'!F100)),ISNUMBER(FIND(".",'Товары_исходные'!F100))),SUBSTITUTE(SUBSTITUTE(SUBSTITUTE(SUBSTITUTE('Товары_исходные'!F100," ",""),"руб.",""),"руб",""),",",""),SUBSTITUTE(SUBSTITUTE(SUBSTITUTE(SUBSTITUTE('Товары_исходные'!F100," ",""),"руб.",""),"руб",""),",","."))),0) -> 7500 | G100: =IFERROR(VLOOKUP('Товары_исходные'!G100,Справочники!$D$2:$E$50,2,FALSE),"шт.") -> шт. | H100: =IF(F100>=E100,"OK","Розница ниже закупки") -> OK | I100: =IF(COUNTIF($A$2:$A$502,A100)=1,"OK","Дубликат") -> OK
A101: ="АРТ-"&LEFT(SUBSTITUTE(SUBSTITUTE(SUBSTITUTE(SUBSTITUTE(Товары_исходные!A101,"№",""),"АРТ-",""),"АРТ_",""),"/","-"),3) -> АРТ-100 | B101: =PROPER(TRIM(IFERROR(LEFT(Товары_исходные!B101,FIND("(",Товары_исходные!B101)-1),Товары_исходные!B101))) -> Планшет Apple Ipad Mini | C101: =IFERROR(VLOOKUP(Товары_исходные!C101,Справочники!$A$2:$B$50,2,FALSE),Товары_исходные!C101) -> Планшеты | D101: =PROPER(TRIM(Товары_исходные!D101)) -> Apple | E101: =IFERROR(VALUE(IF(AND(ISNUMBER(FIND(",",Товары_исходные!E101)),ISNUMBER(FIND(".",Товары_исходные!E101))),SUBSTITUTE(SUBSTITUTE(SUBSTITUTE(SUBSTITUTE(Товары_исходные!E101," ",""),"руб.",""),"руб",""),",",""),SUBSTITUTE(SUBSTITUTE(SUBSTITUTE(SUBSTITUTE(Товары_исходные!E101," ",""),"руб.",""),"руб",""),",","."))),0) -> 35000 | F101: =IFERROR(VALUE(IF(AND(ISNUMBER(FIND(",",Товары_исходные!F101)),ISNUMBER(FIND(".",Товары_исходные!F101))),SUBSTITUTE(SUBSTITUTE(SUBSTITUTE(SUBSTITUTE(Товары_исходные!F101," ",""),"руб.",""),"руб",""),",",""),SUBSTITUTE(SUBSTITUTE(SUBSTITUTE(SUBSTITUTE(Товары_исходные!F101," ",""),"руб.",""),"руб",""),",","."))),0) -> 56990 | G101: =IFERROR(VLOOKUP(Товары_исходные!G101,Справочники!$D$2:$E$50,2,FALSE),"шт.") -> шт. | H101: =IF(F101>=E101,"OK","Розница ниже закупки") -> OK | I101: =IF(COUNTIF($A$2:$A$502,A101)=1,"OK","Дубликат") -> OK
A102: ="АРТ-"&LEFT(SUBSTITUTE(SUBSTITUTE(SUBSTITUTE(SUBSTITUTE(Товары_исходные!A102,"№",""),"АРТ-",""),"АРТ_",""),"/","-"),3) -> АРТ-101 | B102: =PROPER(TRIM(IFERROR(LEFT(Товары_исходные!B102,FIND("(",Товары_исходные!B102)-1),Товары_исходные!B102))) -> Планшет Apple Ipad Mini | C102: =IFERROR(VLOOKUP(Товары_исходные!C102,Справочники!$A$2:$B$50,2,FALSE),Товары_исходные!C102) -> Планшеты | D102: =PROPER(TRIM(Товары_исходные!D102)) -> Apple | E102: =IFERROR(VALUE(IF(AND(ISNUMBER(FIND(",",Товары_исходные!E102)),ISNUMBER(FIND(".",Товары_исходные!E102))),SUBSTITUTE(SUBSTITUTE(SUBSTITUTE(SUBSTITUTE(Товары_исходные!E102," ",""),"руб.",""),"руб",""),",",""),SUBSTITUTE(SUBSTITUTE(SUBSTITUTE(SUBSTITUTE(Товары_исходные!E102," ",""),"руб.",""),"руб",""),",","."))),0) -> 34000 | F102: =IFERROR(VALUE(IF(AND(ISNUMBER(FIND(",",Товары_исходные!F102)),ISNUMBER(FIND(".",Товары_исходные!F102))),SUBSTITUTE(SUBSTITUTE(SUBSTITUTE(SUBSTITUTE(Товары_исходные!F102," ",""),"руб.",""),"руб",""),",",""),SUBSTITUTE(SUBSTITUTE(SUBSTITUTE(SUBSTITUTE(Товары_исходные!F102," ",""),"руб.",""),"руб",""),",","."))),0) -> 55500 | G102: =IFERROR(VLOOKUP(Товары_исходные!G102,Справочники!$D$2:$E$50,2,FALSE),"шт.") -> шт. | H102: =IF(F102>=E102,"OK","Розница ниже закупки") -> OK | I102: =IF(COUNTIF($A$2:$A$502,A102)=1,"OK","Дубликат") -> OK
A103: ="АРТ-"&LEFT(SUBSTITUTE(SUBSTITUTE(SUBSTITUTE(SUBSTITUTE(Товары_исходные!A103,"№",""),"АРТ-",""),"АРТ_",""),"/","-"),3) -> АРТ-102 | B103: =PROPER(TRIM(IFERROR(LEFT(Товары_исходные!B103,FIND("(",Товары_исходные!B103)-1),Товары_исходные!B103))) -> Планшет Apple Ipad Mini | C103: =IFERROR(VLOOKUP(Товары_исходные!C103,Справочники!$A$2:$B$50,2,FALSE),Товары_исходные!C103) -> Планшеты | D103: =PROPER(TRIM(Товары_исходные!D103)) -> Apple | E103: =IFERROR(VALUE(IF(AND(ISNUMBER(FIND(",",Товары_исходные!E103)),ISNUMBER(FIND(".",Товары_исходные!E103))),SUBSTITUTE(SUBSTITUTE(SUBSTITUTE(SUBSTITUTE(Товары_исходные!E103," ",""),"руб.",""),"руб",""),",",""),SUBSTITUTE(SUBSTITUTE(SUBSTITUTE(SUBSTITUTE(Товары_исходные!E103," ",""),"руб.",""),"руб",""),",","."))),0) -> 36000 | F103: =IFERROR(VALUE(IF(AND(ISNUMBER(FIND(",",Товары_исходные!F103)),ISNUMBER(FIND(".",Товары_исходные!F103))),SUBSTITUTE(SUBSTITUTE(SUBSTITUTE(SUBSTITUTE(Товары_исходные!F103," ",""),"руб.",""),"руб",""),",",""),SUBSTITUTE(SUBSTITUTE(SUBSTITUTE(SUBSTITUTE(Товары_исходные!F103," ",""),"руб.",""),"руб",""),",","."))),0) -> 58500 | G103: =IFERROR(VLOOKUP(Товары_исходные!G103,Справочники!$D$2:$E$50,2,FALSE),"шт.") -> шт. | H103: =IF(F103>=E103,"OK","Розница ниже закупки") -> OK | I103: =IF(COUNTIF($A$2:$A$502,A103)=1,"OK","Дубликат") -> OK
A104: ="АРТ-"&LEFT(SUBSTITUTE(SUBSTITUTE(SUBSTITUTE(SUBSTITUTE(Товары_исходные!A104,"№",""),"АРТ-",""),"АРТ_",""),"/","-"),3) -> АРТ-103 | B104: =PROPER(TRIM(IFERROR(LEFT(Товары_исходные!B104,FIND("(",Товары_исходные!B104)-1),Товары_исходные!B104))) -> Ноутбук Msi Stealth 16 | C104: =IFERROR(VLOOKUP(Товары_исходные!C104,Справочники!$A$2:$B$50,2,FALSE),Товары_исходные!C104) -> Ноутбуки | D104: =PROPER(TRIM(Товары_исходные!D104)) -> Msi | E104: =IFERROR(VALUE(IF(AND(ISNUMBER(FIND(",",Товары_исходные!E104)),ISNUMBER(FIND(".",Товары_исходные!E104))),SUBSTITUTE(SUBSTITUTE(SUBSTITUTE(SUBSTITUTE(Товары_исходные!E104," ",""),"руб.",""),"руб",""),",",""),SUBSTITUTE(SUBSTITUTE(SUBSTITUTE(SUBSTITUTE(Товары_исходные!E104," ",""),"руб.",""),"руб",""),",","."))),0) -> 98000 | F104: =IFERROR(VALUE(IF(AND(ISNUMBER(FIND(",",Товары_исходные!F104)),ISNUMBER(FIND(".",Товары_исходные!F104))),SUBSTITUTE(SUBSTITUTE(SUBSTITUTE(SUBSTITUTE(Товары_исходные!F104," ",""),"руб.",""),"руб",""),",",""),SUBSTITUTE(SUBSTITUTE(SUBSTITUTE(SUBSTITUTE(Товары_исходные!F104," ",""),"руб.",""),"руб",""),",","."))),0) -> 149990 | G104: =IFERROR(VLOOKUP(Товары_исходные!G104,Справочники!$D$2:$E$50,2,FALSE),"шт.") -> шт. | H104: =IF(F104>=E104,"OK","Розница ниже закупки") -> OK | I104: =IF(COUNTIF($A$2:$A$502,A104)=1,"OK","Дубликат") -> OK
A105: ="АРТ-"&LEFT(SUBSTITUTE(SUBSTITUTE(SUBSTITUTE(SUBSTITUTE(Товары_исходные!A105,"№",""),"АРТ-",""),"АРТ_",""),"/","-"),3) -> АРТ-104 | B105: =PROPER(TRIM(IFERROR(LEFT(Товары_исходные!B105,FIND("(",Товары_исходные!B105)-1),Товары_исходные!B105))) -> Ноутбук Msi Stealth 16 | C105: =IFERROR(VLOOKUP(Товары_исходные!C105,Справочники!$A$2:$B$50,2,FALSE),Товары_исходные!C105) -> Ноутбуки | D105: =PROPER(TRIM(Товары_исходные!D105)) -> Msi | E105: =IFERROR(VALUE(IF(AND(ISNUMBER(FIND(",",Товары_исходные!E105)),ISNUMBER(FIND(".",Товары_исходные!E105))),SUBSTITUTE(SUBSTITUTE(SUBSTITUTE(SUBSTITUTE(Товары_исходные!E105," ",""),"руб.",""),"руб",""),",",""),SUBSTITUTE(SUBSTITUTE(SUBSTITUTE(SUBSTITUTE(Товары_исходные!E105," ",""),"руб.",""),"руб",""),",","."))),0) -> 96000 | F105: =IFERROR(VALUE(IF(AND(ISNUMBER(FIND(",",Товары_исходные!F105)),ISNUMBER(FIND(".",Товары_исходные!F105))),SUBSTITUTE(SUBSTITUTE(SUBSTITUTE(SUBSTITUTE(Товары_исходные!F105," ",""),"руб.",""),"руб",""),",",""),SUBSTITUTE(SUBSTITUTE(SUBSTITUTE(SUBSTITUTE(Товары_исходные!F105," ",""),"руб.",""),"руб",""),",","."))),0) -> 147000 | G105: =IFERROR(VLOOKUP(Товары_исходные!G105,Справочники!$D$2:$E$50,2,FALSE),"шт.") -> шт. | H105: =IF(F105>=E105,"OK","Розница ниже закупки") -> OK | I105: =IF(COUNTIF($A$2:$A$502,A105)=1,"OK","Дубликат") -> OK
A106: ="АРТ-"&LEFT(SUBSTITUTE(SUBSTITUTE(SUBSTITUTE(SUBSTITUTE(Товары_исходные!A106,"№",""),"АРТ-",""),"АРТ_",""),"/","-"),3) -> АРТ-105 | B106: =PROPER(TRIM(IFERROR(LEFT(Товары_исходные!B106,FIND("(",Товары_исходные!B106)-1),Товары_исходные!B106))) -> Ноутбук Msi Stealth 16 | C106: =IFERROR(VLOOKUP(Товары_исходные!C106,Справочники!$A$2:$B$50,2,FALSE),Товары_исходные!C106) -> Ноутбуки | D106: =PROPER(TRIM(Товары_исходные!D106)) -> Msi | E106: =IFERROR(VALUE(IF(AND(ISNUMBER(FIND(",",Товары_исходные!E106)),ISNUMBER(FIND(".",Товары_исходные!E106))),SUBSTITUTE(SUBSTITUTE(SUBSTITUTE(SUBSTITUTE(Товары_исходные!E106," ",""),"руб.",""),"руб",""),",",""),SUBSTITUTE(SUBSTITUTE(SUBSTITUTE(SUBSTITUTE(Товары_исходные!E106," ",""),"руб.",""),"руб",""),",","."))),0) -> 99500 | F106: =IFERROR(VALUE(IF(AND(ISNUMBER(FIND(",",Товары_исходные!F106)),ISNUMBER(FIND(".",Товары_исходные!F106))),SUBSTITUTE(SUBSTITUTE(SUBSTITUTE(SUBSTITUTE(Товары_исходные!F106," ",""),"руб.",""),"руб",""),",",""),SUBSTITUTE(SUBSTITUTE(SUBSTITUTE(SUBSTITUTE(Товары_исходные!F106," ",""),"руб.",""),"руб",""),",","."))),0) -> 152000 | G106: =IFERROR(VLOOKUP(Товары_исходные!G106,Справочники!$D$2:$E$50,2,FALSE),"шт.") -> шт. | H106: =IF(F106>=E106,"OK","Розница ниже закупки") -> OK | I106: =IF(COUNTIF($A$2:$A$502,A106)=1,"OK","Дубликат") -> OK
A107: ="АРТ-"&LEFT(SUBSTITUTE(SUBSTITUTE(SUBSTITUTE(SUBSTITUTE(Товары_исходные!A107,"№",""),"АРТ-",""),"АРТ_",""),"/","-"),3) -> АРТ-106 | B107: =PROPER(TRIM(IFERROR(LEFT(Товары_исходные!B107,FIND("(",Товары_исходные!B107)-1),Товары_исходные!B107))) -> Смартфон Realme Gt 3 | C107: =IFERROR(VLOOKUP(Товары_исходные!C107,Справочники!$A$2:$B$50,2,FALSE),Товары_исходные!C107) -> Смартфоны | D107: =PROPER(TRIM(Товары_исходные!D107)) -> Realme | E107: =IFERROR(VALUE(IF(AND(ISNUMBER(FIND(",",Товары_исходные!E107)),ISNUMBER(FIND(".",Товары_исходные!E107))),SUBSTITUTE(SUBSTITUTE(SUBSTITUTE(SUBSTITUTE(Товары_исходные!E107," ",""),"руб.",""),"руб",""),",",""),SUBSTITUTE(SUBSTITUTE(SUBSTITUTE(SUBSTITUTE(Товары_исходные!E107," ",""),"руб.",""),"руб",""),",","."))),0) -> 28000 | F107: =IFERROR(VALUE(IF(AND(ISNUMBER(FIND(",",Товары_исходные!F107)),ISNUMBER(FIND(".",Товары_исходные!F107))),SUBSTITUTE(SUBSTITUTE(SUBSTITUTE(SUBSTITUTE(Товары_исходные!F107," ",""),"руб.",""),"руб",""),",",""),SUBSTITUTE(SUBSTITUTE(SUBSTITUTE(SUBSTITUTE(Товары_исходные!F107," ",""),"руб.",""),"руб",""),",","."))),0) -> 47990 | G107: =IFERROR(VLOOKUP(Товары_исходные!G107,Справочники!$D$2:$E$50,2,FALSE),"шт.") -> шт. | H107: =IF(F107>=E107,"OK","Розница ниже закупки") -> OK | I107: =IF(COUNTIF($A$2:$A$502,A107)=1,"OK","Дубликат") -> OK
A108: ="АРТ-"&LEFT(SUBSTITUTE(SUBSTITUTE(SUBSTITUTE(SUBSTITUTE(Товары_исходные!A108,"№",""),"АРТ-",""),"АРТ_",""),"/","-"),3) -> АРТ-107 | B108: =PROPER(TRIM(IFERROR(LEFT(Товары_исходные!B108,FIND("(",Товары_исходные!B108)-1),Товары_исходные!B108))) -> Смартфон Realme Gt 3 | C108: =IFERROR(VLOOKUP(Товары_исходные!C108,Справочники!$A$2:$B$50,2,FALSE),Товары_исходные!C108) -> Смартфоны | D108: =PROPER(TRIM(Товары_исходные!D108)) -> Realme | E108: =IFERROR(VALUE(IF(AND(ISNUMBER(FIND(",",Товары_исходные!E108)),ISNUMBER(FIND(".",Товары_исходные!E108))),SUBSTITUTE(SUBSTITUTE(SUBSTITUTE(SUBSTITUTE(Товары_исходные!E108," ",""),"руб.",""),"руб",""),",",""),SUBSTITUTE(SUBSTITUTE(SUBSTITUTE(SUBSTITUTE(Товары_исходные!E108," ",""),"руб.",""),"руб",""),",","."))),0) -> 27000 | F108: =IFERROR(VALUE(IF(AND(ISNUMBER(FIND(",",Товары_исходные!F108)),ISNUMBER(FIND(".",Товары_исходные!F108))),SUBSTITUTE(SUBSTITUTE(SUBSTITUTE(SUBSTITUTE(Товары_исходные!F108," ",""),"руб.",""),"руб",""),",",""),SUBSTITUTE(SUBSTITUTE(SUBSTITUTE(SUBSTITUTE(Товары_исходные!F108," ",""),"руб.",""),"руб",""),",","."))),0) -> 46500 | G108: =IFERROR(VLOOKUP(Товары_исходные!G108,Справочники!$D$2:$E$50,2,FALSE),"шт.") -> шт. | H108: =IF(F108>=E108,"OK","Розница ниже закупки") -> OK | I108: =IF(COUNTIF($A$2:$A$502,A108)=1,"OK","Дубликат") -> OK
A109: ="АРТ-"&LEFT(SUBSTITUTE(SUBSTITUTE(SUBSTITUTE(SUBSTITUTE(Товары_исходные!A109,"№",""),"АРТ-",""),"АРТ_",""),"/","-"),3) -> АРТ-108 | B109: =PROPER(TRIM(IFERROR(LEFT(Товары_исходные!B109,FIND("(",Товары_исходные!B109)-1),Товары_исходные!B109))) -> Смартфон Realme Gt 3 | C109: =IFERROR(VLOOKUP(Товары_исходные!C109,Справочники!$A$2:$B$50,2,FALSE),Товары_исходные!C109) -> Смартфоны | D109: =PROPER(TRIM(Товары_исходные!D109)) -> Realme | E109: =IFERROR(VALUE(IF(AND(ISNUMBER(FIND(",",Товары_исходные!E109)),ISNUMBER(FIND(".",Товары_исходные!E109))),SUBSTITUTE(SUBSTITUTE(SUBSTITUTE(SUBSTITUTE(Товары_исходные!E109," ",""),"руб.",""),"руб",""),",",""),SUBSTITUTE(SUBSTITUTE(SUBSTITUTE(SUBSTITUTE(Товары_исходные!E109," ",""),"руб.",""),"руб",""),",","."))),0) -> 29000 | F109: =IFERROR(VALUE(IF(AND(ISNUMBER(FIND(",",Товары_исходные!F109)),ISNUMBER(FIND(".",Товары_исходные!F109))),SUBSTITUTE(SUBSTITUTE(SUBSTITUTE(SUBSTITUTE(Товары_исходные!F109," ",""),"руб.",""),"руб",""),",",""),SUBSTITUTE(SUBSTITUTE(SUBSTITUTE(SUBSTITUTE(Товары_исходные!F109," ",""),"руб.",""),"руб",""),",","."))),0) -> 49500 | G109: =IFERROR(VLOOKUP(Товары_исходные!G109,Справочники!$D$2:$E$50,2,FALSE),"шт.") -> шт. | H109: =IF(F109>=E109,"OK","Розница ниже закупки") -> OK | I109: =IF(COUNTIF($A$2:$A$502,A109)=1,"OK","Дубликат") -> OK
A110: ="АРТ-"&LEFT(SUBSTITUTE(SUBSTITUTE(SUBSTITUTE(SUBSTITUTE(Товары_исходные!A110,"№",""),"АРТ-",""),"АРТ_",""),"/","-"),3) -> АРТ-109 | B110: =PROPER(TRIM(IFERROR(LEFT(Товары_исходные!B110,FIND("(",Товары_исходные!B110)-1),Товары_исходные!B110))) -> Телевизор Hisense U8K | C110: =IFERROR(VLOOKUP(Товары_исходные!C110,Справочники!$A$2:$B$50,2,FALSE),Товары_исходные!C110) -> Телевизоры | D110: =PROPER(TRIM(Товары_исходные!D110)) -> Hisense | E110: =IFERROR(VALUE(IF(AND(ISNUMBER(FIND(",",Товары_исходные!E110)),ISNUMBER(FIND(".",Товары_исходные!E110))),SUBSTITUTE(SUBSTITUTE(SUBSTITUTE(SUBSTITUTE(Товары_исходные!E110," ",""),"руб.",""),"руб",""),",",""),SUBSTITUTE(SUBSTITUTE(SUBSTITUTE(SUBSTITUTE(Товары_исходные!E110," ",""),"руб.",""),"руб",""),",","."))),0) -> 78000 | F110: =IFERROR(VALUE(IF(AND(ISNUMBER(FIND(",",Товары_исходные!F110)),ISNUMBER(FIND(".",Товары_исходные!F110))),SUBSTITUTE(SUBSTITUTE(SUBSTITUTE(SUBSTITUTE(Товары_исходные!F110," ",""),"руб.",""),"руб",""),",",""),SUBSTITUTE(SUBSTITUTE(SUBSTITUTE(SUBSTITUTE(Товары_исходные!F110," ",""),"руб.",""),"руб",""),",","."))),0) -> 119999 | G110: =IFERROR(VLOOKUP(Товары_исходные!G110,Справочники!$D$2:$E$50,2,FALSE),"шт.") -> шт. | H110: =IF(F110>=E110,"OK","Розница ниже закупки") -> OK | I110: =IF(COUNTIF($A$2:$A$502,A110)=1,"OK","Дубликат") -> OK
A111: ="АРТ-"&LEFT(SUBSTITUTE(SUBSTITUTE(SUBSTITUTE(SUBSTITUTE(Товары_исходные!A111,"№",""),"АРТ-",""),"АРТ_",""),"/","-"),3) -> АРТ-110 | B111: =PROPER(TRIM(IFERROR(LEFT(Товары_исходные!B111,FIND("(",Товары_исходные!B111)-1),Товары_исходные!B111))) -> Телевизор Hisense U8K | C111: =IFERROR(VLOOKUP(Товары_исходные!C111,Справочники!$A$2:$B$50,2,FALSE),Товары_исходные!C111) -> Телевизоры | D111: =PROPER(TRIM(Товары_исходные!D111)) -> Hisense | E111: =IFERROR(VALUE(IF(AND(ISNUMBER(FIND(",",Товары_исходные!E111)),ISNUMBER(FIND(".",Товары_исходные!E111))),SUBSTITUTE(SUBSTITUTE(SUBSTITUTE(SUBSTITUTE(Товары_исходные!E111," ",""),"руб.",""),"руб",""),",",""),SUBSTITUTE(SUBSTITUTE(SUBSTITUTE(SUBSTITUTE(Товары_исходные!E111," ",""),"руб.",""),"руб",""),",","."))),0) -> 76000 | F111: =IFERROR(VALUE(IF(AND(ISNUMBER(FIND(",",Товары_исходные!F111)),ISNUMBER(FIND(".",Товары_исходные!F111))),SUBSTITUTE(SUBSTITUTE(SUBSTITUTE(SUBSTITUTE(Товары_исходные!F111," ",""),"руб.",""),"руб",""),",",""),SUBSTITUTE(SUBSTITUTE(SUBSTITUTE(SUBSTITUTE(Товары_исходные!F111," ",""),"руб.",""),"руб",""),",","."))),0) -> 117000 | G111: =IFERROR(VLOOKUP(Товары_исходные!G111,Справочники!$D$2:$E$50,2,FALSE),"шт.") -> шт. | H111: =IF(F111>=E111,"OK","Розница ниже закупки") -> OK | I111: =IF(COUNTIF($A$2:$A$502,A111)=1,"OK","Дубликат") -> OK
A112: ="АРТ-"&LEFT(SUBSTITUTE(SUBSTITUTE(SUBSTITUTE(SUBSTITUTE(Товары_исходные!A112,"№",""),"АРТ-",""),"АРТ_",""),"/","-"),3) -> АРТ-111 | B112: =PROPER(TRIM(IFERROR(LEFT(Товары_исходные!B112,FIND("(",Товары_исходные!B112)-1),Товары_исходные!B112))) -> Телевизор Hisense U8K | C112: =IFERROR(VLOOKUP(Товары_исходные!C112,Справочники!$A$2:$B$50,2,FALSE),Товары_исходные!C112) -> Телевизоры | D112: =PROPER(TRIM(Товары_исходные!D112)) -> Hisense | E112: =IFERROR(VALUE(IF(AND(ISNUMBER(FIND(",",Товары_исходные!E112)),ISNUMBER(FIND(".",Товары_исходные!E112))),SUBSTITUTE(SUBSTITUTE(SUBSTITUTE(SUBSTITUTE(Товары_исходные!E112," ",""),"руб.",""),"руб",""),",",""),SUBSTITUTE(SUBSTITUTE(SUBSTITUTE(SUBSTITUTE(Товары_исходные!E112," ",""),"руб.",""),"руб",""),",","."))),0) -> 79500 | F112: =IFERROR(VALUE(IF(AND(ISNUMBER(FIND(",",Товары_исходные!F112)),ISNUMBER(FIND(".",Товары_исходные!F112))),SUBSTITUTE(SUBSTITUTE(SUBSTITUTE(SUBSTITUTE(Товары_исходные!F112," ",""),"руб.",""),"руб",""),",",""),SUBSTITUTE(SUBSTITUTE(SUBSTITUTE(SUBSTITUTE(Товары_исходные!F112," ",""),"руб.",""),"руб",""),",","."))),0) -> 122500 | G112: =IFERROR(VLOOKUP(Товары_исходные!G112,Справочники!$D$2:$E$50,2,FALSE),"шт.") -> шт. | H112: =IF(F112>=E112,"OK","Розница ниже закупки") -> OK | I112: =IF(COUNTIF($A$2:$A$502,A112)=1,"OK","Дубликат") -> OK
... A502: ="АРТ-"&LEFT(SUBSTITUTE(SUBSTITUTE(SUBSTITUTE(SUBSTITUTE(Товары_исходные!A502,"№",""),"АРТ-",""),"АРТ_",""),"/","-"),3) -> АРТ-501 | B502: =PROPER(TRIM(IFERROR(LEFT(Товары_исходные!B502,FIND("(",Товары_исходные!B502)-1),Товары_исходные!B502))) -> Клавиатура Logitech Pop Keys | C502: =IFERROR(VLOOKUP(Товары_исходные!C502,Справочники!$A$2:$B$50,2,FALSE),Товары_исходные!C502) -> Аксессуары | D502: =PROPER(TRIM(Товары_исходные!D502)) -> Logitech | E502: =IFERROR(VALUE(IF(AND(ISNUMBER(FIND(",",Товары_исходные!E502)),ISNUMBER(FIND(".",Товары_исходные!E502))),SUBSTITUTE(SUBSTITUTE(SUBSTITUTE(SUBSTITUTE(Товары_исходные!E502," ",""),"руб.",""),"руб",""),",",""),SUBSTITUTE(SUBSTITUTE(SUBSTITUTE(SUBSTITUTE(Товары_исходные!E502," ",""),"руб.",""),"руб",""),",","."))),0) -> 4000 | F502: =IFERROR(VALUE(IF(AND(ISNUMBER(FIND(",",Товары_исходные!F502)),ISNUMBER(FIND(".",Товары_исходные!F502))),SUBSTITUTE(SUBSTITUTE(SUBSTITUTE(SUBSTITUTE(Товары_исходные!F502," ",""),"руб.",""),"руб",""),",",""),SUBSTITUTE(SUBSTITUTE(SUBSTITUTE(SUBSTITUTE(Товары_исходные!F502," ",""),"руб.",""),"руб",""),",","."))),0) -> 6800 | G502: =IFERROR(VLOOKUP(Товары_исходные!G502,Справочники!$D$2:$E$50,2,FALSE),"шт.") -> шт. | H502: =IF(F502>=E502,"OK","Розница ниже закупки") -> OK | I502: =IF(COUNTIF($A$2:$A$502,A502)=1,"OK","Дубликат") -> OK

Sheet Поставщики_исходные
A1: ID_поставщика | B1: Название | C1: ИНН | D1: КПП | E1: Телефон | F1: Email | G1: Адрес
A2: P001 | B2: ООО ТехноСнаб | C2: 7708123456 | D2: 770801001 | E2: 8-903-123-45-67 | F2: info@tehnosnab.ru | G2: 125009 г.Москва ул.Тверская д.15
A3: P002 | B3: ЗАО ЭлектроПром | C3: 7812345678123 | D3: 781201001 | E3: +7 903 234-56-78 | F3: zakaz@electroprom | G3: 191186 г.Санкт-Петербург Невский пр.д.28
A4: P003 | B4: ООО КомплектСервис | C4: 77098765 | D4: 770901001 | E4: 8 903 345 67 89 | F4: komplekt@mail.ru | G4: 127006 г.Москва ул.Петровка д.20
A5: P004 | B5: АО ТехноИмпорт | C5: 7712345678 | D5: 771001001 | E5: +79034567890 | F5: import@techno | G5: 119019 г.Москва ул.Арбат д.12
A6: P005 | B6: ООО ТоргМастер | C6: 7801234567890 | D6: 780101001 | E6: 8-903-567-89-01 | F6: torg@master | G6: 192007 г.Санкт-Петербург пр.Обуховской Обороны д.120
A7: P006 | B7: ЗАО Техноресурс | C7: 77134567 | D7: 771101001 | E7: 8-903-678-90-12 | F7: resurs@techno.ru | G7: 119121 г.Москва ул.Плющиха д.25
A8: P007 | B8: ООО ПрогрессПлюс | C8: 7802345678 | D8: 780201001 | E8: +7 903 789-01-23 | F8: progress@mail | G8: 197022 г.Санкт-Петербург ул.Профессора Попова д.37
A9: P008 | B9: АО ЭлектронСбыт | C9: 771456789012 | D9: 771201001 | E9: 8-903-890-12-34 | F9: electron@sbyt | G9: 109316 г.Москва ул.Таганская д.54
A10: P009 | B10: ООО СмартТех | C10: 7803456789 | D10: 780301001 | E10: +79039012345 | F10: smart@tech | G10: 196084 г.Санкт-Петербург ул.Заставская д.22
A11: P010 | B11: ЗАО ТехноПром | C11: 7715678901 | D11: 771301001 | E11: 8-903-012-34-56 | F11: prom@tehno | G11: 119334 г.Москва ул.Косыгина д.17
A12: P011 | B12: ООО СервисПлюс | C12: 78045678 | D12: 780401001 | E12: 8-903-123-45-67 | F12: service@plus.ru | G12: 199178 г.Санкт-Петербург ул.Средний пр.В.О.д.78
... A51: P050 | B51: ЗАО ТехноПроект | C51: 7735678901 | D51: 773301001 | E51: 8-903-012-34-56 | F51: proekt@tehno | G51: 119435 г.Москва ул.Погодинская д.18

Sheet Поставщики_очищенные
A1: ID_поставщика | B1: Название | C1: ИНН | D1: КПП | E1: Телефон | F1: Email | G1: Адрес | H1: Индекс | I1: Адрес_остаток | J1: Проверка_ИНН | K1: Проверка_Email
A2: ='Поставщики_исходные'!A2 -> P001 | B2: =PROPER(TRIM('Поставщики_исходные'!B2)) -> Ооо Техноснаб | C2: =IF(ISBLANK(Поставщики_исходные!C2),"",TRIM(Поставщики_исходные!C2)) -> 7708123456 | D2: ='Поставщики_исходные'!D2 -> 770801001 | E2: =IF(ISBLANK(Поставщики_исходные!E2),"",IF(LEN(SUBSTITUTE(SUBSTITUTE(SUBSTITUTE(SUBSTITUTE(SUBSTITUTE(Поставщики_исходные!E2," ",""),"-",""),"+",""),"(",""),")",""))=11,"+7 ("&MID(IF(LEFT(SUBSTITUTE(SUBSTITUTE(SUBSTITUTE(SUBSTITUTE(SUBSTITUTE(Поставщики_исходные!E2," ",""),"-",""),"+",""),"(",""),")",""))="8","7"&MID(SUBSTITUTE(SUBSTITUTE(SUBSTITUTE(SUBSTITUTE(SUBSTITUTE(Поставщики_исходные!E2," ",""),"-",""),"+",""),"(",""),")",""),2,10),SUBSTITUTE(SUBSTITUTE(SUBSTITUTE(SUBSTITUTE(SUBSTITUTE(Поставщики_исходные!E2," ",""),"-",""),"+",""),"(",""),")","")),2,3)&") "&MID(IF(LEFT(SUBSTITUTE(SUBSTITUTE(SUBSTITUTE(SUBSTITUTE(SUBSTITUTE(Поставщики_исходные!E2," ",""),"-",""),"+",""),"(",""),")",""))="8","7"&MID(SUBSTITUTE(SUBSTITUTE(SUBSTITUTE(SUBSTITUTE(SUBSTITUTE(Поставщики_исходные!E2," ",""),"-",""),"+",""),"(",""),")",""),2,10),SUBSTITUTE(SUBSTITUTE(SUBSTITUTE(SUBSTITUTE(SUBSTITUTE(Поставщики_исходные!E2," ",""),"-",""),"+",""),"(",""),")","")),5,3)&"-"&MID(IF(LEFT(SUBSTITUTE(SUBSTITUTE(SUBSTITUTE(SUBSTITUTE(SUBSTITUTE(Поставщики_исходные!E2," ",""),"-",""),"+",""),"(",""),")",""))="8","7"&MID(SUBSTITUTE(SUBSTITUTE(SUBSTITUTE(SUBSTITUTE(SUBSTITUTE(Поставщики_исходные!E2," ",""),"-",""),"+",""),"(",""),")",""),2,10),SUBSTITUTE(SUBSTITUTE(SUBSTITUTE(SUBSTITUTE(SUBSTITUTE(Поставщики_исходные!E2," ",""),"-",""),"+",""),"(",""),")","")),8,2)&"-"&MID(IF(LEFT(SUBSTITUTE(SUBSTITUTE(SUBSTITUTE(SUBSTITUTE(SUBSTITUTE(Поставщики_исходные!E2," ",""),"-",""),"+",""),"(",""),")",""))="8","7"&MID(SUBSTITUTE(SUBSTITUTE(SUBSTITUTE(SUBSTITUTE(SUBSTITUTE(Поставщики_исходные!E2," ",""),"-",""),"+",""),"(",""),")",""),2,10),SUBSTITUTE(SUBSTITUTE(SUBSTITUTE(SUBSTITUTE(SUBSTITUTE(Поставщики_исходные!E2," ",""),"-",""),"+",""),"(",""),")","")),10,2),IF(LEN(SUBSTITUTE(SUBSTITUTE(SUBSTITUTE(SUBSTITUTE(SUBSTITUTE(Поставщики_исходные!E2," ",""),"-",""),"+",""),"(",""),")",""))=10,"+7 ("&MID(SUBSTITUTE(SUBSTITUTE(SUBSTITUTE(SUBSTITUTE(SUBSTITUTE(Поставщики_исходные!E2," ",""),"-",""),"+",""),"(",""),")",""),1,3)&") "&MID(SUBSTITUTE(SUBSTITUTE(SUBSTITUTE(SUBSTITUTE(SUBSTITUTE(Поставщики_исходные!E2," ",""),"-",""),"+",""),"(",""),")",""),4,3)&"-"&MID(SUBSTITUTE(SUBSTITUTE(SUBSTITUTE(SUBSTITUTE(SUBSTITUTE(Поставщики_исходные!E2," ",""),"-",""),"+",""),"(",""),")",""),6,2)&"-"&MID(SUBSTITUTE(SUBSTITUTE(SUBSTITUTE(SUBSTITUTE(SUBSTITUTE(Поставщики_исходные!E2," ",""),"-",""),"+",""),"(",""),")",""),8,2),Поставщики_исходные!E2))) -> +7 (903) 123-45-67 | F2: =IF(ISBLANK(Поставщики_исходные!F2),"",IF(ISNUMBER(FIND(".",MID(Поставщики_исходные!F2,FIND("@",Поставщики_исходные!F2)+1,255))),Поставщики_исходные!F2,IF(ISNUMBER(FIND("gmail",Поставщики_исходные!F2)),Поставщики_исходные!F2&".com",Поставщики_исходные!F2&".ru"))) -> info@tehnosnab.ru | G2: =TRIM('Поставщики_исходные'!G2) -> 125009 г.Москва ул.Тверская д.15 | H2: =IF(ISNUMBER(VALUE(LEFT(TRIM('Поставщики_исходные'!G2),6))),LEFT(TRIM('Поставщики_исходные'!G2),6),"") -> 125009 | I2: =TRIM(MID(TRIM('Поставщики_исходные'!G2),7,255)) -> г.Москва ул.Тверская д.15 | J2: =IF(OR(LEN(C2)=10,LEN(C2)=12),"OK","Ошибка ИНН") -> OK | K2: =IF(ISBLANK(Поставщики_исходные!F2),"",IF(ISNUMBER(FIND(".",MID(Поставщики_исходные!F2,FIND("@",Поставщики_исходные!F2)+1,255))),Поставщики_исходные!F2,IF(ISNUMBER(FIND("gmail",Поставщики_исходные!F2)),Поставщики_исходные!F2&".com",Поставщики_исходные!F2&".ru"))) -> info@tehnosnab.ru
A3: =Поставщики_исходные!A3 -> P002 | B3: =PROPER(TRIM(Поставщики_исходные!B3)) -> Зао Электропром | C3: =IF(ISBLANK(Поставщики_исходные!C3),"",TRIM(Поставщики_исходные!C3)) -> 7812345678123 | D3: =Поставщики_исходные!D3 -> 781201001 | E3: =IF(ISBLANK(Поставщики_исходные!E3),"",IF(LEN(SUBSTITUTE(SUBSTITUTE(SUBSTITUTE(SUBSTITUTE(SUBSTITUTE(Поставщики_исходные!E3," ",""),"-",""),"+",""),"(",""),")",""))=11,"+7 ("&MID(IF(LEFT(SUBSTITUTE(SUBSTITUTE(SUBSTITUTE(SUBSTITUTE(SUBSTITUTE(Поставщики_исходные!E3," ",""),"-",""),"+",""),"(",""),")",""))="8","7"&MID(SUBSTITUTE(SUBSTITUTE(SUBSTITUTE(SUBSTITUTE(SUBSTITUTE(Поставщики_исходные!E3," ",""),"-",""),"+",""),"(",""),")",""),2,10),SUBSTITUTE(SUBSTITUTE(SUBSTITUTE(SUBSTITUTE(SUBSTITUTE(Поставщики_исходные!E3," ",""),"-",""),"+",""),"(",""),")","")),2,3)&") "&MID(IF(LEFT(SUBSTITUTE(SUBSTITUTE(SUBSTITUTE(SUBSTITUTE(SUBSTITUTE(Поставщики_исходные!E3," ",""),"-",""),"+",""),"(",""),")",""))="8","7"&MID(SUBSTITUTE(SUBSTITUTE(SUBSTITUTE(SUBSTITUTE(SUBSTITUTE(Поставщики_исходные!E3," ",""),"-",""),"+",""),"(",""),")",""),2,10),SUBSTITUTE(SUBSTITUTE(SUBSTITUTE(SUBSTITUTE(SUBSTITUTE(Поставщики_исходные!E3," ",""),"-",""),"+",""),"(",""),")","")),5,3)&"-"&MID(IF(LEFT(SUBSTITUTE(SUBSTITUTE(SUBSTITUTE(SUBSTITUTE(SUBSTITUTE(Поставщики_исходные!E3," ",""),"-",""),"+",""),"(",""),")",""))="8","7"&MID(SUBSTITUTE(SUBSTITUTE(SUBSTITUTE(SUBSTITUTE(SUBSTITUTE(Поставщики_исходные!E3," ",""),"-",""),"+",""),"(",""),")",""),2,10),SUBSTITUTE(SUBSTITUTE(SUBSTITUTE(SUBSTITUTE(SUBSTITUTE(Поставщики_исходные!E3," ",""),"-",""),"+",""),"(",""),")","")),8,2)&"-"&MID(IF(LEFT(SUBSTITUTE(SUBSTITUTE(SUBSTITUTE(SUBSTITUTE(SUBSTITUTE(Поставщики_исходные!E3," ",""),"-",""),"+",""),"(",""),")",""))="8","7"&MID(SUBSTITUTE(SUBSTITUTE(SUBSTITUTE(SUBSTITUTE(SUBSTITUTE(Поставщики_исходные!E3," ",""),"-",""),"+",""),"(",""),")",""),2,10),SUBSTITUTE(SUBSTITUTE(SUBSTITUTE(SUBSTITUTE(SUBSTITUTE(Поставщики_исходные!E3," ",""),"-",""),"+",""),"(",""),")","")),10,2),IF(LEN(SUBSTITUTE(SUBSTITUTE(SUBSTITUTE(SUBSTITUTE(SUBSTITUTE(Поставщики_исходные!E3," ",""),"-",""),"+",""),"(",""),")",""))=10,"+7 ("&MID(SUBSTITUTE(SUBSTITUTE(SUBSTITUTE(SUBSTITUTE(SUBSTITUTE(Поставщики_исходные!E3," ",""),"-",""),"+",""),"(",""),")",""),1,3)&") "&MID(SUBSTITUTE(SUBSTITUTE(SUBSTITUTE(SUBSTITUTE(SUBSTITUTE(Поставщики_исходные!E3," ",""),"-",""),"+",""),"(",""),")",""),4,3)&"-"&MID(SUBSTITUTE(SUBSTITUTE(SUBSTITUTE(SUBSTITUTE(SUBSTITUTE(Поставщики_исходные!E3," ",""),"-",""),"+",""),"(",""),")",""),6,2)&"-"&MID(SUBSTITUTE(SUBSTITUTE(SUBSTITUTE(SUBSTITUTE(SUBSTITUTE(Поставщики_исходные!E3," ",""),"-",""),"+",""),"(",""),")",""),8,2),Поставщики_исходные!E3))) -> +7 (903) 234-56-78 | F3: =IF(ISBLANK(Поставщики_исходные!F3),"",IF(ISNUMBER(FIND(".",MID(Поставщики_исходные!F3,FIND("@",Поставщики_исходные!F3)+1,255))),Поставщики_исходные!F3,IF(ISNUMBER(FIND("gmail",Поставщики_исходные!F3)),Поставщики_исходные!F3&".com",Поставщики_исходные!F3&".ru"))) -> zakaz@electroprom.ru | G3: =TRIM(Поставщики_исходные!G3) -> 191186 г.Санкт-Петербург Невский пр.д.28 | H3: =IF(ISNUMBER(VALUE(LEFT(TRIM(Поставщики_исходные!G3),6))),LEFT(TRIM(Поставщики_исходные!G3),6),"") -> 191186 | I3: =TRIM(MID(TRIM(Поставщики_исходные!G3),7,255)) -> г.Санкт-Петербург Невский пр.д.28 | J3: =IF(OR(LEN(C3)=10,LEN(C3)=12),"OK","Ошибка ИНН") -> Ошибка ИНН | K3: =IF(AND(ISNUMBER(FIND("@",F3)),ISNUMBER(FIND(".",MID(F3,FIND("@",F3)+1,255)))),"OK","Ошибка Email") -> OK
A4: =Поставщики_исходные!A4 -> P003 | B4: =PROPER(TRIM(Поставщики_исходные!B4)) -> Ооо Комплектсервис | C4: =IF(ISBLANK(Поставщики_исходные!C4),"",TRIM(Поставщики_исходные!C4)) -> 77098765 | D4: =Поставщики_исходные!D4 -> 770901001 | E4: =IF(ISBLANK(Поставщики_исходные!E4),"",IF(LEN(SUBSTITUTE(SUBSTITUTE(SUBSTITUTE(SUBSTITUTE(SUBSTITUTE(Поставщики_исходные!E4," ",""),"-",""),"+",""),"(",""),")",""))=11,"+7 ("&MID(IF(LEFT(SUBSTITUTE(SUBSTITUTE(SUBSTITUTE(SUBSTITUTE(SUBSTITUTE(Поставщики_исходные!E4," ",""),"-",""),"+",""),"(",""),")",""))="8","7"&MID(SUBSTITUTE(SUBSTITUTE(SUBSTITUTE(SUBSTITUTE(SUBSTITUTE(Поставщики_исходные!E4," ",""),"-",""),"+",""),"(",""),")",""),2,10),SUBSTITUTE(SUBSTITUTE(SUBSTITUTE(SUBSTITUTE(SUBSTITUTE(Поставщики_исходные!E4," ",""),"-",""),"+",""),"(",""),")","")),2,3)&") "&MID(IF(LEFT(SUBSTITUTE(SUBSTITUTE(SUBSTITUTE(SUBSTITUTE(SUBSTITUTE(Поставщики_исходные!E4," ",""),"-",""),"+",""),"(",""),")",""))="8","7"&MID(SUBSTITUTE(SUBSTITUTE(SUBSTITUTE(SUBSTITUTE(SUBSTITUTE(Поставщики_исходные!E4," ",""),"-",""),"+",""),"(",""),")",""),2,10),SUBSTITUTE(SUBSTITUTE(SUBSTITUTE(SUBSTITUTE(SUBSTITUTE(Поставщики_исходные!E4," ",""),"-",""),"+",""),"(",""),")","")),5,3)&"-"&MID(IF(LEFT(SUBSTITUTE(SUBSTITUTE(SUBSTITUTE(SUBSTITUTE(SUBSTITUTE(Поставщики_исходные!E4," ",""),"-",""),"+",""),"(",""),")",""))="8","7"&MID(SUBSTITUTE(SUBSTITUTE(SUBSTITUTE(SUBSTITUTE(SUBSTITUTE(Поставщики_исходные!E4," ",""),"-",""),"+",""),"(",""),")",""),2,10),SUBSTITUTE(SUBSTITUTE(SUBSTITUTE(SUBSTITUTE(SUBSTITUTE(Поставщики_исходные!E4," ",""),"-",""),"+",""),"(",""),")","")),8,2)&"-"&MID(IF(LEFT(SUBSTITUTE(SUBSTITUTE(SUBSTITUTE(SUBSTITUTE(SUBSTITUTE(Поставщики_исходные!E4," ",""),"-",""),"+",""),"(",""),")",""))="8","7"&MID(SUBSTITUTE(SUBSTITUTE(SUBSTITUTE(SUBSTITUTE(SUBSTITUTE(Поставщики_исходные!E4," ",""),"-",""),"+",""),"(",""),")",""),2,10),SUBSTITUTE(SUBSTITUTE(SUBSTITUTE(SUBSTITUTE(SUBSTITUTE(Поставщики_исходные!E4," ",""),"-",""),"+",""),"(",""),")","")),10,2),IF(LEN(SUBSTITUTE(SUBSTITUTE(SUBSTITUTE(SUBSTITUTE(SUBSTITUTE(Поставщики_исходные!E4," ",""),"-",""),"+",""),"(",""),")",""))=10,"+7 ("&MID(SUBSTITUTE(SUBSTITUTE(SUBSTITUTE(SUBSTITUTE(SUBSTITUTE(Поставщики_исходные!E4," ",""),"-",""),"+",""),"(",""),")",""),1,3)&") "&MID(SUBSTITUTE(SUBSTITUTE(SUBSTITUTE(SUBSTITUTE(SUBSTITUTE(Поставщики_исходные!E4," ",""),"-",""),"+",""),"(",""),")",""),4,3)&"-"&MID(SUBSTITUTE(SUBSTITUTE(SUBSTITUTE(SUBSTITUTE(SUBSTITUTE(Поставщики_исходные!E4," ",""),"-",""),"+",""),"(",""),")",""),6,2)&"-"&MID(SUBSTITUTE(SUBSTITUTE(SUBSTITUTE(SUBSTITUTE(SUBSTITUTE(Поставщики_исходные!E4," ",""),"-",""),"+",""),"(",""),")",""),8,2),Поставщики_исходные!E4))) -> +7 (903) 345-67-89 | F4: =IF(ISBLANK(Поставщики_исходные!F4),"",IF(ISNUMBER(FIND(".",MID(Поставщики_исходные!F4,FIND("@",Поставщики_исходные!F4)+1,255))),Поставщики_исходные!F4,IF(ISNUMBER(FIND("gmail",Поставщики_исходные!F4)),Поставщики_исходные!F4&".com",Поставщики_исходные!F4&".ru"))) -> komplekt@mail.ru | G4: =TRIM(Поставщики_исходные!G4) -> 127006 г.Москва ул.Петровка д.20 | H4: =IF(ISNUMBER(VALUE(LEFT(TRIM(Поставщики_исходные!G4),6))),LEFT(TRIM(Поставщики_исходные!G4),6),"") -> 127006 | I4: =TRIM(MID(TRIM(Поставщики_исходные!G4),7,255)) -> г.Москва ул.Петровка д.20 | J4: =IF(OR(LEN(C4)=10,LEN(C4)=12),"OK","Ошибка ИНН") -> Ошибка ИНН | K4: =IF(AND(ISNUMBER(FIND("@",F4)),ISNUMBER(FIND(".",MID(F4,FIND("@",F4)+1,255)))),"OK","Ошибка Email") -> OK
A5: =Поставщики_исходные!A5 -> P004 | B5: =PROPER(TRIM(Поставщики_исходные!B5)) -> Ао Техноимпорт | C5: =IF(ISBLANK(Поставщики_исходные!C5),"",TRIM(Поставщики_исходные!C5)) -> 7712345678 | D5: =Поставщики_исходные!D5 -> 771001001 | E5: =IF(ISBLANK(Поставщики_исходные!E5),"",IF(LEN(SUBSTITUTE(SUBSTITUTE(SUBSTITUTE(SUBSTITUTE(SUBSTITUTE(Поставщики_исходные!E5," ",""),"-",""),"+",""),"(",""),")",""))=11,"+7 ("&MID(IF(LEFT(SUBSTITUTE(SUBSTITUTE(SUBSTITUTE(SUBSTITUTE(SUBSTITUTE(Поставщики_исходные!E5," ",""),"-",""),"+",""),"(",""),")",""))="8","7"&MID(SUBSTITUTE(SUBSTITUTE(SUBSTITUTE(SUBSTITUTE(SUBSTITUTE(Поставщики_исходные!E5," ",""),"-",""),"+",""),"(",""),")",""),2,10),SUBSTITUTE(SUBSTITUTE(SUBSTITUTE(SUBSTITUTE(SUBSTITUTE(Поставщики_исходные!E5," ",""),"-",""),"+",""),"(",""),")","")),2,3)&") "&MID(IF(LEFT(SUBSTITUTE(SUBSTITUTE(SUBSTITUTE(SUBSTITUTE(SUBSTITUTE(Поставщики_исходные!E5," ",""),"-",""),"+",""),"(",""),")",""))="8","7"&MID(SUBSTITUTE(SUBSTITUTE(SUBSTITUTE(SUBSTITUTE(SUBSTITUTE(Поставщики_исходные!E5," ",""),"-",""),"+",""),"(",""),")",""),2,10),SUBSTITUTE(SUBSTITUTE(SUBSTITUTE(SUBSTITUTE(SUBSTITUTE(Поставщики_исходные!E5," ",""),"-",""),"+",""),"(",""),")","")),5,3)&"-"&MID(IF(LEFT(SUBSTITUTE(SUBSTITUTE(SUBSTITUTE(SUBSTITUTE(SUBSTITUTE(Поставщики_исходные!E5," ",""),"-",""),"+",""),"(",""),")",""))="8","7"&MID(SUBSTITUTE(SUBSTITUTE(SUBSTITUTE(SUBSTITUTE(SUBSTITUTE(Поставщики_исходные!E5," ",""),"-",""),"+",""),"(",""),")",""),2,10),SUBSTITUTE(SUBSTITUTE(SUBSTITUTE(SUBSTITUTE(SUBSTITUTE(Поставщики_исходные!E5," ",""),"-",""),"+",""),"(",""),")","")),8,2)&"-"&MID(IF(LEFT(SUBSTITUTE(SUBSTITUTE(SUBSTITUTE(SUBSTITUTE(SUBSTITUTE(Поставщики_исходные!E5," ",""),"-",""),"+",""),"(",""),")",""))="8","7"&MID(SUBSTITUTE(SUBSTITUTE(SUBSTITUTE(SUBSTITUTE(SUBSTITUTE(Поставщики_исходные!E5," ",""),"-",""),"+",""),"(",""),")",""),2,10),SUBSTITUTE(SUBSTITUTE(SUBSTITUTE(SUBSTITUTE(SUBSTITUTE(Поставщики_исходные!E5," ",""),"-",""),"+",""),"(",""),")","")),10,2),IF(LEN(SUBSTITUTE(SUBSTITUTE(SUBSTITUTE(SUBSTITUTE(SUBSTITUTE(Поставщики_исходные!E5," ",""),"-",""),"+",""),"(",""),")",""))=10,"+7 ("&MID(SUBSTITUTE(SUBSTITUTE(SUBSTITUTE(SUBSTITUTE(SUBSTITUTE(Поставщики_исходные!E5," ",""),"-",""),"+",""),"(",""),")",""),1,3)&") "&MID(SUBSTITUTE(SUBSTITUTE(SUBSTITUTE(SUBSTITUTE(SUBSTITUTE(Поставщики_исходные!E5," ",""),"-",""),"+",""),"(",""),")",""),4,3)&"-"&MID(SUBSTITUTE(SUBSTITUTE(SUBSTITUTE(SUBSTITUTE(SUBSTITUTE(Поставщики_исходные!E5," ",""),"-",""),"+",""),"(",""),")",""),6,2)&"-"&MID(SUBSTITUTE(SUBSTITUTE(SUBSTITUTE(SUBSTITUTE(SUBSTITUTE(Поставщики_исходные!E5," ",""),"-",""),"+",""),"(",""),")",""),8,2),Поставщики_исходные!E5))) -> +7 (903) 456-78-90 | F5: =IF(ISBLANK(Поставщики_исходные!F5),"",IF(ISNUMBER(FIND(".",MID(Поставщики_исходные!F5,FIND("@",Поставщики_исходные!F5)+1,255))),Поставщики_исходные!F5,IF(ISNUMBER(FIND("gmail",Поставщики_исходные!F5)),Поставщики_исходные!F5&".com",Поставщики_исходные!F5&".ru"))) -> import@techno.ru | G5: =TRIM(Поставщики_исходные!G5) -> 119019 г.Москва ул.Арбат д.12 | H5: =IF(ISNUMBER(VALUE(LEFT(TRIM(Поставщики_исходные!G5),6))),LEFT(TRIM(Поставщики_исходные!G5),6),"") -> 119019 | I5: =TRIM(MID(TRIM(Поставщики_исходные!G5),7,255)) -> г.Москва ул.Арбат д.12 | J5: =IF(OR(LEN(C5)=10,LEN(C5)=12),"OK","Ошибка ИНН") -> OK | K5: =IF(AND(ISNUMBER(FIND("@",F5)),ISNUMBER(FIND(".",MID(F5,FIND("@",F5)+1,255)))),"OK","Ошибка Email") -> OK
A6: =Поставщики_исходные!A6 -> P005 | B6: =PROPER(TRIM(Поставщики_исходные!B6)) -> Ооо Торгмастер | C6: =IF(ISBLANK(Поставщики_исходные!C6),"",TRIM(Поставщики_исходные!C6)) -> 7801234567890 | D6: =Поставщики_исходные!D6 -> 780101001 | E6: =IF(ISBLANK(Поставщики_исходные!E6),"",IF(LEN(SUBSTITUTE(SUBSTITUTE(SUBSTITUTE(SUBSTITUTE(SUBSTITUTE(Поставщики_исходные!E6," ",""),"-",""),"+",""),"(",""),")",""))=11,"+7 ("&MID(IF(LEFT(SUBSTITUTE(SUBSTITUTE(SUBSTITUTE(SUBSTITUTE(SUBSTITUTE(Поставщики_исходные!E6," ",""),"-",""),"+",""),"(",""),")",""))="8","7"&MID(SUBSTITUTE(SUBSTITUTE(SUBSTITUTE(SUBSTITUTE(SUBSTITUTE(Поставщики_исходные!E6," ",""),"-",""),"+",""),"(",""),")",""),2,10),SUBSTITUTE(SUBSTITUTE(SUBSTITUTE(SUBSTITUTE(SUBSTITUTE(Поставщики_исходные!E6," ",""),"-",""),"+",""),"(",""),")","")),2,3)&") "&MID(IF(LEFT(SUBSTITUTE(SUBSTITUTE(SUBSTITUTE(SUBSTITUTE(SUBSTITUTE(Поставщики_исходные!E6," ",""),"-",""),"+",""),"(",""),")",""))="8","7"&MID(SUBSTITUTE(SUBSTITUTE(SUBSTITUTE(SUBSTITUTE(SUBSTITUTE(Поставщики_исходные!E6," ",""),"-",""),"+",""),"(",""),")",""),2,10),SUBSTITUTE(SUBSTITUTE(SUBSTITUTE(SUBSTITUTE(SUBSTITUTE(Поставщики_исходные!E6," ",""),"-",""),"+",""),"(",""),")","")),5,3)&"-"&MID(IF(LEFT(SUBSTITUTE(SUBSTITUTE(SUBSTITUTE(SUBSTITUTE(SUBSTITUTE(Поставщики_исходные!E6," ",""),"-",""),"+",""),"(",""),")",""))="8","7"&MID(SUBSTITUTE(SUBSTITUTE(SUBSTITUTE(SUBSTITUTE(SUBSTITUTE(Поставщики_исходные!E6," ",""),"-",""),"+",""),"(",""),")",""),2,10),SUBSTITUTE(SUBSTITUTE(SUBSTITUTE(SUBSTITUTE(SUBSTITUTE(Поставщики_исходные!E6," ",""),"-",""),"+",""),"(",""),")","")),8,2)&"-"&MID(IF(LEFT(SUBSTITUTE(SUBSTITUTE(SUBSTITUTE(SUBSTITUTE(SUBSTITUTE(Поставщики_исходные!E6," ",""),"-",""),"+",""),"(",""),")",""))="8","7"&MID(SUBSTITUTE(SUBSTITUTE(SUBSTITUTE(SUBSTITUTE(SUBSTITUTE(Поставщики_исходные!E6," ",""),"-",""),"+",""),"(",""),")",""),2,10),SUBSTITUTE(SUBSTITUTE(SUBSTITUTE(SUBSTITUTE(SUBSTITUTE(Поставщики_исходные!E6," ",""),"-",""),"+",""),"(",""),")","")),10,2),IF(LEN(SUBSTITUTE(SUBSTITUTE(SUBSTITUTE(SUBSTITUTE(SUBSTITUTE(Поставщики_исходные!E6," ",""),"-",""),"+",""),"(",""),")",""))=10,"+7 ("&MID(SUBSTITUTE(SUBSTITUTE(SUBSTITUTE(SUBSTITUTE(SUBSTITUTE(Поставщики_исходные!E6," ",""),"-",""),"+",""),"(",""),")",""),1,3)&") "&MID(SUBSTITUTE(SUBSTITUTE(SUBSTITUTE(SUBSTITUTE(SUBSTITUTE(Поставщики_исходные!E6," ",""),"-",""),"+",""),"(",""),")",""),4,3)&"-"&MID(SUBSTITUTE(SUBSTITUTE(SUBSTITUTE(SUBSTITUTE(SUBSTITUTE(Поставщики_исходные!E6," ",""),"-",""),"+",""),"(",""),")",""),6,2)&"-"&MID(SUBSTITUTE(SUBSTITUTE(SUBSTITUTE(SUBSTITUTE(SUBSTITUTE(Поставщики_исходные!E6," ",""),"-",""),"+",""),"(",""),")",""),8,2),Поставщики_исходные!E6))) -> +7 (903) 567-89-01 | F6: =IF(ISBLANK(Поставщики_исходные!F6),"",IF(ISNUMBER(FIND(".",MID(Поставщики_исходные!F6,FIND("@",Поставщики_исходные!F6)+1,255))),Поставщики_исходные!F6,IF(ISNUMBER(FIND("gmail",Поставщики_исходные!F6)),Поставщики_исходные!F6&".com",Поставщики_исходные!F6&".ru"))) -> torg@master.ru | G6: =TRIM(Поставщики_исходные!G6) -> 192007 г.Санкт-Петербург пр.Обуховской Обороны д.120 | H6: =IF(ISNUMBER(VALUE(LEFT(TRIM(Поставщики_исходные!G6),6))),LEFT(TRIM(Поставщики_исходные!G6),6),"") -> 192007 | I6: =TRIM(MID(TRIM(Поставщики_исходные!G6),7,255)) -> г.Санкт-Петербург пр.Обуховской Обороны д.120 | J6: =IF(OR(LEN(C6)=10,LEN(C6)=12),"OK","Ошибка ИНН") -> Ошибка ИНН | K6: =IF(AND(ISNUMBER(FIND("@",F6)),ISNUMBER(FIND(".",MID(F6,FIND("@",F6)+1,255)))),"OK","Ошибка Email") -> OK
A7: =Поставщики_исходные!A7 -> P006 | B7: =PROPER(TRIM(Поставщики_исходные!B7)) -> Зао Техноресурс | C7: =IF(ISBLANK(Поставщики_исходные!C7),"",TRIM(Поставщики_исходные!C7)) -> 77134567 | D7: =Поставщики_исходные!D7 -> 771101001 | E7: =IF(ISBLANK(Поставщики_исходные!E7),"",IF(LEN(SUBSTITUTE(SUBSTITUTE(SUBSTITUTE(SUBSTITUTE(SUBSTITUTE(Поставщики_исходные!E7," ",""),"-",""),"+",""),"(",""),")",""))=11,"+7 ("&MID(IF(LEFT(SUBSTITUTE(SUBSTITUTE(SUBSTITUTE(SUBSTITUTE(SUBSTITUTE(Поставщики_исходные!E7," ",""),"-",""),"+",""),"(",""),")",""))="8","7"&MID(SUBSTITUTE(SUBSTITUTE(SUBSTITUTE(SUBSTITUTE(SUBSTITUTE(Поставщики_исходные!E7," ",""),"-",""),"+",""),"(",""),")",""),2,10),SUBSTITUTE(SUBSTITUTE(SUBSTITUTE(SUBSTITUTE(SUBSTITUTE(Поставщики_исходные!E7," ",""),"-",""),"+",""),"(",""),")","")),2,3)&") "&MID(IF(LEFT(SUBSTITUTE(SUBSTITUTE(SUBSTITUTE(SUBSTITUTE(SUBSTITUTE(Поставщики_исходные!E7," ",""),"-",""),"+",""),"(",""),")",""))="8","7"&MID(SUBSTITUTE(SUBSTITUTE(SUBSTITUTE(SUBSTITUTE(SUBSTITUTE(Поставщики_исходные!E7," ",""),"-",""),"+",""),"(",""),")",""),2,10),SUBSTITUTE(SUBSTITUTE(SUBSTITUTE(SUBSTITUTE(SUBSTITUTE(Поставщики_исходные!E7," ",""),"-",""),"+",""),"(",""),")","")),5,3)&"-"&MID(IF(LEFT(SUBSTITUTE(SUBSTITUTE(SUBSTITUTE(SUBSTITUTE(SUBSTITUTE(Поставщики_исходные!E7," ",""),"-",""),"+",""),"(",""),")",""))="8","7"&MID(SUBSTITUTE(SUBSTITUTE(SUBSTITUTE(SUBSTITUTE(SUBSTITUTE(Поставщики_исходные!E7," ",""),"-",""),"+",""),"(",""),")",""),2,10),SUBSTITUTE(SUBSTITUTE(SUBSTITUTE(SUBSTITUTE(SUBSTITUTE(Поставщики_исходные!E7," ",""),"-",""),"+",""),"(",""),")","")),8,2)&"-"&MID(IF(LEFT(SUBSTITUTE(SUBSTITUTE(SUBSTITUTE(SUBSTITUTE(SUBSTITUTE(Поставщики_исходные!E7," ",""),"-",""),"+",""),"(",""),")",""))="8","7"&MID(SUBSTITUTE(SUBSTITUTE(SUBSTITUTE(SUBSTITUTE(SUBSTITUTE(Поставщики_исходные!E7," ",""),"-",""),"+",""),"(",""),")",""),2,10),SUBSTITUTE(SUBSTITUTE(SUBSTITUTE(SUBSTITUTE(SUBSTITUTE(Поставщики_исходные!E7," ",""),"-",""),"+",""),"(",""),")","")),10,2),IF(LEN(SUBSTITUTE(SUBSTITUTE(SUBSTITUTE(SUBSTITUTE(SUBSTITUTE(Поставщики_исходные!E7," ",""),"-",""),"+",""),"(",""),")",""))=10,"+7 ("&MID(SUBSTITUTE(SUBSTITUTE(SUBSTITUTE(SUBSTITUTE(SUBSTITUTE(Поставщики_исходные!E7," ",""),"-",""),"+",""),"(",""),")",""),1,3)&") "&MID(SUBSTITUTE(SUBSTITUTE(SUBSTITUTE(SUBSTITUTE(SUBSTITUTE(Поставщики_исходные!E7," ",""),"-",""),"+",""),"(",""),")",""),4,3)&"-"&MID(SUBSTITUTE(SUBSTITUTE(SUBSTITUTE(SUBSTITUTE(SUBSTITUTE(Поставщики_исходные!E7," ",""),"-",""),"+",""),"(",""),")",""),6,2)&"-"&MID(SUBSTITUTE(SUBSTITUTE(SUBSTITUTE(SUBSTITUTE(SUBSTITUTE(Поставщики_исходные!E7," ",""),"-",""),"+",""),"(",""),")",""),8,2),Поставщики_исходные!E7))) -> +7 (903) 678-90-12 | F7: =IF(ISBLANK(Поставщики_исходные!F7),"",IF(ISNUMBER(FIND(".",MID(Поставщики_исходные!F7,FIND("@",Поставщики_исходные!F7)+1,255))),Поставщики_исходные!F7,IF(ISNUMBER(FIND("gmail",Поставщики_исходные!F7)),Поставщики_исходные!F7&".com",Поставщики_исходные!F7&".ru"))) -> resurs@techno.ru | G7: =TRIM(Поставщики_исходные!G7) -> 119121 г.Москва ул.Плющиха д.25 | H7: =IF(ISNUMBER(VALUE(LEFT(TRIM(Поставщики_исходные!G7),6))),LEFT(TRIM(Поставщики_исходные!G7),6),"") -> 119121 | I7: =TRIM(MID(TRIM(Поставщики_исходные!G7),7,255)) -> г.Москва ул.Плющиха д.25 | J7: =IF(OR(LEN(C7)=10,LEN(C7)=12),"OK","Ошибка ИНН") -> Ошибка ИНН | K7: =IF(AND(ISNUMBER(FIND("@",F7)),ISNUMBER(FIND(".",MID(F7,FIND("@",F7)+1,255)))),"OK","Ошибка Email") -> OK
A8: =Поставщики_исходные!A8 -> P007 | B8: =PROPER(TRIM(Поставщики_исходные!B8)) -> Ооо Прогрессплюс | C8: =IF(ISBLANK(Поставщики_исходные!C8),"",TRIM(Поставщики_исходные!C8)) -> 7802345678 | D8: =Поставщики_исходные!D8 -> 780201001 | E8: =IF(ISBLANK(Поставщики_исходные!E8),"",IF(LEN(SUBSTITUTE(SUBSTITUTE(SUBSTITUTE(SUBSTITUTE(SUBSTITUTE(Поставщики_исходные!E8," ",""),"-",""),"+",""),"(",""),")",""))=11,"+7 ("&MID(IF(LEFT(SUBSTITUTE(SUBSTITUTE(SUBSTITUTE(SUBSTITUTE(SUBSTITUTE(Поставщики_исходные!E8," ",""),"-",""),"+",""),"(",""),")",""))="8","7"&MID(SUBSTITUTE(SUBSTITUTE(SUBSTITUTE(SUBSTITUTE(SUBSTITUTE(Поставщики_исходные!E8," ",""),"-",""),"+",""),"(",""),")",""),2,10),SUBSTITUTE(SUBSTITUTE(SUBSTITUTE(SUBSTITUTE(SUBSTITUTE(Поставщики_исходные!E8," ",""),"-",""),"+",""),"(",""),")","")),2,3)&") "&MID(IF(LEFT(SUBSTITUTE(SUBSTITUTE(SUBSTITUTE(SUBSTITUTE(SUBSTITUTE(Поставщики_исходные!E8," ",""),"-",""),"+",""),"(",""),")",""))="8","7"&MID(SUBSTITUTE(SUBSTITUTE(SUBSTITUTE(SUBSTITUTE(SUBSTITUTE(Поставщики_исходные!E8," ",""),"-",""),"+",""),"(",""),")",""),2,10),SUBSTITUTE(SUBSTITUTE(SUBSTITUTE(SUBSTITUTE(SUBSTITUTE(Поставщики_исходные!E8," ",""),"-",""),"+",""),"(",""),")","")),5,3)&"-"&MID(IF(LEFT(SUBSTITUTE(SUBSTITUTE(SUBSTITUTE(SUBSTITUTE(SUBSTITUTE(Поставщики_исходные!E8," ",""),"-",""),"+",""),"(",""),")",""))="8","7"&MID(SUBSTITUTE(SUBSTITUTE(SUBSTITUTE(SUBSTITUTE(SUBSTITUTE(Поставщики_исходные!E8," ",""),"-",""),"+",""),"(",""),")",""),2,10),SUBSTITUTE(SUBSTITUTE(SUBSTITUTE(SUBSTITUTE(SUBSTITUTE(Поставщики_исходные!E8," ",""),"-",""),"+",""),"(",""),")","")),8,2)&"-"&MID(IF(LEFT(SUBSTITUTE(SUBSTITUTE(SUBSTITUTE(SUBSTITUTE(SUBSTITUTE(Поставщики_исходные!E8," ",""),"-",""),"+",""),"(",""),")",""))="8","7"&MID(SUBSTITUTE(SUBSTITUTE(SUBSTITUTE(SUBSTITUTE(SUBSTITUTE(Поставщики_исходные!E8," ",""),"-",""),"+",""),"(",""),")",""),2,10),SUBSTITUTE(SUBSTITUTE(SUBSTITUTE(SUBSTITUTE(SUBSTITUTE(Поставщики_исходные!E8," ",""),"-",""),"+",""),"(",""),")","")),10,2),IF(LEN(SUBSTITUTE(SUBSTITUTE(SUBSTITUTE(SUBSTITUTE(SUBSTITUTE(Поставщики_исходные!E8," ",""),"-",""),"+",""),"(",""),")",""))=10,"+7 ("&MID(SUBSTITUTE(SUBSTITUTE(SUBSTITUTE(SUBSTITUTE(SUBSTITUTE(Поставщики_исходные!E8," ",""),"-",""),"+",""),"(",""),")",""),1,3)&") "&MID(SUBSTITUTE(SUBSTITUTE(SUBSTITUTE(SUBSTITUTE(SUBSTITUTE(Поставщики_исходные!E8," ",""),"-",""),"+",""),"(",""),")",""),4,3)&"-"&MID(SUBSTITUTE(SUBSTITUTE(SUBSTITUTE(SUBSTITUTE(SUBSTITUTE(Поставщики_исходные!E8," ",""),"-",""),"+",""),"(",""),")",""),6,2)&"-"&MID(SUBSTITUTE(SUBSTITUTE(SUBSTITUTE(SUBSTITUTE(SUBSTITUTE(Поставщики_исходные!E8," ",""),"-",""),"+",""),"(",""),")",""),8,2),Поставщики_исходные!E8))) -> +7 (903) 789-01-23 | F8: =IF(ISBLANK(Поставщики_исходные!F8),"",IF(ISNUMBER(FIND(".",MID(Поставщики_исходные!F8,FIND("@",Поставщики_исходные!F8)+1,255))),Поставщики_исходные!F8,IF(ISNUMBER(FIND("gmail",Поставщики_исходные!F8)),Поставщики_исходные!F8&".com",Поставщики_исходные!F8&".ru"))) -> progress@mail.ru | G8: =TRIM(Поставщики_исходные!G8) -> 197022 г.Санкт-Петербург ул.Профессора Попова д.37 | H8: =IF(ISNUMBER(VALUE(LEFT(TRIM(Поставщики_исходные!G8),6))),LEFT(TRIM(Поставщики_исходные!G8),6),"") -> 197022 | I8: =TRIM(MID(TRIM(Поставщики_исходные!G8),7,255)) -> г.Санкт-Петербург ул.Профессора Попова д.37 | J8: =IF(OR(LEN(C8)=10,LEN(C8)=12),"OK","Ошибка ИНН") -> OK | K8: =IF(AND(ISNUMBER(FIND("@",F8)),ISNUMBER(FIND(".",MID(F8,FIND("@",F8)+1,255)))),"OK","Ошибка Email") -> OK
A9: =Поставщики_исходные!A9 -> P008 | B9: =PROPER(TRIM(Поставщики_исходные!B9)) -> Ао Электронсбыт | C9: =IF(ISBLANK(Поставщики_исходные!C9),"",TRIM(Поставщики_исходные!C9)) -> 771456789012 | D9: =Поставщики_исходные!D9 -> 771201001 | E9: =IF(ISBLANK(Поставщики_исходные!E9),"",IF(LEN(SUBSTITUTE(SUBSTITUTE(SUBSTITUTE(SUBSTITUTE(SUBSTITUTE(Поставщики_исходные!E9," ",""),"-",""),"+",""),"(",""),")",""))=11,"+7 ("&MID(IF(LEFT(SUBSTITUTE(SUBSTITUTE(SUBSTITUTE(SUBSTITUTE(SUBSTITUTE(Поставщики_исходные!E9," ",""),"-",""),"+",""),"(",""),")",""))="8","7"&MID(SUBSTITUTE(SUBSTITUTE(SUBSTITUTE(SUBSTITUTE(SUBSTITUTE(Поставщики_исходные!E9," ",""),"-",""),"+",""),"(",""),")",""),2,10),SUBSTITUTE(SUBSTITUTE(SUBSTITUTE(SUBSTITUTE(SUBSTITUTE(Поставщики_исходные!E9," ",""),"-",""),"+",""),"(",""),")","")),2,3)&") "&MID(IF(LEFT(SUBSTITUTE(SUBSTITUTE(SUBSTITUTE(SUBSTITUTE(SUBSTITUTE(Поставщики_исходные!E9," ",""),"-",""),"+",""),"(",""),")",""))="8","7"&MID(SUBSTITUTE(SUBSTITUTE(SUBSTITUTE(SUBSTITUTE(SUBSTITUTE(Поставщики_исходные!E9," ",""),"-",""),"+",""),"(",""),")",""),2,10),SUBSTITUTE(SUBSTITUTE(SUBSTITUTE(SUBSTITUTE(SUBSTITUTE(Поставщики_исходные!E9," ",""),"-",""),"+",""),"(",""),")","")),5,3)&"-"&MID(IF(LEFT(SUBSTITUTE(SUBSTITUTE(SUBSTITUTE(SUBSTITUTE(SUBSTITUTE(Поставщики_исходные!E9," ",""),"-",""),"+",""),"(",""),")",""))="8","7"&MID(SUBSTITUTE(SUBSTITUTE(SUBSTITUTE(SUBSTITUTE(SUBSTITUTE(Поставщики_исходные!E9," ",""),"-",""),"+",""),"(",""),")",""),2,10),SUBSTITUTE(SUBSTITUTE(SUBSTITUTE(SUBSTITUTE(SUBSTITUTE(Поставщики_исходные!E9," ",""),"-",""),"+",""),"(",""),")","")),8,2)&"-"&MID(IF(LEFT(SUBSTITUTE(SUBSTITUTE(SUBSTITUTE(SUBSTITUTE(SUBSTITUTE(Поставщики_исходные!E9," ",""),"-",""),"+",""),"(",""),")",""))="8","7"&MID(SUBSTITUTE(SUBSTITUTE(SUBSTITUTE(SUBSTITUTE(SUBSTITUTE(Поставщики_исходные!E9," ",""),"-",""),"+",""),"(",""),")",""),2,10),SUBSTITUTE(SUBSTITUTE(SUBSTITUTE(SUBSTITUTE(SUBSTITUTE(Поставщики_исходные!E9," ",""),"-",""),"+",""),"(",""),")","")),10,2),IF(LEN(SUBSTITUTE(SUBSTITUTE(SUBSTITUTE(SUBSTITUTE(SUBSTITUTE(Поставщики_исходные!E9," ",""),"-",""),"+",""),"(",""),")",""))=10,"+7 ("&MID(SUBSTITUTE(SUBSTITUTE(SUBSTITUTE(SUBSTITUTE(SUBSTITUTE(Поставщики_исходные!E9," ",""),"-",""),"+",""),"(",""),")",""),1,3)&") "&MID(SUBSTITUTE(SUBSTITUTE(SUBSTITUTE(SUBSTITUTE(SUBSTITUTE(Поставщики_исходные!E9," ",""),"-",""),"+",""),"(",""),")",""),4,3)&"-"&MID(SUBSTITUTE(SUBSTITUTE(SUBSTITUTE(SUBSTITUTE(SUBSTITUTE(Поставщики_исходные!E9," ",""),"-",""),"+",""),"(",""),")",""),6,2)&"-"&MID(SUBSTITUTE(SUBSTITUTE(SUBSTITUTE(SUBSTITUTE(SUBSTITUTE(Поставщики_исходные!E9," ",""),"-",""),"+",""),"(",""),")",""),8,2),Поставщики_исходные!E9))) -> +7 (903) 890-12-34 | F9: =IF(ISBLANK(Поставщики_исходные!F9),"",IF(ISNUMBER(FIND(".",MID(Поставщики_исходные!F9,FIND("@",Поставщики_исходные!F9)+1,255))),Поставщики_исходные!F9,IF(ISNUMBER(FIND("gmail",Поставщики_исходные!F9)),Поставщики_исходные!F9&".com",Поставщики_исходные!F9&".ru"))) -> electron@sbyt.ru | G9: =TRIM(Поставщики_исходные!G9) -> 109316 г.Москва ул.Таганская д.54 | H9: =IF(ISNUMBER(VALUE(LEFT(TRIM(Поставщики_исходные!G9),6))),LEFT(TRIM(Поставщики_исходные!G9),6),"") -> 109316 | I9: =TRIM(MID(TRIM(Поставщики_исходные!G9),7,255)) -> г.Москва ул.Таганская д.54 | J9: =IF(OR(LEN(C9)=10,LEN(C9)=12),"OK","Ошибка ИНН") -> OK | K9: =IF(AND(ISNUMBER(FIND("@",F9)),ISNUMBER(FIND(".",MID(F9,FIND("@",F9)+1,255)))),"OK","Ошибка Email") -> OK
A10: ='Поставщики_исходные'!A10 -> P009 | B10: =PROPER(TRIM('Поставщики_исходные'!B10)) -> Ооо Смарттех | C10: =IF(ISBLANK(Поставщики_исходные!C8),"",TRIM(Поставщики_исходные!C8)) -> 7802345678 | D10: ='Поставщики_исходные'!D10 -> 780301001 | E10: =IF(ISBLANK(Поставщики_исходные!E10),"",IF(LEN(SUBSTITUTE(SUBSTITUTE(SUBSTITUTE(SUBSTITUTE(SUBSTITUTE(Поставщики_исходные!E10," ",""),"-",""),"+",""),"(",""),")",""))=11,"+7 ("&MID(IF(LEFT(SUBSTITUTE(SUBSTITUTE(SUBSTITUTE(SUBSTITUTE(SUBSTITUTE(Поставщики_исходные!E10," ",""),"-",""),"+",""),"(",""),")",""))="8","7"&MID(SUBSTITUTE(SUBSTITUTE(SUBSTITUTE(SUBSTITUTE(SUBSTITUTE(Поставщики_исходные!E10," ",""),"-",""),"+",""),"(",""),")",""),2,10),SUBSTITUTE(SUBSTITUTE(SUBSTITUTE(SUBSTITUTE(SUBSTITUTE(Поставщики_исходные!E10," ",""),"-",""),"+",""),"(",""),")","")),2,3)&") "&MID(IF(LEFT(SUBSTITUTE(SUBSTITUTE(SUBSTITUTE(SUBSTITUTE(SUBSTITUTE(Поставщики_исходные!E10," ",""),"-",""),"+",""),"(",""),")",""))="8","7"&MID(SUBSTITUTE(SUBSTITUTE(SUBSTITUTE(SUBSTITUTE(SUBSTITUTE(Поставщики_исходные!E10," ",""),"-",""),"+",""),"(",""),")",""),2,10),SUBSTITUTE(SUBSTITUTE(SUBSTITUTE(SUBSTITUTE(SUBSTITUTE(Поставщики_исходные!E10," ",""),"-",""),"+",""),"(",""),")","")),5,3)&"-"&MID(IF(LEFT(SUBSTITUTE(SUBSTITUTE(SUBSTITUTE(SUBSTITUTE(SUBSTITUTE(Поставщики_исходные!E10," ",""),"-",""),"+",""),"(",""),")",""))="8","7"&MID(SUBSTITUTE(SUBSTITUTE(SUBSTITUTE(SUBSTITUTE(SUBSTITUTE(Поставщики_исходные!E10," ",""),"-",""),"+",""),"(",""),")",""),2,10),SUBSTITUTE(SUBSTITUTE(SUBSTITUTE(SUBSTITUTE(SUBSTITUTE(Поставщики_исходные!E10," ",""),"-",""),"+",""),"(",""),")","")),8,2)&"-"&MID(IF(LEFT(SUBSTITUTE(SUBSTITUTE(SUBSTITUTE(SUBSTITUTE(SUBSTITUTE(Поставщики_исходные!E10," ",""),"-",""),"+",""),"(",""),")",""))="8","7"&MID(SUBSTITUTE(SUBSTITUTE(SUBSTITUTE(SUBSTITUTE(SUBSTITUTE(Поставщики_исходные!E10," ",""),"-",""),"+",""),"(",""),")",""),2,10),SUBSTITUTE(SUBSTITUTE(SUBSTITUTE(SUBSTITUTE(SUBSTITUTE(Поставщики_исходные!E10," ",""),"-",""),"+",""),"(",""),")","")),10,2),IF(LEN(SUBSTITUTE(SUBSTITUTE(SUBSTITUTE(SUBSTITUTE(SUBSTITUTE(Поставщики_исходные!E10," ",""),"-",""),"+",""),"(",""),")",""))=10,"+7 ("&MID(SUBSTITUTE(SUBSTITUTE(SUBSTITUTE(SUBSTITUTE(SUBSTITUTE(Поставщики_исходные!E10," ",""),"-",""),"+",""),"(",""),")",""),1,3)&") "&MID(SUBSTITUTE(SUBSTITUTE(SUBSTITUTE(SUBSTITUTE(SUBSTITUTE(Поставщики_исходные!E10," ",""),"-",""),"+",""),"(",""),")",""),4,3)&"-"&MID(SUBSTITUTE(SUBSTITUTE(SUBSTITUTE(SUBSTITUTE(SUBSTITUTE(Поставщики_исходные!E10," ",""),"-",""),"+",""),"(",""),")",""),6,2)&"-"&MID(SUBSTITUTE(SUBSTITUTE(SUBSTITUTE(SUBSTITUTE(SUBSTITUTE(Поставщики_исходные!E10," ",""),"-",""),"+",""),"(",""),")",""),8,2),Поставщики_исходные!E10))) -> +7 (903) 901-23-45 | F10: =IF(ISBLANK(Поставщики_исходные!F10),"",IF(ISNUMBER(FIND(".",MID(Поставщики_исходные!F10,FIND("@",Поставщики_исходные!F10)+1,255))),Поставщики_исходные!F10,IF(ISNUMBER(FIND("gmail",Поставщики_исходные!F10)),Поставщики_исходные!F10&".com",Поставщики_исходные!F10&".ru"))) -> smart@tech.ru | G10: =TRIM('Поставщики_исходные'!G10) -> 196084 г.Санкт-Петербург ул.Заставская д.22 | H10: =IF(ISNUMBER(VALUE(LEFT(TRIM('Поставщики_исходные'!G10),6))),LEFT(TRIM('Поставщики_исходные'!G10),6),"") -> 196084 | I10: =TRIM(MID(TRIM('Поставщики_исходные'!G10),7,255)) -> г.Санкт-Петербург ул.Заставская д.22 | J10: =IF(OR(LEN(C10)=10,LEN(C10)=12),"OK","Ошибка ИНН") -> OK | K10: =IF(AND(ISNUMBER(FIND("@",F10)),ISNUMBER(FIND(".",MID(F10,FIND("@",F10)+1,255)))),"OK","Ошибка Email") -> OK
A11: =Поставщики_исходные!A11 -> P010 | B11: =PROPER(TRIM(Поставщики_исходные!B11)) -> Зао Технопром | C11: =IF(ISBLANK(Поставщики_исходные!C9),"",TRIM(Поставщики_исходные!C9)) -> 771456789012 | D11: =Поставщики_исходные!D11 -> 771301001 | E11: =IF(ISBLANK(Поставщики_исходные!E11),"",IF(LEN(SUBSTITUTE(SUBSTITUTE(SUBSTITUTE(SUBSTITUTE(SUBSTITUTE(Поставщики_исходные!E11," ",""),"-",""),"+",""),"(",""),")",""))=11,"+7 ("&MID(IF(LEFT(SUBSTITUTE(SUBSTITUTE(SUBSTITUTE(SUBSTITUTE(SUBSTITUTE(Поставщики_исходные!E11," ",""),"-",""),"+",""),"(",""),")",""))="8","7"&MID(SUBSTITUTE(SUBSTITUTE(SUBSTITUTE(SUBSTITUTE(SUBSTITUTE(Поставщики_исходные!E11," ",""),"-",""),"+",""),"(",""),")",""),2,10),SUBSTITUTE(SUBSTITUTE(SUBSTITUTE(SUBSTITUTE(SUBSTITUTE(Поставщики_исходные!E11," ",""),"-",""),"+",""),"(",""),")","")),2,3)&") "&MID(IF(LEFT(SUBSTITUTE(SUBSTITUTE(SUBSTITUTE(SUBSTITUTE(SUBSTITUTE(Поставщики_исходные!E11," ",""),"-",""),"+",""),"(",""),")",""))="8","7"&MID(SUBSTITUTE(SUBSTITUTE(SUBSTITUTE(SUBSTITUTE(SUBSTITUTE(Поставщики_исходные!E11," ",""),"-",""),"+",""),"(",""),")",""),2,10),SUBSTITUTE(SUBSTITUTE(SUBSTITUTE(SUBSTITUTE(SUBSTITUTE(Поставщики_исходные!E11," ",""),"-",""),"+",""),"(",""),")","")),5,3)&"-"&MID(IF(LEFT(SUBSTITUTE(SUBSTITUTE(SUBSTITUTE(SUBSTITUTE(SUBSTITUTE(Поставщики_исходные!E11," ",""),"-",""),"+",""),"(",""),")",""))="8","7"&MID(SUBSTITUTE(SUBSTITUTE(SUBSTITUTE(SUBSTITUTE(SUBSTITUTE(Поставщики_исходные!E11," ",""),"-",""),"+",""),"(",""),")",""),2,10),SUBSTITUTE(SUBSTITUTE(SUBSTITUTE(SUBSTITUTE(SUBSTITUTE(Поставщики_исходные!E11," ",""),"-",""),"+",""),"(",""),")","")),8,2)&"-"&MID(IF(LEFT(SUBSTITUTE(SUBSTITUTE(SUBSTITUTE(SUBSTITUTE(SUBSTITUTE(Поставщики_исходные!E11," ",""),"-",""),"+",""),"(",""),")",""))="8","7"&MID(SUBSTITUTE(SUBSTITUTE(SUBSTITUTE(SUBSTITUTE(SUBSTITUTE(Поставщики_исходные!E11," ",""),"-",""),"+",""),"(",""),")",""),2,10),SUBSTITUTE(SUBSTITUTE(SUBSTITUTE(SUBSTITUTE(SUBSTITUTE(Поставщики_исходные!E11," ",""),"-",""),"+",""),"(",""),")","")),10,2),IF(LEN(SUBSTITUTE(SUBSTITUTE(SUBSTITUTE(SUBSTITUTE(SUBSTITUTE(Поставщики_исходные!E11," ",""),"-",""),"+",""),"(",""),")",""))=10,"+7 ("&MID(SUBSTITUTE(SUBSTITUTE(SUBSTITUTE(SUBSTITUTE(SUBSTITUTE(Поставщики_исходные!E11," ",""),"-",""),"+",""),"(",""),")",""),1,3)&") "&MID(SUBSTITUTE(SUBSTITUTE(SUBSTITUTE(SUBSTITUTE(SUBSTITUTE(Поставщики_исходные!E11," ",""),"-",""),"+",""),"(",""),")",""),4,3)&"-"&MID(SUBSTITUTE(SUBSTITUTE(SUBSTITUTE(SUBSTITUTE(SUBSTITUTE(Поставщики_исходные!E11," ",""),"-",""),"+",""),"(",""),")",""),6,2)&"-"&MID(SUBSTITUTE(SUBSTITUTE(SUBSTITUTE(SUBSTITUTE(SUBSTITUTE(Поставщики_исходные!E11," ",""),"-",""),"+",""),"(",""),")",""),8,2),Поставщики_исходные!E11))) -> +7 (903) 012-34-56 | F11: =IF(ISBLANK(Поставщики_исходные!F11),"",IF(ISNUMBER(FIND(".",MID(Поставщики_исходные!F11,FIND("@",Поставщики_исходные!F11)+1,255))),Поставщики_исходные!F11,IF(ISNUMBER(FIND("gmail",Поставщики_исходные!F11)),Поставщики_исходные!F11&".com",Поставщики_исходные!F11&".ru"))) -> prom@tehno.ru | G11: =TRIM(Поставщики_исходные!G11) -> 119334 г.Москва ул.Косыгина д.17 | H11: =IF(ISNUMBER(VALUE(LEFT(TRIM(Поставщики_исходные!G11),6))),LEFT(TRIM(Поставщики_исходные!G11),6),"") -> 119334 | I11: =TRIM(MID(TRIM(Поставщики_исходные!G11),7,255)) -> г.Москва ул.Косыгина д.17 | J11: =IF(OR(LEN(C11)=10,LEN(C11)=12),"OK","Ошибка ИНН") -> OK | K11: =IF(AND(ISNUMBER(FIND("@",F11)),ISNUMBER(FIND(".",MID(F11,FIND("@",F11)+1,255)))),"OK","Ошибка Email") -> OK
A12: =Поставщики_исходные!A12 -> P011 | B12: =PROPER(TRIM(Поставщики_исходные!B12)) -> Ооо Сервисплюс | C12: =IF(ISBLANK(Поставщики_исходные!C10),"",TRIM(Поставщики_исходные!C10)) -> 7803456789 | D12: =Поставщики_исходные!D12 -> 780401001 | E12: =IF(ISBLANK(Поставщики_исходные!E12),"",IF(LEN(SUBSTITUTE(SUBSTITUTE(SUBSTITUTE(SUBSTITUTE(SUBSTITUTE(Поставщики_исходные!E12," ",""),"-",""),"+",""),"(",""),")",""))=11,"+7 ("&MID(IF(LEFT(SUBSTITUTE(SUBSTITUTE(SUBSTITUTE(SUBSTITUTE(SUBSTITUTE(Поставщики_исходные!E12," ",""),"-",""),"+",""),"(",""),")",""))="8","7"&MID(SUBSTITUTE(SUBSTITUTE(SUBSTITUTE(SUBSTITUTE(SUBSTITUTE(Поставщики_исходные!E12," ",""),"-",""),"+",""),"(",""),")",""),2,10),SUBSTITUTE(SUBSTITUTE(SUBSTITUTE(SUBSTITUTE(SUBSTITUTE(Поставщики_исходные!E12," ",""),"-",""),"+",""),"(",""),")","")),2,3)&") "&MID(IF(LEFT(SUBSTITUTE(SUBSTITUTE(SUBSTITUTE(SUBSTITUTE(SUBSTITUTE(Поставщики_исходные!E12," ",""),"-",""),"+",""),"(",""),")",""))="8","7"&MID(SUBSTITUTE(SUBSTITUTE(SUBSTITUTE(SUBSTITUTE(SUBSTITUTE(Поставщики_исходные!E12," ",""),"-",""),"+",""),"(",""),")",""),2,10),SUBSTITUTE(SUBSTITUTE(SUBSTITUTE(SUBSTITUTE(SUBSTITUTE(Поставщики_исходные!E12," ",""),"-",""),"+",""),"(",""),")","")),5,3)&"-"&MID(IF(LEFT(SUBSTITUTE(SUBSTITUTE(SUBSTITUTE(SUBSTITUTE(SUBSTITUTE(Поставщики_исходные!E12," ",""),"-",""),"+",""),"(",""),")",""))="8","7"&MID(SUBSTITUTE(SUBSTITUTE(SUBSTITUTE(SUBSTITUTE(SUBSTITUTE(Поставщики_исходные!E12," ",""),"-",""),"+",""),"(",""),")",""),2,10),SUBSTITUTE(SUBSTITUTE(SUBSTITUTE(SUBSTITUTE(SUBSTITUTE(Поставщики_исходные!E12," ",""),"-",""),"+",""),"(",""),")","")),8,2)&"-"&MID(IF(LEFT(SUBSTITUTE(SUBSTITUTE(SUBSTITUTE(SUBSTITUTE(SUBSTITUTE(Поставщики_исходные!E12," ",""),"-",""),"+",""),"(",""),")",""))="8","7"&MID(SUBSTITUTE(SUBSTITUTE(SUBSTITUTE(SUBSTITUTE(SUBSTITUTE(Поставщики_исходные!E12," ",""),"-",""),"+",""),"(",""),")",""),2,10),SUBSTITUTE(SUBSTITUTE(SUBSTITUTE(SUBSTITUTE(SUBSTITUTE(Поставщики_исходные!E12," ",""),"-",""),"+",""),"(",""),")","")),10,2),IF(LEN(SUBSTITUTE(SUBSTITUTE(SUBSTITUTE(SUBSTITUTE(SUBSTITUTE(Поставщики_исходные!E12," ",""),"-",""),"+",""),"(",""),")",""))=10,"+7 ("&MID(SUBSTITUTE(SUBSTITUTE(SUBSTITUTE(SUBSTITUTE(SUBSTITUTE(Поставщики_исходные!E12," ",""),"-",""),"+",""),"(",""),")",""),1,3)&") "&MID(SUBSTITUTE(SUBSTITUTE(SUBSTITUTE(SUBSTITUTE(SUBSTITUTE(Поставщики_исходные!E12," ",""),"-",""),"+",""),"(",""),")",""),4,3)&"-"&MID(SUBSTITUTE(SUBSTITUTE(SUBSTITUTE(SUBSTITUTE(SUBSTITUTE(Поставщики_исходные!E12," ",""),"-",""),"+",""),"(",""),")",""),6,2)&"-"&MID(SUBSTITUTE(SUBSTITUTE(SUBSTITUTE(SUBSTITUTE(SUBSTITUTE(Поставщики_исходные!E12," ",""),"-",""),"+",""),"(",""),")",""),8,2),Поставщики_исходные!E12))) -> +7 (903) 123-45-67 | F12: =IF(ISBLANK(Поставщики_исходные!F12),"",IF(ISNUMBER(FIND(".",MID(Поставщики_исходные!F12,FIND("@",Поставщики_исходные!F12)+1,255))),Поставщики_исходные!F12,IF(ISNUMBER(FIND("gmail",Поставщики_исходные!F12)),Поставщики_исходные!F12&".com",Поставщики_исходные!F12&".ru"))) -> service@plus.ru | G12: =TRIM(Поставщики_исходные!G12) -> 199178 г.Санкт-Петербург ул.Средний пр.В.О.д.78 | H12: =IF(ISNUMBER(VALUE(LEFT(TRIM(Поставщики_исходные!G12),6))),LEFT(TRIM(Поставщики_исходные!G12),6),"") -> 199178 | I12: =TRIM(MID(TRIM(Поставщики_исходные!G12),7,255)) -> г.Санкт-Петербург ул.Средний пр.В.О.д.78 | J12: =IF(OR(LEN(C12)=10,LEN(C12)=12),"OK","Ошибка ИНН") -> OK | K12: =IF(AND(ISNUMBER(FIND("@",F12)),ISNUMBER(FIND(".",MID(F12,FIND("@",F12)+1,255)))),"OK","Ошибка Email") -> OK
A13: =Поставщики_исходные!A13 -> P012 | B13: =PROPER(TRIM(Поставщики_исходные!B13)) -> Ао Технотрейд | C13: =IF(ISBLANK(Поставщики_исходные!C11),"",TRIM(Поставщики_исходные!C11)) -> 7715678901 | D13: =Поставщики_исходные!D13 -> 771401001 | E13: =IF(ISBLANK(Поставщики_исходные!E13),"",IF(LEN(SUBSTITUTE(SUBSTITUTE(SUBSTITUTE(SUBSTITUTE(SUBSTITUTE(Поставщики_исходные!E13," ",""),"-",""),"+",""),"(",""),")",""))=11,"+7 ("&MID(IF(LEFT(SUBSTITUTE(SUBSTITUTE(SUBSTITUTE(SUBSTITUTE(SUBSTITUTE(Поставщики_исходные!E13," ",""),"-",""),"+",""),"(",""),")",""))="8","7"&MID(SUBSTITUTE(SUBSTITUTE(SUBSTITUTE(SUBSTITUTE(SUBSTITUTE(Поставщики_исходные!E13," ",""),"-",""),"+",""),"(",""),")",""),2,10),SUBSTITUTE(SUBSTITUTE(SUBSTITUTE(SUBSTITUTE(SUBSTITUTE(Поставщики_исходные!E13," ",""),"-",""),"+",""),"(",""),")","")),2,3)&") "&MID(IF(LEFT(SUBSTITUTE(SUBSTITUTE(SUBSTITUTE(SUBSTITUTE(SUBSTITUTE(Поставщики_исходные!E13," ",""),"-",""),"+",""),"(",""),")",""))="8","7"&MID(SUBSTITUTE(SUBSTITUTE(SUBSTITUTE(SUBSTITUTE(SUBSTITUTE(Поставщики_исходные!E13," ",""),"-",""),"+",""),"(",""),")",""),2,10),SUBSTITUTE(SUBSTITUTE(SUBSTITUTE(SUBSTITUTE(SUBSTITUTE(Поставщики_исходные!E13," ",""),"-",""),"+",""),"(",""),")","")),5,3)&"-"&MID(IF(LEFT(SUBSTITUTE(SUBSTITUTE(SUBSTITUTE(SUBSTITUTE(SUBSTITUTE(Поставщики_исходные!E13," ",""),"-",""),"+",""),"(",""),")",""))="8","7"&MID(SUBSTITUTE(SUBSTITUTE(SUBSTITUTE(SUBSTITUTE(SUBSTITUTE(Поставщики_исходные!E13," ",""),"-",""),"+",""),"(",""),")",""),2,10),SUBSTITUTE(SUBSTITUTE(SUBSTITUTE(SUBSTITUTE(SUBSTITUTE(Поставщики_исходные!E13," ",""),"-",""),"+",""),"(",""),")","")),8,2)&"-"&MID(IF(LEFT(SUBSTITUTE(SUBSTITUTE(SUBSTITUTE(SUBSTITUTE(SUBSTITUTE(Поставщики_исходные!E13," ",""),"-",""),"+",""),"(",""),")",""))="8","7"&MID(SUBSTITUTE(SUBSTITUTE(SUBSTITUTE(SUBSTITUTE(SUBSTITUTE(Поставщики_исходные!E13," ",""),"-",""),"+",""),"(",""),")",""),2,10),SUBSTITUTE(SUBSTITUTE(SUBSTITUTE(SUBSTITUTE(SUBSTITUTE(Поставщики_исходные!E13," ",""),"-",""),"+",""),"(",""),")","")),10,2),IF(LEN(SUBSTITUTE(SUBSTITUTE(SUBSTITUTE(SUBSTITUTE(SUBSTITUTE(Поставщики_исходные!E13," ",""),"-",""),"+",""),"(",""),")",""))=10,"+7 ("&MID(SUBSTITUTE(SUBSTITUTE(SUBSTITUTE(SUBSTITUTE(SUBSTITUTE(Поставщики_исходные!E13," ",""),"-",""),"+",""),"(",""),")",""),1,3)&") "&MID(SUBSTITUTE(SUBSTITUTE(SUBSTITUTE(SUBSTITUTE(SUBSTITUTE(Поставщики_исходные!E13," ",""),"-",""),"+",""),"(",""),")",""),4,3)&"-"&MID(SUBSTITUTE(SUBSTITUTE(SUBSTITUTE(SUBSTITUTE(SUBSTITUTE(Поставщики_исходные!E13," ",""),"-",""),"+",""),"(",""),")",""),6,2)&"-"&MID(SUBSTITUTE(SUBSTITUTE(SUBSTITUTE(SUBSTITUTE(SUBSTITUTE(Поставщики_исходные!E13," ",""),"-",""),"+",""),"(",""),")",""),8,2),Поставщики_исходные!E13))) -> +7 (903) 234-56-78 | F13: =IF(ISBLANK(Поставщики_исходные!F13),"",IF(ISNUMBER(FIND(".",MID(Поставщики_исходные!F13,FIND("@",Поставщики_исходные!F13)+1,255))),Поставщики_исходные!F13,IF(ISNUMBER(FIND("gmail",Поставщики_исходные!F13)),Поставщики_исходные!F13&".com",Поставщики_исходные!F13&".ru"))) -> trade@tehno.ru | G13: =TRIM(Поставщики_исходные!G13) -> 107113 г.Москва ул.Сокольнический вал д.3 | H13: =IF(ISNUMBER(VALUE(LEFT(TRIM(Поставщики_исходные!G13),6))),LEFT(TRIM(Поставщики_исходные!G13),6),"") -> 107113 | I13: =TRIM(MID(TRIM(Поставщики_исходные!G13),7,255)) -> г.Москва ул.Сокольнический вал д.3 | J13: =IF(OR(LEN(C13)=10,LEN(C13)=12),"OK","Ошибка ИНН") -> OK | K13: =IF(AND(ISNUMBER(FIND("@",F13)),ISNUMBER(FIND(".",MID(F13,FIND("@",F13)+1,255)))),"OK","Ошибка Email") -> OK
A14: =Поставщики_исходные!A14 -> P013 | B14: =PROPER(TRIM(Поставщики_исходные!B14)) -> Ооо Ресурсснаб | C14: =IF(ISBLANK(Поставщики_исходные!C12),"",TRIM(Поставщики_исходные!C12)) -> 78045678 | D14: =Поставщики_исходные!D14 -> 780501001 | E14: =IF(ISBLANK(Поставщики_исходные!E14),"",IF(LEN(SUBSTITUTE(SUBSTITUTE(SUBSTITUTE(SUBSTITUTE(SUBSTITUTE(Поставщики_исходные!E14," ",""),"-",""),"+",""),"(",""),")",""))=11,"+7 ("&MID(IF(LEFT(SUBSTITUTE(SUBSTITUTE(SUBSTITUTE(SUBSTITUTE(SUBSTITUTE(Поставщики_исходные!E14," ",""),"-",""),"+",""),"(",""),")",""))="8","7"&MID(SUBSTITUTE(SUBSTITUTE(SUBSTITUTE(SUBSTITUTE(SUBSTITUTE(Поставщики_исходные!E14," ",""),"-",""),"+",""),"(",""),")",""),2,10),SUBSTITUTE(SUBSTITUTE(SUBSTITUTE(SUBSTITUTE(SUBSTITUTE(Поставщики_исходные!E14," ",""),"-",""),"+",""),"(",""),")","")),2,3)&") "&MID(IF(LEFT(SUBSTITUTE(SUBSTITUTE(SUBSTITUTE(SUBSTITUTE(SUBSTITUTE(Поставщики_исходные!E14," ",""),"-",""),"+",""),"(",""),")",""))="8","7"&MID(SUBSTITUTE(SUBSTITUTE(SUBSTITUTE(SUBSTITUTE(SUBSTITUTE(Поставщики_исходные!E14," ",""),"-",""),"+",""),"(",""),")",""),2,10),SUBSTITUTE(SUBSTITUTE(SUBSTITUTE(SUBSTITUTE(SUBSTITUTE(Поставщики_исходные!E14," ",""),"-",""),"+",""),"(",""),")","")),5,3)&"-"&MID(IF(LEFT(SUBSTITUTE(SUBSTITUTE(SUBSTITUTE(SUBSTITUTE(SUBSTITUTE(Поставщики_исходные!E14," ",""),"-",""),"+",""),"(",""),")",""))="8","7"&MID(SUBSTITUTE(SUBSTITUTE(SUBSTITUTE(SUBSTITUTE(SUBSTITUTE(Поставщики_исходные!E14," ",""),"-",""),"+",""),"(",""),")",""),2,10),SUBSTITUTE(SUBSTITUTE(SUBSTITUTE(SUBSTITUTE(SUBSTITUTE(Поставщики_исходные!E14," ",""),"-",""),"+",""),"(",""),")","")),8,2)&"-"&MID(IF(LEFT(SUBSTITUTE(SUBSTITUTE(SUBSTITUTE(SUBSTITUTE(SUBSTITUTE(Поставщики_исходные!E14," ",""),"-",""),"+",""),"(",""),")",""))="8","7"&MID(SUBSTITUTE(SUBSTITUTE(SUBSTITUTE(SUBSTITUTE(SUBSTITUTE(Поставщики_исходные!E14," ",""),"-",""),"+",""),"(",""),")",""),2,10),SUBSTITUTE(SUBSTITUTE(SUBSTITUTE(SUBSTITUTE(SUBSTITUTE(Поставщики_исходные!E14," ",""),"-",""),"+",""),"(",""),")","")),10,2),IF(LEN(SUBSTITUTE(SUBSTITUTE(SUBSTITUTE(SUBSTITUTE(SUBSTITUTE(Поставщики_исходные!E14," ",""),"-",""),"+",""),"(",""),")",""))=10,"+7 ("&MID(SUBSTITUTE(SUBSTITUTE(SUBSTITUTE(SUBSTITUTE(SUBSTITUTE(Поставщики_исходные!E14," ",""),"-",""),"+",""),"(",""),")",""),1,3)&") "&MID(SUBSTITUTE(SUBSTITUTE(SUBSTITUTE(SUBSTITUTE(SUBSTITUTE(Поставщики_исходные!E14," ",""),"-",""),"+",""),"(",""),")",""),4,3)&"-"&MID(SUBSTITUTE(SUBSTITUTE(SUBSTITUTE(SUBSTITUTE(SUBSTITUTE(Поставщики_исходные!E14," ",""),"-",""),"+",""),"(",""),")",""),6,2)&"-"&MID(SUBSTITUTE(SUBSTITUTE(SUBSTITUTE(SUBSTITUTE(SUBSTITUTE(Поставщики_исходные!E14," ",""),"-",""),"+",""),"(",""),")",""),8,2),Поставщики_исходные!E14))) -> +7 (903) 345-67-89 | F14: =IF(ISBLANK(Поставщики_исходные!F14),"",IF(ISNUMBER(FIND(".",MID(Поставщики_исходные!F14,FIND("@",Поставщики_исходные!F14)+1,255))),Поставщики_исходные!F14,IF(ISNUMBER(FIND("gmail",Поставщики_исходные!F14)),Поставщики_исходные!F14&".com",Поставщики_исходные!F14&".ru"))) -> resurs_snab@mail.ru | G14: =TRIM(Поставщики_исходные!G14) -> 196247 г.Санкт-Петербург ул.Ленина д.45 | H14: =IF(ISNUMBER(VALUE(LEFT(TRIM(Поставщики_исходные!G14),6))),LEFT(TRIM(Поставщики_исходные!G14),6),"") -> 196247 | I14: =TRIM(MID(TRIM(Поставщики_исходные!G14),7,255)) -> г.Санкт-Петербург ул.Ленина д.45 | J14: =IF(OR(LEN(C14)=10,LEN(C14)=12),"OK","Ошибка ИНН") -> Ошибка ИНН | K14: =IF(AND(ISNUMBER(FIND("@",F14)),ISNUMBER(FIND(".",MID(F14,FIND("@",F14)+1,255)))),"OK","Ошибка Email") -> OK
A15: =Поставщики_исходные!A15 -> P014 | B15: =PROPER(TRIM(Поставщики_исходные!B15)) -> Зао Техносервис | C15: =IF(ISBLANK(Поставщики_исходные!C13),"",TRIM(Поставщики_исходные!C13)) -> 7716789012 | D15: =Поставщики_исходные!D15 -> 771501001 | E15: =IF(ISBLANK(Поставщики_исходные!E15),"",IF(LEN(SUBSTITUTE(SUBSTITUTE(SUBSTITUTE(SUBSTITUTE(SUBSTITUTE(Поставщики_исходные!E15," ",""),"-",""),"+",""),"(",""),")",""))=11,"+7 ("&MID(IF(LEFT(SUBSTITUTE(SUBSTITUTE(SUBSTITUTE(SUBSTITUTE(SUBSTITUTE(Поставщики_исходные!E15," ",""),"-",""),"+",""),"(",""),")",""))="8","7"&MID(SUBSTITUTE(SUBSTITUTE(SUBSTITUTE(SUBSTITUTE(SUBSTITUTE(Поставщики_исходные!E15," ",""),"-",""),"+",""),"(",""),")",""),2,10),SUBSTITUTE(SUBSTITUTE(SUBSTITUTE(SUBSTITUTE(SUBSTITUTE(Поставщики_исходные!E15," ",""),"-",""),"+",""),"(",""),")","")),2,3)&") "&MID(IF(LEFT(SUBSTITUTE(SUBSTITUTE(SUBSTITUTE(SUBSTITUTE(SUBSTITUTE(Поставщики_исходные!E15," ",""),"-",""),"+",""),"(",""),")",""))="8","7"&MID(SUBSTITUTE(SUBSTITUTE(SUBSTITUTE(SUBSTITUTE(SUBSTITUTE(Поставщики_исходные!E15," ",""),"-",""),"+",""),"(",""),")",""),2,10),SUBSTITUTE(SUBSTITUTE(SUBSTITUTE(SUBSTITUTE(SUBSTITUTE(Поставщики_исходные!E15," ",""),"-",""),"+",""),"(",""),")","")),5,3)&"-"&MID(IF(LEFT(SUBSTITUTE(SUBSTITUTE(SUBSTITUTE(SUBSTITUTE(SUBSTITUTE(Поставщики_исходные!E15," ",""),"-",""),"+",""),"(",""),")",""))="8","7"&MID(SUBSTITUTE(SUBSTITUTE(SUBSTITUTE(SUBSTITUTE(SUBSTITUTE(Поставщики_исходные!E15," ",""),"-",""),"+",""),"(",""),")",""),2,10),SUBSTITUTE(SUBSTITUTE(SUBSTITUTE(SUBSTITUTE(SUBSTITUTE(Поставщики_исходные!E15," ",""),"-",""),"+",""),"(",""),")","")),8,2)&"-"&MID(IF(LEFT(SUBSTITUTE(SUBSTITUTE(SUBSTITUTE(SUBSTITUTE(SUBSTITUTE(Поставщики_исходные!E15," ",""),"-",""),"+",""),"(",""),")",""))="8","7"&MID(SUBSTITUTE(SUBSTITUTE(SUBSTITUTE(SUBSTITUTE(SUBSTITUTE(Поставщики_исходные!E15," ",""),"-",""),"+",""),"(",""),")",""),2,10),SUBSTITUTE(SUBSTITUTE(SUBSTITUTE(SUBSTITUTE(SUBSTITUTE(Поставщики_исходные!E15," ",""),"-",""),"+",""),"(",""),")","")),10,2),IF(LEN(SUBSTITUTE(SUBSTITUTE(SUBSTITUTE(SUBSTITUTE(SUBSTITUTE(Поставщики_исходные!E15," ",""),"-",""),"+",""),"(",""),")",""))=10,"+7 ("&MID(SUBSTITUTE(SUBSTITUTE(SUBSTITUTE(SUBSTITUTE(SUBSTITUTE(Поставщики_исходные!E15," ",""),"-",""),"+",""),"(",""),")",""),1,3)&") "&MID(SUBSTITUTE(SUBSTITUTE(SUBSTITUTE(SUBSTITUTE(SUBSTITUTE(Поставщики_исходные!E15," ",""),"-",""),"+",""),"(",""),")",""),4,3)&"-"&MID(SUBSTITUTE(SUBSTITUTE(SUBSTITUTE(SUBSTITUTE(SUBSTITUTE(Поставщики_исходные!E15," ",""),"-",""),"+",""),"(",""),")",""),6,2)&"-"&MID(SUBSTITUTE(SUBSTITUTE(SUBSTITUTE(SUBSTITUTE(SUBSTITUTE(Поставщики_исходные!E15," ",""),"-",""),"+",""),"(",""),")",""),8,2),Поставщики_исходные!E15))) -> +7 (903) 456-78-90 | F15: =IF(ISBLANK(Поставщики_исходные!F15),"",IF(ISNUMBER(FIND(".",MID(Поставщики_исходные!F15,FIND("@",Поставщики_исходные!F15)+1,255))),Поставщики_исходные!F15,IF(ISNUMBER(FIND("gmail",Поставщики_исходные!F15)),Поставщики_исходные!F15&".com",Поставщики_исходные!F15&".ru"))) -> service@tehno.ru | G15: =TRIM(Поставщики_исходные!G15) -> 109147 г.Москва ул.Марксистская д.30 | H15: =IF(ISNUMBER(VALUE(LEFT(TRIM(Поставщики_исходные!G15),6))),LEFT(TRIM(Поставщики_исходные!G15),6),"") -> 109147 | I15: =TRIM(MID(TRIM(Поставщики_исходные!G15),7,255)) -> г.Москва ул.Марксистская д.30 | J15: =IF(OR(LEN(C15)=10,LEN(C15)=12),"OK","Ошибка ИНН") -> OK | K15: =IF(AND(ISNUMBER(FIND("@",F15)),ISNUMBER(FIND(".",MID(F15,FIND("@",F15)+1,255)))),"OK","Ошибка Email") -> OK
A16: =Поставщики_исходные!A16 -> P015 | B16: =PROPER(TRIM(Поставщики_исходные!B16)) -> Ооо Электротехника | C16: =IF(ISBLANK(Поставщики_исходные!C14),"",TRIM(Поставщики_исходные!C14)) -> 7805678901234 | D16: =Поставщики_исходные!D16 -> 780601001 | E16: =IF(ISBLANK(Поставщики_исходные!E16),"",IF(LEN(SUBSTITUTE(SUBSTITUTE(SUBSTITUTE(SUBSTITUTE(SUBSTITUTE(Поставщики_исходные!E16," ",""),"-",""),"+",""),"(",""),")",""))=11,"+7 ("&MID(IF(LEFT(SUBSTITUTE(SUBSTITUTE(SUBSTITUTE(SUBSTITUTE(SUBSTITUTE(Поставщики_исходные!E16," ",""),"-",""),"+",""),"(",""),")",""))="8","7"&MID(SUBSTITUTE(SUBSTITUTE(SUBSTITUTE(SUBSTITUTE(SUBSTITUTE(Поставщики_исходные!E16," ",""),"-",""),"+",""),"(",""),")",""),2,10),SUBSTITUTE(SUBSTITUTE(SUBSTITUTE(SUBSTITUTE(SUBSTITUTE(Поставщики_исходные!E16," ",""),"-",""),"+",""),"(",""),")","")),2,3)&") "&MID(IF(LEFT(SUBSTITUTE(SUBSTITUTE(SUBSTITUTE(SUBSTITUTE(SUBSTITUTE(Поставщики_исходные!E16," ",""),"-",""),"+",""),"(",""),")",""))="8","7"&MID(SUBSTITUTE(SUBSTITUTE(SUBSTITUTE(SUBSTITUTE(SUBSTITUTE(Поставщики_исходные!E16," ",""),"-",""),"+",""),"(",""),")",""),2,10),SUBSTITUTE(SUBSTITUTE(SUBSTITUTE(SUBSTITUTE(SUBSTITUTE(Поставщики_исходные!E16," ",""),"-",""),"+",""),"(",""),")","")),5,3)&"-"&MID(IF(LEFT(SUBSTITUTE(SUBSTITUTE(SUBSTITUTE(SUBSTITUTE(SUBSTITUTE(Поставщики_исходные!E16," ",""),"-",""),"+",""),"(",""),")",""))="8","7"&MID(SUBSTITUTE(SUBSTITUTE(SUBSTITUTE(SUBSTITUTE(SUBSTITUTE(Поставщики_исходные!E16," ",""),"-",""),"+",""),"(",""),")",""),2,10),SUBSTITUTE(SUBSTITUTE(SUBSTITUTE(SUBSTITUTE(SUBSTITUTE(Поставщики_исходные!E16," ",""),"-",""),"+",""),"(",""),")","")),8,2)&"-"&MID(IF(LEFT(SUBSTITUTE(SUBSTITUTE(SUBSTITUTE(SUBSTITUTE(SUBSTITUTE(Поставщики_исходные!E16," ",""),"-",""),"+",""),"(",""),")",""))="8","7"&MID(SUBSTITUTE(SUBSTITUTE(SUBSTITUTE(SUBSTITUTE(SUBSTITUTE(Поставщики_исходные!E16," ",""),"-",""),"+",""),"(",""),")",""),2,10),SUBSTITUTE(SUBSTITUTE(SUBSTITUTE(SUBSTITUTE(SUBSTITUTE(Поставщики_исходные!E16," ",""),"-",""),"+",""),"(",""),")","")),10,2),IF(LEN(SUBSTITUTE(SUBSTITUTE(SUBSTITUTE(SUBSTITUTE(SUBSTITUTE(Поставщики_исходные!E16," ",""),"-",""),"+",""),"(",""),")",""))=10,"+7 ("&MID(SUBSTITUTE(SUBSTITUTE(SUBSTITUTE(SUBSTITUTE(SUBSTITUTE(Поставщики_исходные!E16," ",""),"-",""),"+",""),"(",""),")",""),1,3)&") "&MID(SUBSTITUTE(SUBSTITUTE(SUBSTITUTE(SUBSTITUTE(SUBSTITUTE(Поставщики_исходные!E16," ",""),"-",""),"+",""),"(",""),")",""),4,3)&"-"&MID(SUBSTITUTE(SUBSTITUTE(SUBSTITUTE(SUBSTITUTE(SUBSTITUTE(Поставщики_исходные!E16," ",""),"-",""),"+",""),"(",""),")",""),6,2)&"-"&MID(SUBSTITUTE(SUBSTITUTE(SUBSTITUTE(SUBSTITUTE(SUBSTITUTE(Поставщики_исходные!E16," ",""),"-",""),"+",""),"(",""),")",""),8,2),Поставщики_исходные!E16))) -> +7 (903) 567-89-01 | F16: =IF(ISBLANK(Поставщики_исходные!F16),"",IF(ISNUMBER(FIND(".",MID(Поставщики_исходные!F16,FIND("@",Поставщики_исходные!F16)+1,255))),Поставщики_исходные!F16,IF(ISNUMBER(FIND("gmail",Поставщики_исходные!F16)),Поставщики_исходные!F16&".com",Поставщики_исходные!F16&".ru"))) -> electro@tehnika.ru | G16: =TRIM(Поставщики_исходные!G16) -> 192236 г.Санкт-Петербург ул.Софийская д.55 | H16: =IF(ISNUMBER(VALUE(LEFT(TRIM(Поставщики_исходные!G16),6))),LEFT(TRIM(Поставщики_исходные!G16),6),"") -> 192236 | I16: =TRIM(MID(TRIM(Поставщики_исходные!G16),7,255)) -> г.Санкт-Петербург ул.Софийская д.55 | J16: =IF(OR(LEN(C16)=10,LEN(C16)=12),"OK","Ошибка ИНН") -> Ошибка ИНН | K16: =IF(AND(ISNUMBER(FIND("@",F16)),ISNUMBER(FIND(".",MID(F16,FIND("@",F16)+1,255)))),"OK","Ошибка Email") -> OK
A17: =Поставщики_исходные!A17 -> P016 | B17: =PROPER(TRIM(Поставщики_исходные!B17)) -> Ао Профтехно | C17: =IF(ISBLANK(Поставщики_исходные!C15),"",TRIM(Поставщики_исходные!C15)) -> 7717890123 | D17: =Поставщики_исходные!D17 -> 771601001 | E17: =IF(ISBLANK(Поставщики_исходные!E17),"",IF(LEN(SUBSTITUTE(SUBSTITUTE(SUBSTITUTE(SUBSTITUTE(SUBSTITUTE(Поставщики_исходные!E17," ",""),"-",""),"+",""),"(",""),")",""))=11,"+7 ("&MID(IF(LEFT(SUBSTITUTE(SUBSTITUTE(SUBSTITUTE(SUBSTITUTE(SUBSTITUTE(Поставщики_исходные!E17," ",""),"-",""),"+",""),"(",""),")",""))="8","7"&MID(SUBSTITUTE(SUBSTITUTE(SUBSTITUTE(SUBSTITUTE(SUBSTITUTE(Поставщики_исходные!E17," ",""),"-",""),"+",""),"(",""),")",""),2,10),SUBSTITUTE(SUBSTITUTE(SUBSTITUTE(SUBSTITUTE(SUBSTITUTE(Поставщики_исходные!E17," ",""),"-",""),"+",""),"(",""),")","")),2,3)&") "&MID(IF(LEFT(SUBSTITUTE(SUBSTITUTE(SUBSTITUTE(SUBSTITUTE(SUBSTITUTE(Поставщики_исходные!E17," ",""),"-",""),"+",""),"(",""),")",""))="8","7"&MID(SUBSTITUTE(SUBSTITUTE(SUBSTITUTE(SUBSTITUTE(SUBSTITUTE(Поставщики_исходные!E17," ",""),"-",""),"+",""),"(",""),")",""),2,10),SUBSTITUTE(SUBSTITUTE(SUBSTITUTE(SUBSTITUTE(SUBSTITUTE(Поставщики_исходные!E17," ",""),"-",""),"+",""),"(",""),")","")),5,3)&"-"&MID(IF(LEFT(SUBSTITUTE(SUBSTITUTE(SUBSTITUTE(SUBSTITUTE(SUBSTITUTE(Поставщики_исходные!E17," ",""),"-",""),"+",""),"(",""),")",""))="8","7"&MID(SUBSTITUTE(SUBSTITUTE(SUBSTITUTE(SUBSTITUTE(SUBSTITUTE(Поставщики_исходные!E17," ",""),"-",""),"+",""),"(",""),")",""),2,10),SUBSTITUTE(SUBSTITUTE(SUBSTITUTE(SUBSTITUTE(SUBSTITUTE(Поставщики_исходные!E17," ",""),"-",""),"+",""),"(",""),")","")),8,2)&"-"&MID(IF(LEFT(SUBSTITUTE(SUBSTITUTE(SUBSTITUTE(SUBSTITUTE(SUBSTITUTE(Поставщики_исходные!E17," ",""),"-",""),"+",""),"(",""),")",""))="8","7"&MID(SUBSTITUTE(SUBSTITUTE(SUBSTITUTE(SUBSTITUTE(SUBSTITUTE(Поставщики_исходные!E17," ",""),"-",""),"+",""),"(",""),")",""),2,10),SUBSTITUTE(SUBSTITUTE(SUBSTITUTE(SUBSTITUTE(SUBSTITUTE(Поставщики_исходные!E17," ",""),"-",""),"+",""),"(",""),")","")),10,2),IF(LEN(SUBSTITUTE(SUBSTITUTE(SUBSTITUTE(SUBSTITUTE(SUBSTITUTE(Поставщики_исходные!E17," ",""),"-",""),"+",""),"(",""),")",""))=10,"+7 ("&MID(SUBSTITUTE(SUBSTITUTE(SUBSTITUTE(SUBSTITUTE(SUBSTITUTE(Поставщики_исходные!E17," ",""),"-",""),"+",""),"(",""),")",""),1,3)&") "&MID(SUBSTITUTE(SUBSTITUTE(SUBSTITUTE(SUBSTITUTE(SUBSTITUTE(Поставщики_исходные!E17," ",""),"-",""),"+",""),"(",""),")",""),4,3)&"-"&MID(SUBSTITUTE(SUBSTITUTE(SUBSTITUTE(SUBSTITUTE(SUBSTITUTE(Поставщики_исходные!E17," ",""),"-",""),"+",""),"(",""),")",""),6,2)&"-"&MID(SUBSTITUTE(SUBSTITUTE(SUBSTITUTE(SUBSTITUTE(SUBSTITUTE(Поставщики_исходные!E17," ",""),"-",""),"+",""),"(",""),")",""),8,2),Поставщики_исходные!E17))) -> +7 (903) 678-90-12 | F17: =IF(ISBLANK(Поставщики_исходные!F17),"",IF(ISNUMBER(FIND(".",MID(Поставщики_исходные!F17,FIND("@",Поставщики_исходные!F17)+1,255))),Поставщики_исходные!F17,IF(ISNUMBER(FIND("gmail",Поставщики_исходные!F17)),Поставщики_исходные!F17&".com",Поставщики_исходные!F17&".ru"))) -> prof@tehno.ru | G17: =TRIM(Поставщики_исходные!G17) -> 109052 г.Москва ул.Смирновская д.8 | H17: =IF(ISNUMBER(VALUE(LEFT(TRIM(Поставщики_исходные!G17),6))),LEFT(TRIM(Поставщики_исходные!G17),6),"") -> 109052 | I17: =TRIM(MID(TRIM(Поставщики_исходные!G17),7,255)) -> г.Москва ул.Смирновская д.8 | J17: =IF(OR(LEN(C17)=10,LEN(C17)=12),"OK","Ошибка ИНН") -> OK | K17: =IF(AND(ISNUMBER(FIND("@",F17)),ISNUMBER(FIND(".",MID(F17,FIND("@",F17)+1,255)))),"OK","Ошибка Email") -> OK
A18: =Поставщики_исходные!A18 -> P017 | B18: =PROPER(TRIM(Поставщики_исходные!B18)) -> Ооо Технокомплект | C18: =IF(ISBLANK(Поставщики_исходные!C16),"",TRIM(Поставщики_исходные!C16)) -> 7806789012 | D18: =Поставщики_исходные!D18 -> 780701001 | E18: =IF(ISBLANK(Поставщики_исходные!E18),"",IF(LEN(SUBSTITUTE(SUBSTITUTE(SUBSTITUTE(SUBSTITUTE(SUBSTITUTE(Поставщики_исходные!E18," ",""),"-",""),"+",""),"(",""),")",""))=11,"+7 ("&MID(IF(LEFT(SUBSTITUTE(SUBSTITUTE(SUBSTITUTE(SUBSTITUTE(SUBSTITUTE(Поставщики_исходные!E18," ",""),"-",""),"+",""),"(",""),")",""))="8","7"&MID(SUBSTITUTE(SUBSTITUTE(SUBSTITUTE(SUBSTITUTE(SUBSTITUTE(Поставщики_исходные!E18," ",""),"-",""),"+",""),"(",""),")",""),2,10),SUBSTITUTE(SUBSTITUTE(SUBSTITUTE(SUBSTITUTE(SUBSTITUTE(Поставщики_исходные!E18," ",""),"-",""),"+",""),"(",""),")","")),2,3)&") "&MID(IF(LEFT(SUBSTITUTE(SUBSTITUTE(SUBSTITUTE(SUBSTITUTE(SUBSTITUTE(Поставщики_исходные!E18," ",""),"-",""),"+",""),"(",""),")",""))="8","7"&MID(SUBSTITUTE(SUBSTITUTE(SUBSTITUTE(SUBSTITUTE(SUBSTITUTE(Поставщики_исходные!E18," ",""),"-",""),"+",""),"(",""),")",""),2,10),SUBSTITUTE(SUBSTITUTE(SUBSTITUTE(SUBSTITUTE(SUBSTITUTE(Поставщики_исходные!E18," ",""),"-",""),"+",""),"(",""),")","")),5,3)&"-"&MID(IF(LEFT(SUBSTITUTE(SUBSTITUTE(SUBSTITUTE(SUBSTITUTE(SUBSTITUTE(Поставщики_исходные!E18," ",""),"-",""),"+",""),"(",""),")",""))="8","7"&MID(SUBSTITUTE(SUBSTITUTE(SUBSTITUTE(SUBSTITUTE(SUBSTITUTE(Поставщики_исходные!E18," ",""),"-",""),"+",""),"(",""),")",""),2,10),SUBSTITUTE(SUBSTITUTE(SUBSTITUTE(SUBSTITUTE(SUBSTITUTE(Поставщики_исходные!E18," ",""),"-",""),"+",""),"(",""),")","")),8,2)&"-"&MID(IF(LEFT(SUBSTITUTE(SUBSTITUTE(SUBSTITUTE(SUBSTITUTE(SUBSTITUTE(Поставщики_исходные!E18," ",""),"-",""),"+",""),"(",""),")",""))="8","7"&MID(SUBSTITUTE(SUBSTITUTE(SUBSTITUTE(SUBSTITUTE(SUBSTITUTE(Поставщики_исходные!E18," ",""),"-",""),"+",""),"(",""),")",""),2,10),SUBSTITUTE(SUBSTITUTE(SUBSTITUTE(SUBSTITUTE(SUBSTITUTE(Поставщики_исходные!E18," ",""),"-",""),"+",""),"(",""),")","")),10,2),IF(LEN(SUBSTITUTE(SUBSTITUTE(SUBSTITUTE(SUBSTITUTE(SUBSTITUTE(Поставщики_исходные!E18," ",""),"-",""),"+",""),"(",""),")",""))=10,"+7 ("&MID(SUBSTITUTE(SUBSTITUTE(SUBSTITUTE(SUBSTITUTE(SUBSTITUTE(Поставщики_исходные!E18," ",""),"-",""),"+",""),"(",""),")",""),1,3)&") "&MID(SUBSTITUTE(SUBSTITUTE(SUBSTITUTE(SUBSTITUTE(SUBSTITUTE(Поставщики_исходные!E18," ",""),"-",""),"+",""),"(",""),")",""),4,3)&"-"&MID(SUBSTITUTE(SUBSTITUTE(SUBSTITUTE(SUBSTITUTE(SUBSTITUTE(Поставщики_исходные!E18," ",""),"-",""),"+",""),"(",""),")",""),6,2)&"-"&MID(SUBSTITUTE(SUBSTITUTE(SUBSTITUTE(SUBSTITUTE(SUBSTITUTE(Поставщики_исходные!E18," ",""),"-",""),"+",""),"(",""),")",""),8,2),Поставщики_исходные!E18))) -> +7 (903) 789-01-23 | F18: =IF(ISBLANK(Поставщики_исходные!F18),"",IF(ISNUMBER(FIND(".",MID(Поставщики_исходные!F18,FIND("@",Поставщики_исходные!F18)+1,255))),Поставщики_исходные!F18,IF(ISNUMBER(FIND("gmail",Поставщики_исходные!F18)),Поставщики_исходные!F18&".com",Поставщики_исходные!F18&".ru"))) -> komplekt@tehno.ru | G18: =TRIM(Поставщики_исходные!G18) -> 193079 г.Санкт-Петербург ул.Новоселов д.12 | H18: =IF(ISNUMBER(VALUE(LEFT(TRIM(Поставщики_исходные!G18),6))),LEFT(TRIM(Поставщики_исходные!G18),6),"") -> 193079 | I18: =TRIM(MID(TRIM(Поставщики_исходные!G18),7,255)) -> г.Санкт-Петербург ул.Новоселов д.12 | J18: =IF(OR(LEN(C18)=10,LEN(C18)=12),"OK","Ошибка ИНН") -> OK | K18: =IF(AND(ISNUMBER(FIND("@",F18)),ISNUMBER(FIND(".",MID(F18,FIND("@",F18)+1,255)))),"OK","Ошибка Email") -> OK
A19: =Поставщики_исходные!A19 -> P018 | B19: =PROPER(TRIM(Поставщики_исходные!B19)) -> Зао Инновация | C19: =IF(ISBLANK(Поставщики_исходные!C17),"",TRIM(Поставщики_исходные!C17)) -> 7718901234 | D19: =Поставщики_исходные!D19 -> 771701001 | E19: =IF(ISBLANK(Поставщики_исходные!E19),"",IF(LEN(SUBSTITUTE(SUBSTITUTE(SUBSTITUTE(SUBSTITUTE(SUBSTITUTE(Поставщики_исходные!E19," ",""),"-",""),"+",""),"(",""),")",""))=11,"+7 ("&MID(IF(LEFT(SUBSTITUTE(SUBSTITUTE(SUBSTITUTE(SUBSTITUTE(SUBSTITUTE(Поставщики_исходные!E19," ",""),"-",""),"+",""),"(",""),")",""))="8","7"&MID(SUBSTITUTE(SUBSTITUTE(SUBSTITUTE(SUBSTITUTE(SUBSTITUTE(Поставщики_исходные!E19," ",""),"-",""),"+",""),"(",""),")",""),2,10),SUBSTITUTE(SUBSTITUTE(SUBSTITUTE(SUBSTITUTE(SUBSTITUTE(Поставщики_исходные!E19," ",""),"-",""),"+",""),"(",""),")","")),2,3)&") "&MID(IF(LEFT(SUBSTITUTE(SUBSTITUTE(SUBSTITUTE(SUBSTITUTE(SUBSTITUTE(Поставщики_исходные!E19," ",""),"-",""),"+",""),"(",""),")",""))="8","7"&MID(SUBSTITUTE(SUBSTITUTE(SUBSTITUTE(SUBSTITUTE(SUBSTITUTE(Поставщики_исходные!E19," ",""),"-",""),"+",""),"(",""),")",""),2,10),SUBSTITUTE(SUBSTITUTE(SUBSTITUTE(SUBSTITUTE(SUBSTITUTE(Поставщики_исходные!E19," ",""),"-",""),"+",""),"(",""),")","")),5,3)&"-"&MID(IF(LEFT(SUBSTITUTE(SUBSTITUTE(SUBSTITUTE(SUBSTITUTE(SUBSTITUTE(Поставщики_исходные!E19," ",""),"-",""),"+",""),"(",""),")",""))="8","7"&MID(SUBSTITUTE(SUBSTITUTE(SUBSTITUTE(SUBSTITUTE(SUBSTITUTE(Поставщики_исходные!E19," ",""),"-",""),"+",""),"(",""),")",""),2,10),SUBSTITUTE(SUBSTITUTE(SUBSTITUTE(SUBSTITUTE(SUBSTITUTE(Поставщики_исходные!E19," ",""),"-",""),"+",""),"(",""),")","")),8,2)&"-"&MID(IF(LEFT(SUBSTITUTE(SUBSTITUTE(SUBSTITUTE(SUBSTITUTE(SUBSTITUTE(Поставщики_исходные!E19," ",""),"-",""),"+",""),"(",""),")",""))="8","7"&MID(SUBSTITUTE(SUBSTITUTE(SUBSTITUTE(SUBSTITUTE(SUBSTITUTE(Поставщики_исходные!E19," ",""),"-",""),"+",""),"(",""),")",""),2,10),SUBSTITUTE(SUBSTITUTE(SUBSTITUTE(SUBSTITUTE(SUBSTITUTE(Поставщики_исходные!E19," ",""),"-",""),"+",""),"(",""),")","")),10,2),IF(LEN(SUBSTITUTE(SUBSTITUTE(SUBSTITUTE(SUBSTITUTE(SUBSTITUTE(Поставщики_исходные!E19," ",""),"-",""),"+",""),"(",""),")",""))=10,"+7 ("&MID(SUBSTITUTE(SUBSTITUTE(SUBSTITUTE(SUBSTITUTE(SUBSTITUTE(Поставщики_исходные!E19," ",""),"-",""),"+",""),"(",""),")",""),1,3)&") "&MID(SUBSTITUTE(SUBSTITUTE(SUBSTITUTE(SUBSTITUTE(SUBSTITUTE(Поставщики_исходные!E19," ",""),"-",""),"+",""),"(",""),")",""),4,3)&"-"&MID(SUBSTITUTE(SUBSTITUTE(SUBSTITUTE(SUBSTITUTE(SUBSTITUTE(Поставщики_исходные!E19," ",""),"-",""),"+",""),"(",""),")",""),6,2)&"-"&MID(SUBSTITUTE(SUBSTITUTE(SUBSTITUTE(SUBSTITUTE(SUBSTITUTE(Поставщики_исходные!E19," ",""),"-",""),"+",""),"(",""),")",""),8,2),Поставщики_исходные!E19))) -> +7 (903) 890-12-34 | F19: =IF(ISBLANK(Поставщики_исходные!F19),"",IF(ISNUMBER(FIND(".",MID(Поставщики_исходные!F19,FIND("@",Поставщики_исходные!F19)+1,255))),Поставщики_исходные!F19,IF(ISNUMBER(FIND("gmail",Поставщики_исходные!F19)),Поставщики_исходные!F19&".com",Поставщики_исходные!F19&".ru"))) -> innov@mail.ru | G19: =TRIM(Поставщики_исходные!G19) -> 109004 г.Москва ул.Земляной вал д.42 | H19: =IF(ISNUMBER(VALUE(LEFT(TRIM(Поставщики_исходные!G19),6))),LEFT(TRIM(Поставщики_исходные!G19),6),"") -> 109004 | I19: =TRIM(MID(TRIM(Поставщики_исходные!G19),7,255)) -> г.Москва ул.Земляной вал д.42 | J19: =IF(OR(LEN(C19)=10,LEN(C19)=12),"OK","Ошибка ИНН") -> OK | K19: =IF(AND(ISNUMBER(FIND("@",F19)),ISNUMBER(FIND(".",MID(F19,FIND("@",F19)+1,255)))),"OK","Ошибка Email") -> OK
A20: =Поставщики_исходные!A20 -> P019 | B20: =PROPER(TRIM(Поставщики_исходные!B20)) -> Ооо Электропром | C20: =IF(ISBLANK(Поставщики_исходные!C18),"",TRIM(Поставщики_исходные!C18)) -> 7807890 | D20: =Поставщики_исходные!D20 -> 780801001 | E20: =IF(ISBLANK(Поставщики_исходные!E20),"",IF(LEN(SUBSTITUTE(SUBSTITUTE(SUBSTITUTE(SUBSTITUTE(SUBSTITUTE(Поставщики_исходные!E20," ",""),"-",""),"+",""),"(",""),")",""))=11,"+7 ("&MID(IF(LEFT(SUBSTITUTE(SUBSTITUTE(SUBSTITUTE(SUBSTITUTE(SUBSTITUTE(Поставщики_исходные!E20," ",""),"-",""),"+",""),"(",""),")",""))="8","7"&MID(SUBSTITUTE(SUBSTITUTE(SUBSTITUTE(SUBSTITUTE(SUBSTITUTE(Поставщики_исходные!E20," ",""),"-",""),"+",""),"(",""),")",""),2,10),SUBSTITUTE(SUBSTITUTE(SUBSTITUTE(SUBSTITUTE(SUBSTITUTE(Поставщики_исходные!E20," ",""),"-",""),"+",""),"(",""),")","")),2,3)&") "&MID(IF(LEFT(SUBSTITUTE(SUBSTITUTE(SUBSTITUTE(SUBSTITUTE(SUBSTITUTE(Поставщики_исходные!E20," ",""),"-",""),"+",""),"(",""),")",""))="8","7"&MID(SUBSTITUTE(SUBSTITUTE(SUBSTITUTE(SUBSTITUTE(SUBSTITUTE(Поставщики_исходные!E20," ",""),"-",""),"+",""),"(",""),")",""),2,10),SUBSTITUTE(SUBSTITUTE(SUBSTITUTE(SUBSTITUTE(SUBSTITUTE(Поставщики_исходные!E20," ",""),"-",""),"+",""),"(",""),")","")),5,3)&"-"&MID(IF(LEFT(SUBSTITUTE(SUBSTITUTE(SUBSTITUTE(SUBSTITUTE(SUBSTITUTE(Поставщики_исходные!E20," ",""),"-",""),"+",""),"(",""),")",""))="8","7"&MID(SUBSTITUTE(SUBSTITUTE(SUBSTITUTE(SUBSTITUTE(SUBSTITUTE(Поставщики_исходные!E20," ",""),"-",""),"+",""),"(",""),")",""),2,10),SUBSTITUTE(SUBSTITUTE(SUBSTITUTE(SUBSTITUTE(SUBSTITUTE(Поставщики_исходные!E20," ",""),"-",""),"+",""),"(",""),")","")),8,2)&"-"&MID(IF(LEFT(SUBSTITUTE(SUBSTITUTE(SUBSTITUTE(SUBSTITUTE(SUBSTITUTE(Поставщики_исходные!E20," ",""),"-",""),"+",""),"(",""),")",""))="8","7"&MID(SUBSTITUTE(SUBSTITUTE(SUBSTITUTE(SUBSTITUTE(SUBSTITUTE(Поставщики_исходные!E20," ",""),"-",""),"+",""),"(",""),")",""),2,10),SUBSTITUTE(SUBSTITUTE(SUBSTITUTE(SUBSTITUTE(SUBSTITUTE(Поставщики_исходные!E20," ",""),"-",""),"+",""),"(",""),")","")),10,2),IF(LEN(SUBSTITUTE(SUBSTITUTE(SUBSTITUTE(SUBSTITUTE(SUBSTITUTE(Поставщики_исходные!E20," ",""),"-",""),"+",""),"(",""),")",""))=10,"+7 ("&MID(SUBSTITUTE(SUBSTITUTE(SUBSTITUTE(SUBSTITUTE(SUBSTITUTE(Поставщики_исходные!E20," ",""),"-",""),"+",""),"(",""),")",""),1,3)&") "&MID(SUBSTITUTE(SUBSTITUTE(SUBSTITUTE(SUBSTITUTE(SUBSTITUTE(Поставщики_исходные!E20," ",""),"-",""),"+",""),"(",""),")",""),4,3)&"-"&MID(SUBSTITUTE(SUBSTITUTE(SUBSTITUTE(SUBSTITUTE(SUBSTITUTE(Поставщики_исходные!E20," ",""),"-",""),"+",""),"(",""),")",""),6,2)&"-"&MID(SUBSTITUTE(SUBSTITUTE(SUBSTITUTE(SUBSTITUTE(SUBSTITUTE(Поставщики_исходные!E20," ",""),"-",""),"+",""),"(",""),")",""),8,2),Поставщики_исходные!E20))) -> +7 (903) 901-23-45 | F20: =IF(ISBLANK(Поставщики_исходные!F20),"",IF(ISNUMBER(FIND(".",MID(Поставщики_исходные!F20,FIND("@",Поставщики_исходные!F20)+1,255))),Поставщики_исходные!F20,IF(ISNUMBER(FIND("gmail",Поставщики_исходные!F20)),Поставщики_исходные!F20&".com",Поставщики_исходные!F20&".ru"))) -> electro_prom@mail.ru | G20: =TRIM(Поставщики_исходные!G20) -> 194100 г.Санкт-Петербург ул.Кантемировская д.18 | H20: =IF(ISNUMBER(VALUE(LEFT(TRIM(Поставщики_исходные!G20),6))),LEFT(TRIM(Поставщики_исходные!G20),6),"") -> 194100 | I20: =TRIM(MID(TRIM(Поставщики_исходные!G20),7,255)) -> г.Санкт-Петербург ул.Кантемировская д.18 | J20: =IF(OR(LEN(C20)=10,LEN(C20)=12),"OK","Ошибка ИНН") -> Ошибка ИНН | K20: =IF(AND(ISNUMBER(FIND("@",F20)),ISNUMBER(FIND(".",MID(F20,FIND("@",F20)+1,255)))),"OK","Ошибка Email") -> OK
A21: =Поставщики_исходные!A21 -> P020 | B21: =PROPER(TRIM(Поставщики_исходные!B21)) -> Ао Техноинвест | C21: =IF(ISBLANK(Поставщики_исходные!C19),"",TRIM(Поставщики_исходные!C19)) -> 7719012345 | D21: =Поставщики_исходные!D21 -> 771801001 | E21: =IF(ISBLANK(Поставщики_исходные!E21),"",IF(LEN(SUBSTITUTE(SUBSTITUTE(SUBSTITUTE(SUBSTITUTE(SUBSTITUTE(Поставщики_исходные!E21," ",""),"-",""),"+",""),"(",""),")",""))=11,"+7 ("&MID(IF(LEFT(SUBSTITUTE(SUBSTITUTE(SUBSTITUTE(SUBSTITUTE(SUBSTITUTE(Поставщики_исходные!E21," ",""),"-",""),"+",""),"(",""),")",""))="8","7"&MID(SUBSTITUTE(SUBSTITUTE(SUBSTITUTE(SUBSTITUTE(SUBSTITUTE(Поставщики_исходные!E21," ",""),"-",""),"+",""),"(",""),")",""),2,10),SUBSTITUTE(SUBSTITUTE(SUBSTITUTE(SUBSTITUTE(SUBSTITUTE(Поставщики_исходные!E21," ",""),"-",""),"+",""),"(",""),")","")),2,3)&") "&MID(IF(LEFT(SUBSTITUTE(SUBSTITUTE(SUBSTITUTE(SUBSTITUTE(SUBSTITUTE(Поставщики_исходные!E21," ",""),"-",""),"+",""),"(",""),")",""))="8","7"&MID(SUBSTITUTE(SUBSTITUTE(SUBSTITUTE(SUBSTITUTE(SUBSTITUTE(Поставщики_исходные!E21," ",""),"-",""),"+",""),"(",""),")",""),2,10),SUBSTITUTE(SUBSTITUTE(SUBSTITUTE(SUBSTITUTE(SUBSTITUTE(Поставщики_исходные!E21," ",""),"-",""),"+",""),"(",""),")","")),5,3)&"-"&MID(IF(LEFT(SUBSTITUTE(SUBSTITUTE(SUBSTITUTE(SUBSTITUTE(SUBSTITUTE(Поставщики_исходные!E21," ",""),"-",""),"+",""),"(",""),")",""))="8","7"&MID(SUBSTITUTE(SUBSTITUTE(SUBSTITUTE(SUBSTITUTE(SUBSTITUTE(Поставщики_исходные!E21," ",""),"-",""),"+",""),"(",""),")",""),2,10),SUBSTITUTE(SUBSTITUTE(SUBSTITUTE(SUBSTITUTE(SUBSTITUTE(Поставщики_исходные!E21," ",""),"-",""),"+",""),"(",""),")","")),8,2)&"-"&MID(IF(LEFT(SUBSTITUTE(SUBSTITUTE(SUBSTITUTE(SUBSTITUTE(SUBSTITUTE(Поставщики_исходные!E21," ",""),"-",""),"+",""),"(",""),")",""))="8","7"&MID(SUBSTITUTE(SUBSTITUTE(SUBSTITUTE(SUBSTITUTE(SUBSTITUTE(Поставщики_исходные!E21," ",""),"-",""),"+",""),"(",""),")",""),2,10),SUBSTITUTE(SUBSTITUTE(SUBSTITUTE(SUBSTITUTE(SUBSTITUTE(Поставщики_исходные!E21," ",""),"-",""),"+",""),"(",""),")","")),10,2),IF(LEN(SUBSTITUTE(SUBSTITUTE(SUBSTITUTE(SUBSTITUTE(SUBSTITUTE(Поставщики_исходные!E21," ",""),"-",""),"+",""),"(",""),")",""))=10,"+7 ("&MID(SUBSTITUTE(SUBSTITUTE(SUBSTITUTE(SUBSTITUTE(SUBSTITUTE(Поставщики_исходные!E21," ",""),"-",""),"+",""),"(",""),")",""),1,3)&") "&MID(SUBSTITUTE(SUBSTITUTE(SUBSTITUTE(SUBSTITUTE(SUBSTITUTE(Поставщики_исходные!E21," ",""),"-",""),"+",""),"(",""),")",""),4,3)&"-"&MID(SUBSTITUTE(SUBSTITUTE(SUBSTITUTE(SUBSTITUTE(SUBSTITUTE(Поставщики_исходные!E21," ",""),"-",""),"+",""),"(",""),")",""),6,2)&"-"&MID(SUBSTITUTE(SUBSTITUTE(SUBSTITUTE(SUBSTITUTE(SUBSTITUTE(Поставщики_исходные!E21," ",""),"-",""),"+",""),"(",""),")",""),8,2),Поставщики_исходные!E21))) -> +7 (903) 012-34-56 | F21: =IF(ISBLANK(Поставщики_исходные!F21),"",IF(ISNUMBER(FIND(".",MID(Поставщики_исходные!F21,FIND("@",Поставщики_исходные!F21)+1,255))),Поставщики_исходные!F21,IF(ISNUMBER(FIND("gmail",Поставщики_исходные!F21)),Поставщики_исходные!F21&".com",Поставщики_исходные!F21&".ru"))) -> invest@tehno.ru | G21: =TRIM(Поставщики_исходные!G21) -> 109380 г.Москва ул.Люблинская д.75 | H21: =IF(ISNUMBER(VALUE(LEFT(TRIM(Поставщики_исходные!G21),6))),LEFT(TRIM(Поставщики_исходные!G21),6),"") -> 109380 | I21: =TRIM(MID(TRIM(Поставщики_исходные!G21),7,255)) -> г.Москва ул.Люблинская д.75 | J21: =IF(OR(LEN(C21)=10,LEN(C21)=12),"OK","Ошибка ИНН") -> OK | K21: =IF(AND(ISNUMBER(FIND("@",F21)),ISNUMBER(FIND(".",MID(F21,FIND("@",F21)+1,255)))),"OK","Ошибка Email") -> OK
A22: =Поставщики_исходные!A22 -> P021 | B22: =PROPER(TRIM(Поставщики_исходные!B22)) -> Ооо Технопарк | C22: =IF(ISBLANK(Поставщики_исходные!C20),"",TRIM(Поставщики_исходные!C20)) -> 780890123456 | D22: =Поставщики_исходные!D22 -> 780901001 | E22: =IF(ISBLANK(Поставщики_исходные!E22),"",IF(LEN(SUBSTITUTE(SUBSTITUTE(SUBSTITUTE(SUBSTITUTE(SUBSTITUTE(Поставщики_исходные!E22," ",""),"-",""),"+",""),"(",""),")",""))=11,"+7 ("&MID(IF(LEFT(SUBSTITUTE(SUBSTITUTE(SUBSTITUTE(SUBSTITUTE(SUBSTITUTE(Поставщики_исходные!E22," ",""),"-",""),"+",""),"(",""),")",""))="8","7"&MID(SUBSTITUTE(SUBSTITUTE(SUBSTITUTE(SUBSTITUTE(SUBSTITUTE(Поставщики_исходные!E22," ",""),"-",""),"+",""),"(",""),")",""),2,10),SUBSTITUTE(SUBSTITUTE(SUBSTITUTE(SUBSTITUTE(SUBSTITUTE(Поставщики_исходные!E22," ",""),"-",""),"+",""),"(",""),")","")),2,3)&") "&MID(IF(LEFT(SUBSTITUTE(SUBSTITUTE(SUBSTITUTE(SUBSTITUTE(SUBSTITUTE(Поставщики_исходные!E22," ",""),"-",""),"+",""),"(",""),")",""))="8","7"&MID(SUBSTITUTE(SUBSTITUTE(SUBSTITUTE(SUBSTITUTE(SUBSTITUTE(Поставщики_исходные!E22," ",""),"-",""),"+",""),"(",""),")",""),2,10),SUBSTITUTE(SUBSTITUTE(SUBSTITUTE(SUBSTITUTE(SUBSTITUTE(Поставщики_исходные!E22," ",""),"-",""),"+",""),"(",""),")","")),5,3)&"-"&MID(IF(LEFT(SUBSTITUTE(SUBSTITUTE(SUBSTITUTE(SUBSTITUTE(SUBSTITUTE(Поставщики_исходные!E22," ",""),"-",""),"+",""),"(",""),")",""))="8","7"&MID(SUBSTITUTE(SUBSTITUTE(SUBSTITUTE(SUBSTITUTE(SUBSTITUTE(Поставщики_исходные!E22," ",""),"-",""),"+",""),"(",""),")",""),2,10),SUBSTITUTE(SUBSTITUTE(SUBSTITUTE(SUBSTITUTE(SUBSTITUTE(Поставщики_исходные!E22," ",""),"-",""),"+",""),"(",""),")","")),8,2)&"-"&MID(IF(LEFT(SUBSTITUTE(SUBSTITUTE(SUBSTITUTE(SUBSTITUTE(SUBSTITUTE(Поставщики_исходные!E22," ",""),"-",""),"+",""),"(",""),")",""))="8","7"&MID(SUBSTITUTE(SUBSTITUTE(SUBSTITUTE(SUBSTITUTE(SUBSTITUTE(Поставщики_исходные!E22," ",""),"-",""),"+",""),"(",""),")",""),2,10),SUBSTITUTE(SUBSTITUTE(SUBSTITUTE(SUBSTITUTE(SUBSTITUTE(Поставщики_исходные!E22," ",""),"-",""),"+",""),"(",""),")","")),10,2),IF(LEN(SUBSTITUTE(SUBSTITUTE(SUBSTITUTE(SUBSTITUTE(SUBSTITUTE(Поставщики_исходные!E22," ",""),"-",""),"+",""),"(",""),")",""))=10,"+7 ("&MID(SUBSTITUTE(SUBSTITUTE(SUBSTITUTE(SUBSTITUTE(SUBSTITUTE(Поставщики_исходные!E22," ",""),"-",""),"+",""),"(",""),")",""),1,3)&") "&MID(SUBSTITUTE(SUBSTITUTE(SUBSTITUTE(SUBSTITUTE(SUBSTITUTE(Поставщики_исходные!E22," ",""),"-",""),"+",""),"(",""),")",""),4,3)&"-"&MID(SUBSTITUTE(SUBSTITUTE(SUBSTITUTE(SUBSTITUTE(SUBSTITUTE(Поставщики_исходные!E22," ",""),"-",""),"+",""),"(",""),")",""),6,2)&"-"&MID(SUBSTITUTE(SUBSTITUTE(SUBSTITUTE(SUBSTITUTE(SUBSTITUTE(Поставщики_исходные!E22," ",""),"-",""),"+",""),"(",""),")",""),8,2),Поставщики_исходные!E22))) -> +7 (903) 123-45-67 | F22: =IF(ISBLANK(Поставщики_исходные!F22),"",IF(ISNUMBER(FIND(".",MID(Поставщики_исходные!F22,FIND("@",Поставщики_исходные!F22)+1,255))),Поставщики_исходные!F22,IF(ISNUMBER(FIND("gmail",Поставщики_исходные!F22)),Поставщики_исходные!F22&".com",Поставщики_исходные!F22&".ru"))) -> park@tehno.ru | G22: =TRIM(Поставщики_исходные!G22) -> 191040 г.Санкт-Петербург ул.Коломенская д.29 | H22: =IF(ISNUMBER(VALUE(LEFT(TRIM(Поставщики_исходные!G22),6))),LEFT(TRIM(Поставщики_исходные!G22),6),"") -> 191040 | I22: =TRIM(MID(TRIM(Поставщики_исходные!G22),7,255)) -> г.Санкт-Петербург ул.Коломенская д.29 | J22: =IF(OR(LEN(C22)=10,LEN(C22)=12),"OK","Ошибка ИНН") -> OK | K22: =IF(AND(ISNUMBER(FIND("@",F22)),ISNUMBER(FIND(".",MID(F22,FIND("@",F22)+1,255)))),"OK","Ошибка Email") -> OK
... A51: =Поставщики_исходные!A51 -> P050 | B51: =PROPER(TRIM(Поставщики_исходные!B51)) -> Зао Технопроект | C51: =IF(ISBLANK(Поставщики_исходные!C49),"",TRIM(Поставщики_исходные!C49)) -> 773456789012 | D51: =Поставщики_исходные!D51 -> 773301001 | E51: =IF(ISBLANK(Поставщики_исходные!E51),"",IF(LEN(SUBSTITUTE(SUBSTITUTE(SUBSTITUTE(SUBSTITUTE(SUBSTITUTE(Поставщики_исходные!E51," ",""),"-",""),"+",""),"(",""),")",""))=11,"+7 ("&MID(IF(LEFT(SUBSTITUTE(SUBSTITUTE(SUBSTITUTE(SUBSTITUTE(SUBSTITUTE(Поставщики_исходные!E51," ",""),"-",""),"+",""),"(",""),")",""))="8","7"&MID(SUBSTITUTE(SUBSTITUTE(SUBSTITUTE(SUBSTITUTE(SUBSTITUTE(Поставщики_исходные!E51," ",""),"-",""),"+",""),"(",""),")",""),2,10),SUBSTITUTE(SUBSTITUTE(SUBSTITUTE(SUBSTITUTE(SUBSTITUTE(Поставщики_исходные!E51," ",""),"-",""),"+",""),"(",""),")","")),2,3)&") "&MID(IF(LEFT(SUBSTITUTE(SUBSTITUTE(SUBSTITUTE(SUBSTITUTE(SUBSTITUTE(Поставщики_исходные!E51," ",""),"-",""),"+",""),"(",""),")",""))="8","7"&MID(SUBSTITUTE(SUBSTITUTE(SUBSTITUTE(SUBSTITUTE(SUBSTITUTE(Поставщики_исходные!E51," ",""),"-",""),"+",""),"(",""),")",""),2,10),SUBSTITUTE(SUBSTITUTE(SUBSTITUTE(SUBSTITUTE(SUBSTITUTE(Поставщики_исходные!E51," ",""),"-",""),"+",""),"(",""),")","")),5,3)&"-"&MID(IF(LEFT(SUBSTITUTE(SUBSTITUTE(SUBSTITUTE(SUBSTITUTE(SUBSTITUTE(Поставщики_исходные!E51," ",""),"-",""),"+",""),"(",""),")",""))="8","7"&MID(SUBSTITUTE(SUBSTITUTE(SUBSTITUTE(SUBSTITUTE(SUBSTITUTE(Поставщики_исходные!E51," ",""),"-",""),"+",""),"(",""),")",""),2,10),SUBSTITUTE(SUBSTITUTE(SUBSTITUTE(SUBSTITUTE(SUBSTITUTE(Поставщики_исходные!E51," ",""),"-",""),"+",""),"(",""),")","")),8,2)&"-"&MID(IF(LEFT(SUBSTITUTE(SUBSTITUTE(SUBSTITUTE(SUBSTITUTE(SUBSTITUTE(Поставщики_исходные!E51," ",""),"-",""),"+",""),"(",""),")",""))="8","7"&MID(SUBSTITUTE(SUBSTITUTE(SUBSTITUTE(SUBSTITUTE(SUBSTITUTE(Поставщики_исходные!E51," ",""),"-",""),"+",""),"(",""),")",""),2,10),SUBSTITUTE(SUBSTITUTE(SUBSTITUTE(SUBSTITUTE(SUBSTITUTE(Поставщики_исходные!E51," ",""),"-",""),"+",""),"(",""),")","")),10,2),IF(LEN(SUBSTITUTE(SUBSTITUTE(SUBSTITUTE(SUBSTITUTE(SUBSTITUTE(Поставщики_исходные!E51," ",""),"-",""),"+",""),"(",""),")",""))=10,"+7 ("&MID(SUBSTITUTE(SUBSTITUTE(SUBSTITUTE(SUBSTITUTE(SUBSTITUTE(Поставщики_исходные!E51," ",""),"-",""),"+",""),"(",""),")",""),1,3)&") "&MID(SUBSTITUTE(SUBSTITUTE(SUBSTITUTE(SUBSTITUTE(SUBSTITUTE(Поставщики_исходные!E51," ",""),"-",""),"+",""),"(",""),")",""),4,3)&"-"&MID(SUBSTITUTE(SUBSTITUTE(SUBSTITUTE(SUBSTITUTE(SUBSTITUTE(Поставщики_исходные!E51," ",""),"-",""),"+",""),"(",""),")",""),6,2)&"-"&MID(SUBSTITUTE(SUBSTITUTE(SUBSTITUTE(SUBSTITUTE(SUBSTITUTE(Поставщики_исходные!E51," ",""),"-",""),"+",""),"(",""),")",""),8,2),Поставщики_исходные!E51))) -> +7 (903) 012-34-56 | F51: =IF(ISBLANK(Поставщики_исходные!F51),"",IF(ISNUMBER(FIND(".",MID(Поставщики_исходные!F51,FIND("@",Поставщики_исходные!F51)+1,255))),Поставщики_исходные!F51,IF(ISNUMBER(FIND("gmail",Поставщики_исходные!F51)),Поставщики_исходные!F51&".com",Поставщики_исходные!F51&".ru"))) -> proekt@tehno.ru | G51: =TRIM(Поставщики_исходные!G51) -> 119435 г.Москва ул.Погодинская д.18 | H51: =IF(ISNUMBER(VALUE(LEFT(TRIM(Поставщики_исходные!G51),6))),LEFT(TRIM(Поставщики_исходные!G51),6),"") -> 119435 | I51: =TRIM(MID(TRIM(Поставщики_исходные!G51),7,255)) -> г.Москва ул.Погодинская д.18 | J51: =IF(OR(LEN(C51)=10,LEN(C51)=12),"OK","Ошибка ИНН") -> OK | K51: =IF(AND(ISNUMBER(FIND("@",F51)),ISNUMBER(FIND(".",MID(F51,FIND("@",F51)+1,255)))),"OK","Ошибка Email") -> OK

Sheet Продажи_исходные
B1: Артикул | C1: Количество | D1: Цена_продажи | E1: ID_клиента | F1: ID_поставщика | G1: Статус
A2: 01/15/2025 | B2: №АРТ-045 | C2: 2 | D2: $100 | E2: C0001 | F2: P012 | G2: Завершен
A3: 01/15/2025 | B3: АРТ_112 | C3: 1 | D3: €85 | E3: C0002 | F3: P007 | G3: завершен
A4: 01/16/2025 | B4: 003/24 | C4: 3 шт. | D4: 7500 ₽ | E4: C0003 | F4: P023 | G4: completed
A5: 01/16/2025 | B5: №АРТ-234 | C5: -1 | D5: $110 | E5: C0004 | F5: P045 | G5: отменен
A6: 01/17/2025 | B6: АРТ_067 | C6: 2 шт | D6: €90 | E6: C0005 | F6: P008 | G6: canceled
A7: 01/17/2025 | B7: 078-24 | C7: 1 | D7: 8000 ₽ | E7: C0006 | F7: P031 | G7: возврат
A8: 01/18/2025 | B8: №АРТ-389 | C8: 3 | D8: $105 | E8: C0007 | F8: P019 | G8: Завершен
A9: 01/18/2025 | B9: АРТ_156 | C9: 2 | D9: €95 | E9: C0008 | F9: P042 | G9: completed
A10: 01/19/2025 | B10: 251/24 | C10: 1 шт. | D10: 6500 ₽ | E10: C0009 | F10: P005 | G10: завершен
A11: 01/19/2025 | B11: №АРТ-023 | C11: -2 | D11: $115 | E11: C0010 | F11: P036 | G11: Отменен
A12: 01/20/2025 | B12: АРТ_478 | C12: 3 | D12: €80 | E12: C0011 | F12: P014 | G12: возврат
A13: 01/20/2025 | B13: 045-24 | C13: 1 | D13: 8500 ₽ | E13: C0012 | F13: P028 | G13: Завершен
... A1001: 05/29/2026 | B1001: №АРТ-357 | C1001: -3 | D1001: $120 | E1001: C1000 | F1001: P030 | G1001: завершен

Sheet Продажи_очищенные
A1: Дата | B1: Артикул | C1: Количество | D1: Цена_продажи | E1: ID_клиента | F1: ID_поставщика | G1: Статус | H1: Розничная_цена | I1: Категория_товара | J1: Проверка_цены
A2: =DATE(RIGHT('Продажи_исходные'!A2,4),LEFT('Продажи_исходные'!A2,2),MID('Продажи_исходные'!A2,4,2)) -> 45672 | B2: ="АРТ-"&LEFT(SUBSTITUTE(SUBSTITUTE(SUBSTITUTE(SUBSTITUTE('Продажи_исходные'!B2,"№",""),"АРТ-",""),"АРТ_",""),"/","-"),3) -> АРТ-045 | C2: =IFERROR(VALUE(TRIM(SUBSTITUTE(SUBSTITUTE(SUBSTITUTE(SUBSTITUTE('Продажи_исходные'!C2," шт.","")," шт",""),"шт.",""),"шт",""))),0) -> 2 | D2: =IF(LEFT('Продажи_исходные'!D2,1)="$",VALUE(MID('Продажи_исходные'!D2,2,255))*95,IF(LEFT('Продажи_исходные'!D2,1)="€",VALUE(MID('Продажи_исходные'!D2,2,255))*100,VALUE(SUBSTITUTE(SUBSTITUTE('Продажи_исходные'!D2,"₽","")," ","")))) -> 9500 | E2: ='Продажи_исходные'!E2 -> C0001 | F2: ='Продажи_исходные'!F2 -> P012 | G2: =IFERROR(VLOOKUP('Продажи_исходные'!G2,Справочники!$G$2:$H$50,2,FALSE),'Продажи_исходные'!G2) -> Завершен | H2: =IFERROR(VLOOKUP(B2,'Товары_очищенные'!$A$1:$G$1000,6,FALSE),"нет в каталоге") -> 137000 | I2: =IFERROR(VLOOKUP(B2,'Товары_очищенные'!$A$1:$G$1000,3,FALSE),"нет в каталоге") -> Телевизоры | J2: =IF(D2>0,"OK","Некорректная цена") -> OK
A3: =DATE(RIGHT(Продажи_исходные!A3,4),LEFT(Продажи_исходные!A3,2),MID(Продажи_исходные!A3,4,2)) -> 45672 | B3: ="АРТ-"&LEFT(SUBSTITUTE(SUBSTITUTE(SUBSTITUTE(SUBSTITUTE(Продажи_исходные!B3,"№",""),"АРТ-",""),"АРТ_",""),"/","-"),3) -> АРТ-112 | C3: =IFERROR(VALUE(TRIM(SUBSTITUTE(SUBSTITUTE(SUBSTITUTE(SUBSTITUTE(Продажи_исходные!C3," шт.","")," шт",""),"шт.",""),"шт",""))),0) -> 1 | D3: =IF(LEFT(Продажи_исходные!D3,1)="$",VALUE(MID(Продажи_исходные!D3,2,255))*95,IF(LEFT(Продажи_исходные!D3,1)="€",VALUE(MID(Продажи_исходные!D3,2,255))*100,VALUE(SUBSTITUTE(SUBSTITUTE(Продажи_исходные!D3,"₽","")," ","")))) -> 8500 | E3: =Продажи_исходные!E3 -> C0002 | F3: =Продажи_исходные!F3 -> P007 | G3: =IFERROR(VLOOKUP(Продажи_исходные!G3,Справочники!$G$2:$H$50,2,FALSE),Продажи_исходные!G3) -> Завершен | H3: =IFERROR(VLOOKUP(B3,Товары_очищенные!$A$1:$G$1000,6,FALSE),"нет в каталоге") -> 34990 | I3: =IFERROR(VLOOKUP(B3,Товары_очищенные!$A$1:$G$1000,3,FALSE),"нет в каталоге") -> Наушники | J3: =IF(D3>0,"OK","Некорректная цена") -> OK
A4: =DATE(RIGHT(Продажи_исходные!A4,4),LEFT(Продажи_исходные!A4,2),MID(Продажи_исходные!A4,4,2)) -> 45673 | B4: ="АРТ-"&LEFT(SUBSTITUTE(SUBSTITUTE(SUBSTITUTE(SUBSTITUTE(Продажи_исходные!B4,"№",""),"АРТ-",""),"АРТ_",""),"/","-"),3) -> АРТ-003 | C4: =IFERROR(VALUE(TRIM(SUBSTITUTE(SUBSTITUTE(SUBSTITUTE(SUBSTITUTE(Продажи_исходные!C4," шт.","")," шт",""),"шт.",""),"шт",""))),0) -> 3 | D4: =IF(LEFT(Продажи_исходные!D4,1)="$",VALUE(MID(Продажи_исходные!D4,2,255))*95,IF(LEFT(Продажи_исходные!D4,1)="€",VALUE(MID(Продажи_исходные!D4,2,255))*100,VALUE(SUBSTITUTE(SUBSTITUTE(Продажи_исходные!D4,"₽","")," ","")))) -> 7500 | E4: =Продажи_исходные!E4 -> C0003 | F4: =Продажи_исходные!F4 -> P023 | G4: =IFERROR(VLOOKUP(Продажи_исходные!G4,Справочники!$G$2:$H$50,2,FALSE),Продажи_исходные!G4) -> Завершен | H4: =IFERROR(VLOOKUP(B4,Товары_очищенные!$A$1:$G$1000,6,FALSE),"нет в каталоге") -> 77700 | I4: =IFERROR(VLOOKUP(B4,Товары_очищенные!$A$1:$G$1000,3,FALSE),"нет в каталоге") -> Смартфоны | J4: =IF(D4>0,"OK","Некорректная цена") -> OK
A5: =DATE(RIGHT(Продажи_исходные!A5,4),LEFT(Продажи_исходные!A5,2),MID(Продажи_исходные!A5,4,2)) -> 45673 | B5: ="АРТ-"&LEFT(SUBSTITUTE(SUBSTITUTE(SUBSTITUTE(SUBSTITUTE(Продажи_исходные!B5,"№",""),"АРТ-",""),"АРТ_",""),"/","-"),3) -> АРТ-234 | C5: =IFERROR(VALUE(TRIM(SUBSTITUTE(SUBSTITUTE(SUBSTITUTE(SUBSTITUTE(Продажи_исходные!C5," шт.","")," шт",""),"шт.",""),"шт",""))),0) -> -1 | D5: =IF(LEFT(Продажи_исходные!D5,1)="$",VALUE(MID(Продажи_исходные!D5,2,255))*95,IF(LEFT(Продажи_исходные!D5,1)="€",VALUE(MID(Продажи_исходные!D5,2,255))*100,VALUE(SUBSTITUTE(SUBSTITUTE(Продажи_исходные!D5,"₽","")," ","")))) -> 10450 | E5: =Продажи_исходные!E5 -> C0004 | F5: =Продажи_исходные!F5 -> P045 | G5: =IFERROR(VLOOKUP(Продажи_исходные!G5,Справочники!$G$2:$H$50,2,FALSE),Продажи_исходные!G5) -> Отменен | H5: =IFERROR(VLOOKUP(B5,Товары_очищенные!$A$1:$G$1000,6,FALSE),"нет в каталоге") -> 44500 | I5: =IFERROR(VLOOKUP(B5,Товары_очищенные!$A$1:$G$1000,3,FALSE),"нет в каталоге") -> Смартфоны | J5: =IF(D5>0,"OK","Некорректная цена") -> OK
A6: =DATE(RIGHT(Продажи_исходные!A6,4),LEFT(Продажи_исходные!A6,2),MID(Продажи_исходные!A6,4,2)) -> 45674 | B6: ="АРТ-"&LEFT(SUBSTITUTE(SUBSTITUTE(SUBSTITUTE(SUBSTITUTE(Продажи_исходные!B6,"№",""),"АРТ-",""),"АРТ_",""),"/","-"),3) -> АРТ-067 | C6: =IFERROR(VALUE(TRIM(SUBSTITUTE(SUBSTITUTE(SUBSTITUTE(SUBSTITUTE(Продажи_исходные!C6," шт.","")," шт",""),"шт.",""),"шт",""))),0) -> 2 | D6: =IF(LEFT(Продажи_исходные!D6,1)="$",VALUE(MID(Продажи_исходные!D6,2,255))*95,IF(LEFT(Продажи_исходные!D6,1)="€",VALUE(MID(Продажи_исходные!D6,2,255))*100,VALUE(SUBSTITUTE(SUBSTITUTE(Продажи_исходные!D6,"₽","")," ","")))) -> 9000 | E6: =Продажи_исходные!E6 -> C0005 | F6: =Продажи_исходные!F6 -> P008 | G6: =IFERROR(VLOOKUP(Продажи_исходные!G6,Справочники!$G$2:$H$50,2,FALSE),Продажи_исходные!G6) -> Отменен | H6: =IFERROR(VLOOKUP(B6,Товары_очищенные!$A$1:$G$1000,6,FALSE),"нет в каталоге") -> 109999 | I6: =IFERROR(VLOOKUP(B6,Товары_очищенные!$A$1:$G$1000,3,FALSE),"нет в каталоге") -> Телевизоры | J6: =IF(D6>0,"OK","Некорректная цена") -> OK
A7: =DATE(RIGHT(Продажи_исходные!A7,4),LEFT(Продажи_исходные!A7,2),MID(Продажи_исходные!A7,4,2)) -> 45674 | B7: ="АРТ-"&LEFT(SUBSTITUTE(SUBSTITUTE(SUBSTITUTE(SUBSTITUTE(Продажи_исходные!B7,"№",""),"АРТ-",""),"АРТ_",""),"/","-"),3) -> АРТ-078 | C7: =IFERROR(VALUE(TRIM(SUBSTITUTE(SUBSTITUTE(SUBSTITUTE(SUBSTITUTE(Продажи_исходные!C7," шт.","")," шт",""),"шт.",""),"шт",""))),0) -> 1 | D7: =IF(LEFT(Продажи_исходные!D7,1)="$",VALUE(MID(Продажи_исходные!D7,2,255))*95,IF(LEFT(Продажи_исходные!D7,1)="€",VALUE(MID(Продажи_исходные!D7,2,255))*100,VALUE(SUBSTITUTE(SUBSTITUTE(Продажи_исходные!D7,"₽","")," ","")))) -> 8000 | E7: =Продажи_исходные!E7 -> C0006 | F7: =Продажи_исходные!F7 -> P031 | G7: =IFERROR(VLOOKUP(Продажи_исходные!G7,Справочники!$G$2:$H$50,2,FALSE),Продажи_исходные!G7) -> Возврат | H7: =IFERROR(VLOOKUP(B7,Товары_очищенные!$A$1:$G$1000,6,FALSE),"нет в каталоге") -> 13500 | I7: =IFERROR(VLOOKUP(B7,Товары_очищенные!$A$1:$G$1000,3,FALSE),"нет в каталоге") -> Аксессуары | J7: =IF(D7>0,"OK","Некорректная цена") -> OK
A8: =DATE(RIGHT(Продажи_исходные!A8,4),LEFT(Продажи_исходные!A8,2),MID(Продажи_исходные!A8,4,2)) -> 45675 | B8: ="АРТ-"&LEFT(SUBSTITUTE(SUBSTITUTE(SUBSTITUTE(SUBSTITUTE(Продажи_исходные!B8,"№",""),"АРТ-",""),"АРТ_",""),"/","-"),3) -> АРТ-389 | C8: =IFERROR(VALUE(TRIM(SUBSTITUTE(SUBSTITUTE(SUBSTITUTE(SUBSTITUTE(Продажи_исходные!C8," шт.","")," шт",""),"шт.",""),"шт",""))),0) -> 3 | D8: =IF(LEFT(Продажи_исходные!D8,1)="$",VALUE(MID(Продажи_исходные!D8,2,255))*95,IF(LEFT(Продажи_исходные!D8,1)="€",VALUE(MID(Продажи_исходные!D8,2,255))*100,VALUE(SUBSTITUTE(SUBSTITUTE(Продажи_исходные!D8,"₽","")," ","")))) -> 9975 | E8: =Продажи_исходные!E8 -> C0007 | F8: =Продажи_исходные!F8 -> P019 | G8: =IFERROR(VLOOKUP(Продажи_исходные!G8,Справочники!$G$2:$H$50,2,FALSE),Продажи_исходные!G8) -> Завершен | H8: =IFERROR(VLOOKUP(B8,Товары_очищенные!$A$1:$G$1000,6,FALSE),"нет в каталоге") -> 75000 | I8: =IFERROR(VLOOKUP(B8,Товары_очищенные!$A$1:$G$1000,3,FALSE),"нет в каталоге") -> Телевизоры | J8: =IF(D8>0,"OK","Некорректная цена") -> OK
A9: =DATE(RIGHT(Продажи_исходные!A9,4),LEFT(Продажи_исходные!A9,2),MID(Продажи_исходные!A9,4,2)) -> 45675 | B9: ="АРТ-"&LEFT(SUBSTITUTE(SUBSTITUTE(SUBSTITUTE(SUBSTITUTE(Продажи_исходные!B9,"№",""),"АРТ-",""),"АРТ_",""),"/","-"),3) -> АРТ-156 | C9: =IFERROR(VALUE(TRIM(SUBSTITUTE(SUBSTITUTE(SUBSTITUTE(SUBSTITUTE(Продажи_исходные!C9," шт.","")," шт",""),"шт.",""),"шт",""))),0) -> 2 | D9: =IF(LEFT(Продажи_исходные!D9,1)="$",VALUE(MID(Продажи_исходные!D9,2,255))*95,IF(LEFT(Продажи_исходные!D9,1)="€",VALUE(MID(Продажи_исходные!D9,2,255))*100,VALUE(SUBSTITUTE(SUBSTITUTE(Продажи_исходные!D9,"₽","")," ","")))) -> 9500 | E9: =Продажи_исходные!E9 -> C0008 | F9: =Продажи_исходные!F9 -> P042 | G9: =IFERROR(VLOOKUP(Продажи_исходные!G9,Справочники!$G$2:$H$50,2,FALSE),Продажи_исходные!G9) -> Завершен | H9: =IFERROR(VLOOKUP(B9,Товары_очищенные!$A$1:$G$1000,6,FALSE),"нет в каталоге") -> 17800 | I9: =IFERROR(VLOOKUP(B9,Товары_очищенные!$A$1:$G$1000,3,FALSE),"нет в каталоге") -> Наушники | J9: =IF(D9>0,"OK","Некорректная цена") -> OK
A10: =DATE(RIGHT('Продажи_исходные'!A10,4),LEFT('Продажи_исходные'!A10,2),MID('Продажи_исходные'!A10,4,2)) -> 45676 | B10: ="АРТ-"&LEFT(SUBSTITUTE(SUBSTITUTE(SUBSTITUTE(SUBSTITUTE('Продажи_исходные'!B10,"№",""),"АРТ-",""),"АРТ_",""),"/","-"),3) -> АРТ-251 | C10: =IFERROR(VALUE(TRIM(SUBSTITUTE(SUBSTITUTE(SUBSTITUTE(SUBSTITUTE('Продажи_исходные'!C10," шт.","")," шт",""),"шт.",""),"шт",""))),0) -> 1 | D10: =IF(LEFT('Продажи_исходные'!D10,1)="$",VALUE(MID('Продажи_исходные'!D10,2,255))*95,IF(LEFT('Продажи_исходные'!D10,1)="€",VALUE(MID('Продажи_исходные'!D10,2,255))*100,VALUE(SUBSTITUTE(SUBSTITUTE('Продажи_исходные'!D10,"₽","")," ","")))) -> 6500 | E10: ='Продажи_исходные'!E10 -> C0009 | F10: ='Продажи_исходные'!F10 -> P005 | G10: =IFERROR(VLOOKUP('Продажи_исходные'!G10,Справочники!$G$2:$H$50,2,FALSE),'Продажи_исходные'!G10) -> Завершен | H10: =IFERROR(VLOOKUP(B10,'Товары_очищенные'!$A$1:$G$1000,6,FALSE),"нет в каталоге") -> 53500 | I10: =IFERROR(VLOOKUP(B10,'Товары_очищенные'!$A$1:$G$1000,3,FALSE),"нет в каталоге") -> Часы | J10: =IF(D10>0,"OK","Некорректная цена") -> OK
A11: =DATE(RIGHT(Продажи_исходные!A11,4),LEFT(Продажи_исходные!A11,2),MID(Продажи_исходные!A11,4,2)) -> 45676 | B11: ="АРТ-"&LEFT(SUBSTITUTE(SUBSTITUTE(SUBSTITUTE(SUBSTITUTE(Продажи_исходные!B11,"№",""),"АРТ-",""),"АРТ_",""),"/","-"),3) -> АРТ-023 | C11: =IFERROR(VALUE(TRIM(SUBSTITUTE(SUBSTITUTE(SUBSTITUTE(SUBSTITUTE(Продажи_исходные!C11," шт.","")," шт",""),"шт.",""),"шт",""))),0) -> -2 | D11: =IF(LEFT(Продажи_исходные!D11,1)="$",VALUE(MID(Продажи_исходные!D11,2,255))*95,IF(LEFT(Продажи_исходные!D11,1)="€",VALUE(MID(Продажи_исходные!D11,2,255))*100,VALUE(SUBSTITUTE(SUBSTITUTE(Продажи_исходные!D11,"₽","")," ","")))) -> 10925 | E11: =Продажи_исходные!E11 -> C0010 | F11: =Продажи_исходные!F11 -> P036 | G11: =IFERROR(VLOOKUP(Продажи_исходные!G11,Справочники!$G$2:$H$50,2,FALSE),Продажи_исходные!G11) -> Отменен | H11: =IFERROR(VLOOKUP(B11,Товары_очищенные!$A$1:$G$1000,6,FALSE),"нет в каталоге") -> 58500 | I11: =IFERROR(VLOOKUP(B11,Товары_очищенные!$A$1:$G$1000,3,FALSE),"нет в каталоге") -> Смартфоны | J11: =IF(D11>0,"OK","Некорректная цена") -> OK
A12: =DATE(RIGHT(Продажи_исходные!A12,4),LEFT(Продажи_исходные!A12,2),MID(Продажи_исходные!A12,4,2)) -> 45677 | B12: ="АРТ-"&LEFT(SUBSTITUTE(SUBSTITUTE(SUBSTITUTE(SUBSTITUTE(Продажи_исходные!B12,"№",""),"АРТ-",""),"АРТ_",""),"/","-"),3) -> АРТ-478 | C12: =IFERROR(VALUE(TRIM(SUBSTITUTE(SUBSTITUTE(SUBSTITUTE(SUBSTITUTE(Продажи_исходные!C12," шт.","")," шт",""),"шт.",""),"шт",""))),0) -> 3 | D12: =IF(LEFT(Продажи_исходные!D12,1)="$",VALUE(MID(Продажи_исходные!D12,2,255))*95,IF(LEFT(Продажи_исходные!D12,1)="€",VALUE(MID(Продажи_исходные!D12,2,255))*100,VALUE(SUBSTITUTE(SUBSTITUTE(Продажи_исходные!D12,"₽","")," ","")))) -> 8000 | E12: =Продажи_исходные!E12 -> C0011 | F12: =Продажи_исходные!F12 -> P014 | G12: =IFERROR(VLOOKUP(Продажи_исходные!G12,Справочники!$G$2:$H$50,2,FALSE),Продажи_исходные!G12) -> Возврат | H12: =IFERROR(VLOOKUP(B12,Товары_очищенные!$A$1:$G$1000,6,FALSE),"нет в каталоге") -> 12990 | I12: =IFERROR(VLOOKUP(B12,Товары_очищенные!$A$1:$G$1000,3,FALSE),"нет в каталоге") -> Аксессуары | J12: =IF(D12>0,"OK","Некорректная цена") -> OK
A13: =DATE(RIGHT(Продажи_исходные!A13,4),LEFT(Продажи_исходные!A13,2),MID(Продажи_исходные!A13,4,2)) -> 45677 | B13: ="АРТ-"&LEFT(SUBSTITUTE(SUBSTITUTE(SUBSTITUTE(SUBSTITUTE(Продажи_исходные!B13,"№",""),"АРТ-",""),"АРТ_",""),"/","-"),3) -> АРТ-045 | C13: =IFERROR(VALUE(TRIM(SUBSTITUTE(SUBSTITUTE(SUBSTITUTE(SUBSTITUTE(Продажи_исходные!C13," шт.","")," шт",""),"шт.",""),"шт",""))),0) -> 1 | D13: =IF(LEFT(Продажи_исходные!D13,1)="$",VALUE(MID(Продажи_исходные!D13,2,255))*95,IF(LEFT(Продажи_исходные!D13,1)="€",VALUE(MID(Продажи_исходные!D13,2,255))*100,VALUE(SUBSTITUTE(SUBSTITUTE(Продажи_исходные!D13,"₽","")," ","")))) -> 8500 | E13: =Продажи_исходные!E13 -> C0012 | F13: =Продажи_исходные!F13 -> P028 | G13: =IFERROR(VLOOKUP(Продажи_исходные!G13,Справочники!$G$2:$H$50,2,FALSE),Продажи_исходные!G13) -> Завершен | H13: =IFERROR(VLOOKUP(B13,Товары_очищенные!$A$1:$G$1000,6,FALSE),"нет в каталоге") -> 137000 | I13: =IFERROR(VLOOKUP(B13,Товары_очищенные!$A$1:$G$1000,3,FALSE),"нет в каталоге") -> Телевизоры | J13: =IF(D13>0,"OK","Некорректная цена") -> OK
A14: =DATE(RIGHT(Продажи_исходные!A14,4),LEFT(Продажи_исходные!A14,2),MID(Продажи_исходные!A14,4,2)) -> 45678 | B14: ="АРТ-"&LEFT(SUBSTITUTE(SUBSTITUTE(SUBSTITUTE(SUBSTITUTE(Продажи_исходные!B14,"№",""),"АРТ-",""),"АРТ_",""),"/","-"),3) -> АРТ-189 | C14: =IFERROR(VALUE(TRIM(SUBSTITUTE(SUBSTITUTE(SUBSTITUTE(SUBSTITUTE(Продажи_исходные!C14," шт.","")," шт",""),"шт.",""),"шт",""))),0) -> 2 | D14: =IF(LEFT(Продажи_исходные!D14,1)="$",VALUE(MID(Продажи_исходные!D14,2,255))*95,IF(LEFT(Продажи_исходные!D14,1)="€",VALUE(MID(Продажи_исходные!D14,2,255))*100,VALUE(SUBSTITUTE(SUBSTITUTE(Продажи_исходные!D14,"₽","")," ","")))) -> 12350 | E14: =Продажи_исходные!E14 -> C0013 | F14: =Продажи_исходные!F14 -> P009 | G14: =IFERROR(VLOOKUP(Продажи_исходные!G14,Справочники!$G$2:$H$50,2,FALSE),Продажи_исходные!G14) -> Отменен | H14: =IFERROR(VLOOKUP(B14,Товары_очищенные!$A$1:$G$1000,6,FALSE),"нет в каталоге") -> 51500 | I14: =IFERROR(VLOOKUP(B14,Товары_очищенные!$A$1:$G$1000,3,FALSE),"нет в каталоге") -> Часы | J14: =IF(D14>0,"OK","Некорректная цена") -> OK
A15: =DATE(RIGHT(Продажи_исходные!A15,4),LEFT(Продажи_исходные!A15,2),MID(Продажи_исходные!A15,4,2)) -> 45678 | B15: ="АРТ-"&LEFT(SUBSTITUTE(SUBSTITUTE(SUBSTITUTE(SUBSTITUTE(Продажи_исходные!B15,"№",""),"АРТ-",""),"АРТ_",""),"/","-"),3) -> АРТ-334 | C15: =IFERROR(VALUE(TRIM(SUBSTITUTE(SUBSTITUTE(SUBSTITUTE(SUBSTITUTE(Продажи_исходные!C15," шт.","")," шт",""),"шт.",""),"шт",""))),0) -> 1 | D15: =IF(LEFT(Продажи_исходные!D15,1)="$",VALUE(MID(Продажи_исходные!D15,2,255))*95,IF(LEFT(Продажи_исходные!D15,1)="€",VALUE(MID(Продажи_исходные!D15,2,255))*100,VALUE(SUBSTITUTE(SUBSTITUTE(Продажи_исходные!D15,"₽","")," ","")))) -> 11000 | E15: =Продажи_исходные!E15 -> C0014 | F15: =Продажи_исходные!F15 -> P041 | G15: =IFERROR(VLOOKUP(Продажи_исходные!G15,Справочники!$G$2:$H$50,2,FALSE),Продажи_исходные!G15) -> Завершен | H15: =IFERROR(VLOOKUP(B15,Товары_очищенные!$A$1:$G$1000,6,FALSE),"нет в каталоге") -> 48990 | I15: =IFERROR(VLOOKUP(B15,Товары_очищенные!$A$1:$G$1000,3,FALSE),"нет в каталоге") -> Планшеты | J15: =IF(D15>0,"OK","Некорректная цена") -> OK
A16: =DATE(RIGHT(Продажи_исходные!A16,4),LEFT(Продажи_исходные!A16,2),MID(Продажи_исходные!A16,4,2)) -> 45679 | B16: ="АРТ-"&LEFT(SUBSTITUTE(SUBSTITUTE(SUBSTITUTE(SUBSTITUTE(Продажи_исходные!B16,"№",""),"АРТ-",""),"АРТ_",""),"/","-"),3) -> АРТ-126 | C16: =IFERROR(VALUE(TRIM(SUBSTITUTE(SUBSTITUTE(SUBSTITUTE(SUBSTITUTE(Продажи_исходные!C16," шт.","")," шт",""),"шт.",""),"шт",""))),0) -> 3 | D16: =IF(LEFT(Продажи_исходные!D16,1)="$",VALUE(MID(Продажи_исходные!D16,2,255))*95,IF(LEFT(Продажи_исходные!D16,1)="€",VALUE(MID(Продажи_исходные!D16,2,255))*100,VALUE(SUBSTITUTE(SUBSTITUTE(Продажи_исходные!D16,"₽","")," ","")))) -> 9500 | E16: =Продажи_исходные!E16 -> C0015 | F16: =Продажи_исходные!F16 -> P017 | G16: =IFERROR(VLOOKUP(Продажи_исходные!G16,Справочники!$G$2:$H$50,2,FALSE),Продажи_исходные!G16) -> Отменен | H16: =IFERROR(VLOOKUP(B16,Товары_очищенные!$A$1:$G$1000,6,FALSE),"нет в каталоге") -> 173000 | I16: =IFERROR(VLOOKUP(B16,Товары_очищенные!$A$1:$G$1000,3,FALSE),"нет в каталоге") -> Ноутбуки | J16: =IF(D16>0,"OK","Некорректная цена") -> OK
A17: =DATE(RIGHT(Продажи_исходные!A17,4),LEFT(Продажи_исходные!A17,2),MID(Продажи_исходные!A17,4,2)) -> 45679 | B17: ="АРТ-"&LEFT(SUBSTITUTE(SUBSTITUTE(SUBSTITUTE(SUBSTITUTE(Продажи_исходные!B17,"№",""),"АРТ-",""),"АРТ_",""),"/","-"),3) -> АРТ-412 | C17: =IFERROR(VALUE(TRIM(SUBSTITUTE(SUBSTITUTE(SUBSTITUTE(SUBSTITUTE(Продажи_исходные!C17," шт.","")," шт",""),"шт.",""),"шт",""))),0) -> -1 | D17: =IF(LEFT(Продажи_исходные!D17,1)="$",VALUE(MID(Продажи_исходные!D17,2,255))*95,IF(LEFT(Продажи_исходные!D17,1)="€",VALUE(MID(Продажи_исходные!D17,2,255))*100,VALUE(SUBSTITUTE(SUBSTITUTE(Продажи_исходные!D17,"₽","")," ","")))) -> 9025 | E17: =Продажи_исходные!E17 -> C0016 | F17: =Продажи_исходные!F17 -> P032 | G17: =IFERROR(VLOOKUP(Продажи_исходные!G17,Справочники!$G$2:$H$50,2,FALSE),Продажи_исходные!G17) -> Завершен | H17: =IFERROR(VLOOKUP(B17,Товары_очищенные!$A$1:$G$1000,6,FALSE),"нет в каталоге") -> 54990 | I17: =IFERROR(VLOOKUP(B17,Товары_очищенные!$A$1:$G$1000,3,FALSE),"нет в каталоге") -> Мониторы | J17: =IF(D17>0,"OK","Некорректная цена") -> OK
A18: =DATE(RIGHT(Продажи_исходные!A18,4),LEFT(Продажи_исходные!A18,2),MID(Продажи_исходные!A18,4,2)) -> 45680 | B18: ="АРТ-"&LEFT(SUBSTITUTE(SUBSTITUTE(SUBSTITUTE(SUBSTITUTE(Продажи_исходные!B18,"№",""),"АРТ-",""),"АРТ_",""),"/","-"),3) -> АРТ-057 | C18: =IFERROR(VALUE(TRIM(SUBSTITUTE(SUBSTITUTE(SUBSTITUTE(SUBSTITUTE(Продажи_исходные!C18," шт.","")," шт",""),"шт.",""),"шт",""))),0) -> 2 | D18: =IF(LEFT(Продажи_исходные!D18,1)="$",VALUE(MID(Продажи_исходные!D18,2,255))*95,IF(LEFT(Продажи_исходные!D18,1)="€",VALUE(MID(Продажи_исходные!D18,2,255))*100,VALUE(SUBSTITUTE(SUBSTITUTE(Продажи_исходные!D18,"₽","")," ","")))) -> 7500 | E18: =Продажи_исходные!E18 -> C0017 | F18: =Продажи_исходные!F18 -> P049 | G18: =IFERROR(VLOOKUP(Продажи_исходные!G18,Справочники!$G$2:$H$50,2,FALSE),Продажи_исходные!G18) -> Завершен | H18: =IFERROR(VLOOKUP(B18,Товары_очищенные!$A$1:$G$1000,6,FALSE),"нет в каталоге") -> 11200 | I18: =IFERROR(VLOOKUP(B18,Товары_очищенные!$A$1:$G$1000,3,FALSE),"нет в каталоге") -> Аксессуары | J18: =IF(D18>0,"OK","Некорректная цена") -> OK
A19: =DATE(RIGHT(Продажи_исходные!A19,4),LEFT(Продажи_исходные!A19,2),MID(Продажи_исходные!A19,4,2)) -> 45680 | B19: ="АРТ-"&LEFT(SUBSTITUTE(SUBSTITUTE(SUBSTITUTE(SUBSTITUTE(Продажи_исходные!B19,"№",""),"АРТ-",""),"АРТ_",""),"/","-"),3) -> АРТ-394 | C19: =IFERROR(VALUE(TRIM(SUBSTITUTE(SUBSTITUTE(SUBSTITUTE(SUBSTITUTE(Продажи_исходные!C19," шт.","")," шт",""),"шт.",""),"шт",""))),0) -> 1 | D19: =IF(LEFT(Продажи_исходные!D19,1)="$",VALUE(MID(Продажи_исходные!D19,2,255))*95,IF(LEFT(Продажи_исходные!D19,1)="€",VALUE(MID(Продажи_исходные!D19,2,255))*100,VALUE(SUBSTITUTE(SUBSTITUTE(Продажи_исходные!D19,"₽","")," ","")))) -> 7000 | E19: =Продажи_исходные!E19 -> C0018 | F19: =Продажи_исходные!F19 -> P006 | G19: =IFERROR(VLOOKUP(Продажи_исходные!G19,Справочники!$G$2:$H$50,2,FALSE),Продажи_исходные!G19) -> Возврат | H19: =IFERROR(VLOOKUP(B19,Товары_очищенные!$A$1:$G$1000,6,FALSE),"нет в каталоге") -> 64990 | I19: =IFERROR(VLOOKUP(B19,Товары_очищенные!$A$1:$G$1000,3,FALSE),"нет в каталоге") -> Мониторы | J19: =IF(D19>0,"OK","Некорректная цена") -> OK
A20: =DATE(RIGHT(Продажи_исходные!A20,4),LEFT(Продажи_исходные!A20,2),MID(Продажи_исходные!A20,4,2)) -> 45681 | B20: ="АРТ-"&LEFT(SUBSTITUTE(SUBSTITUTE(SUBSTITUTE(SUBSTITUTE(Продажи_исходные!B20,"№",""),"АРТ-",""),"АРТ_",""),"/","-"),3) -> АРТ-278 | C20: =IFERROR(VALUE(TRIM(SUBSTITUTE(SUBSTITUTE(SUBSTITUTE(SUBSTITUTE(Продажи_исходные!C20," шт.","")," шт",""),"шт.",""),"шт",""))),0) -> 3 | D20: =IF(LEFT(Продажи_исходные!D20,1)="$",VALUE(MID(Продажи_исходные!D20,2,255))*95,IF(LEFT(Продажи_исходные!D20,1)="€",VALUE(MID(Продажи_исходные!D20,2,255))*100,VALUE(SUBSTITUTE(SUBSTITUTE(Продажи_исходные!D20,"₽","")," ","")))) -> 13300 | E20: =Продажи_исходные!E20 -> C0019 | F20: =Продажи_исходные!F20 -> P024 | G20: =IFERROR(VLOOKUP(Продажи_исходные!G20,Справочники!$G$2:$H$50,2,FALSE),Продажи_исходные!G20) -> Завершен | H20: =IFERROR(VLOOKUP(B20,Товары_очищенные!$A$1:$G$1000,6,FALSE),"нет в каталоге") -> 112000 | I20: =IFERROR(VLOOKUP(B20,Товары_очищенные!$A$1:$G$1000,3,FALSE),"нет в каталоге") -> Телевизоры | J20: =IF(D20>0,"OK","Некорректная цена") -> OK
A21: =DATE(RIGHT(Продажи_исходные!A21,4),LEFT(Продажи_исходные!A21,2),MID(Продажи_исходные!A21,4,2)) -> 45681 | B21: ="АРТ-"&LEFT(SUBSTITUTE(SUBSTITUTE(SUBSTITUTE(SUBSTITUTE(Продажи_исходные!B21,"№",""),"АРТ-",""),"АРТ_",""),"/","-"),3) -> АРТ-193 | C21: =IFERROR(VALUE(TRIM(SUBSTITUTE(SUBSTITUTE(SUBSTITUTE(SUBSTITUTE(Продажи_исходные!C21," шт.","")," шт",""),"шт.",""),"шт",""))),0) -> 2 | D21: =IF(LEFT(Продажи_исходные!D21,1)="$",VALUE(MID(Продажи_исходные!D21,2,255))*95,IF(LEFT(Продажи_исходные!D21,1)="€",VALUE(MID(Продажи_исходные!D21,2,255))*100,VALUE(SUBSTITUTE(SUBSTITUTE(Продажи_исходные!D21,"₽","")," ","")))) -> 12000 | E21: =Продажи_исходные!E21 -> C0020 | F21: =Продажи_исходные!F21 -> P015 | G21: =IFERROR(VLOOKUP(Продажи_исходные!G21,Справочники!$G$2:$H$50,2,FALSE),Продажи_исходные!G21) -> Завершен | H21: =IFERROR(VLOOKUP(B21,Товары_очищенные!$A$1:$G$1000,6,FALSE),"нет в каталоге") -> 129990 | I21: =IFERROR(VLOOKUP(B21,Товары_очищенные!$A$1:$G$1000,3,FALSE),"нет в каталоге") -> Ноутбуки | J21: =IF(D21>0,"OK","Некорректная цена") -> OK
A22: =DATE(RIGHT(Продажи_исходные!A22,4),LEFT(Продажи_исходные!A22,2),MID(Продажи_исходные!A22,4,2)) -> 45682 | B22: ="АРТ-"&LEFT(SUBSTITUTE(SUBSTITUTE(SUBSTITUTE(SUBSTITUTE(Продажи_исходные!B22,"№",""),"АРТ-",""),"АРТ_",""),"/","-"),3) -> АРТ-149 | C22: =IFERROR(VALUE(TRIM(SUBSTITUTE(SUBSTITUTE(SUBSTITUTE(SUBSTITUTE(Продажи_исходные!C22," шт.","")," шт",""),"шт.",""),"шт",""))),0) -> 1 | D22: =IF(LEFT(Продажи_исходные!D22,1)="$",VALUE(MID(Продажи_исходные!D22,2,255))*95,IF(LEFT(Продажи_исходные!D22,1)="€",VALUE(MID(Продажи_исходные!D22,2,255))*100,VALUE(SUBSTITUTE(SUBSTITUTE(Продажи_исходные!D22,"₽","")," ","")))) -> 10000 | E22: =Продажи_исходные!E22 -> C0021 | F22: =Продажи_исходные!F22 -> P037 | G22: =IFERROR(VLOOKUP(Продажи_исходные!G22,Справочники!$G$2:$H$50,2,FALSE),Продажи_исходные!G22) -> Отменен | H22: =IFERROR(VLOOKUP(B22,Товары_очищенные!$A$1:$G$1000,6,FALSE),"нет в каталоге") -> 137000 | I22: =IFERROR(VLOOKUP(B22,Товары_очищенные!$A$1:$G$1000,3,FALSE),"нет в каталоге") -> Ноутбуки | J22: =IF(D22>0,"OK","Некорректная цена") -> OK
... A99: =DATE(RIGHT(Продажи_исходные!A99,4),LEFT(Продажи_исходные!A99,2),MID(Продажи_исходные!A99,4,2)) -> 45720 | B99: ="АРТ-"&LEFT(SUBSTITUTE(SUBSTITUTE(SUBSTITUTE(SUBSTITUTE(Продажи_исходные!B99,"№",""),"АРТ-",""),"АРТ_",""),"/","-"),3) -> АРТ-141 | C99: =IFERROR(VALUE(TRIM(SUBSTITUTE(SUBSTITUTE(SUBSTITUTE(SUBSTITUTE(Продажи_исходные!C99," шт.","")," шт",""),"шт.",""),"шт",""))),0) -> 2 | D99: =IF(LEFT(Продажи_исходные!D99,1)="$",VALUE(MID(Продажи_исходные!D99,2,255))*95,IF(LEFT(Продажи_исходные!D99,1)="€",VALUE(MID(Продажи_исходные!D99,2,255))*100,VALUE(SUBSTITUTE(SUBSTITUTE(Продажи_исходные!D99,"₽","")," ","")))) -> 11000 | E99: =Продажи_исходные!E99 -> C0098 | F99: =Продажи_исходные!F99 -> P022 | G99: =IFERROR(VLOOKUP(Продажи_исходные!G99,Справочники!$G$2:$H$50,2,FALSE),Продажи_исходные!G99) -> Завершен | H99: =IFERROR(VLOOKUP(B99,Товары_очищенные!$A$1:$G$1000,6,FALSE),"нет в каталоге") -> 92500 | I99: =IFERROR(VLOOKUP(B99,Товары_очищенные!$A$1:$G$1000,3,FALSE),"нет в каталоге") -> Мониторы | J99: =IF(D99>0,"OK","Некорректная цена") -> OK
A100: =DATE(RIGHT('Продажи_исходные'!A100,4),LEFT('Продажи_исходные'!A100,2),MID('Продажи_исходные'!A100,4,2)) -> 45721 | B100: ="АРТ-"&LEFT(SUBSTITUTE(SUBSTITUTE(SUBSTITUTE(SUBSTITUTE('Продажи_исходные'!B100,"№",""),"АРТ-",""),"АРТ_",""),"/","-"),3) -> АРТ-226 | C100: =IFERROR(VALUE(TRIM(SUBSTITUTE(SUBSTITUTE(SUBSTITUTE(SUBSTITUTE('Продажи_исходные'!C100," шт.","")," шт",""),"шт.",""),"шт",""))),0) -> 1 | D100: =IF(LEFT('Продажи_исходные'!D100,1)="$",VALUE(MID('Продажи_исходные'!D100,2,255))*95,IF(LEFT('Продажи_исходные'!D100,1)="€",VALUE(MID('Продажи_исходные'!D100,2,255))*100,VALUE(SUBSTITUTE(SUBSTITUTE('Продажи_исходные'!D100,"₽","")," ","")))) -> 9200 | E100: ='Продажи_исходные'!E100 -> C0099 | F100: ='Продажи_исходные'!F100 -> P043 | G100: =IFERROR(VLOOKUP('Продажи_исходные'!G100,Справочники!$G$2:$H$50,2,FALSE),'Продажи_исходные'!G100) -> Отменен | H100: =IFERROR(VLOOKUP(B100,'Товары_очищенные'!$A$1:$G$1000,6,FALSE),"нет в каталоге") -> 5990 | I100: =IFERROR(VLOOKUP(B100,'Товары_очищенные'!$A$1:$G$1000,3,FALSE),"нет в каталоге") -> Аксессуары | J100: =IF(D100>0,"OK","Некорректная цена") -> OK
A101: =DATE(RIGHT(Продажи_исходные!A101,4),LEFT(Продажи_исходные!A101,2),MID(Продажи_исходные!A101,4,2)) -> 45721 | B101: ="АРТ-"&LEFT(SUBSTITUTE(SUBSTITUTE(SUBSTITUTE(SUBSTITUTE(Продажи_исходные!B101,"№",""),"АРТ-",""),"АРТ_",""),"/","-"),3) -> АРТ-322 | C101: =IFERROR(VALUE(TRIM(SUBSTITUTE(SUBSTITUTE(SUBSTITUTE(SUBSTITUTE(Продажи_исходные!C101," шт.","")," шт",""),"шт.",""),"шт",""))),0) -> -1 | D101: =IF(LEFT(Продажи_исходные!D101,1)="$",VALUE(MID(Продажи_исходные!D101,2,255))*95,IF(LEFT(Продажи_исходные!D101,1)="€",VALUE(MID(Продажи_исходные!D101,2,255))*100,VALUE(SUBSTITUTE(SUBSTITUTE(Продажи_исходные!D101,"₽","")," ","")))) -> 8075 | E101: =Продажи_исходные!E101 -> C0100 | F101: =Продажи_исходные!F101 -> P030 | G101: =IFERROR(VLOOKUP(Продажи_исходные!G101,Справочники!$G$2:$H$50,2,FALSE),Продажи_исходные!G101) -> Отменен | H101: =IFERROR(VLOOKUP(B101,Товары_очищенные!$A$1:$G$1000,6,FALSE),"нет в каталоге") -> 12990 | I101: =IFERROR(VLOOKUP(B101,Товары_очищенные!$A$1:$G$1000,3,FALSE),"нет в каталоге") -> Наушники | J101: =IF(D101>0,"OK","Некорректная цена") -> OK
A102: =DATE(RIGHT(Продажи_исходные!A102,4),LEFT(Продажи_исходные!A102,2),MID(Продажи_исходные!A102,4,2)) -> 45722 | B102: ="АРТ-"&LEFT(SUBSTITUTE(SUBSTITUTE(SUBSTITUTE(SUBSTITUTE(Продажи_исходные!B102,"№",""),"АРТ-",""),"АРТ_",""),"/","-"),3) -> АРТ-273 | C102: =IFERROR(VALUE(TRIM(SUBSTITUTE(SUBSTITUTE(SUBSTITUTE(SUBSTITUTE(Продажи_исходные!C102," шт.","")," шт",""),"шт.",""),"шт",""))),0) -> 3 | D102: =IF(LEFT(Продажи_исходные!D102,1)="$",VALUE(MID(Продажи_исходные!D102,2,255))*95,IF(LEFT(Продажи_исходные!D102,1)="€",VALUE(MID(Продажи_исходные!D102,2,255))*100,VALUE(SUBSTITUTE(SUBSTITUTE(Продажи_исходные!D102,"₽","")," ","")))) -> 6500 | E102: =Продажи_исходные!E102 -> C0101 | F102: =Продажи_исходные!F102 -> P012 | G102: =IFERROR(VLOOKUP(Продажи_исходные!G102,Справочники!$G$2:$H$50,2,FALSE),Продажи_исходные!G102) -> Возврат | H102: =IFERROR(VLOOKUP(B102,Товары_очищенные!$A$1:$G$1000,6,FALSE),"нет в каталоге") -> 46500 | I102: =IFERROR(VLOOKUP(B102,Товары_очищенные!$A$1:$G$1000,3,FALSE),"нет в каталоге") -> Смартфоны | J102: =IF(D102>0,"OK","Некорректная цена") -> OK
A103: =DATE(RIGHT(Продажи_исходные!A103,4),LEFT(Продажи_исходные!A103,2),MID(Продажи_исходные!A103,4,2)) -> 45722 | B103: ="АРТ-"&LEFT(SUBSTITUTE(SUBSTITUTE(SUBSTITUTE(SUBSTITUTE(Продажи_исходные!B103,"№",""),"АРТ-",""),"АРТ_",""),"/","-"),3) -> АРТ-184 | C103: =IFERROR(VALUE(TRIM(SUBSTITUTE(SUBSTITUTE(SUBSTITUTE(SUBSTITUTE(Продажи_исходные!C103," шт.","")," шт",""),"шт.",""),"шт",""))),0) -> 2 | D103: =IF(LEFT(Продажи_исходные!D103,1)="$",VALUE(MID(Продажи_исходные!D103,2,255))*95,IF(LEFT(Продажи_исходные!D103,1)="€",VALUE(MID(Продажи_исходные!D103,2,255))*100,VALUE(SUBSTITUTE(SUBSTITUTE(Продажи_исходные!D103,"₽","")," ","")))) -> 6500 | E103: =Продажи_исходные!E103 -> C0102 | F103: =Продажи_исходные!F103 -> P007 | G103: =IFERROR(VLOOKUP(Продажи_исходные!G103,Справочники!$G$2:$H$50,2,FALSE),Продажи_исходные!G103) -> Завершен | H103: =IFERROR(VLOOKUP(B103,Товары_очищенные!$A$1:$G$1000,6,FALSE),"нет в каталоге") -> 19990 | I103: =IFERROR(VLOOKUP(B103,Товары_очищенные!$A$1:$G$1000,3,FALSE),"нет в каталоге") -> Аксессуары | J103: =IF(D103>0,"OK","Некорректная цена") -> OK
A104: =DATE(RIGHT(Продажи_исходные!A104,4),LEFT(Продажи_исходные!A104,2),MID(Продажи_исходные!A104,4,2)) -> 45723 | B104: ="АРТ-"&LEFT(SUBSTITUTE(SUBSTITUTE(SUBSTITUTE(SUBSTITUTE(Продажи_исходные!B104,"№",""),"АРТ-",""),"АРТ_",""),"/","-"),3) -> АРТ-065 | C104: =IFERROR(VALUE(TRIM(SUBSTITUTE(SUBSTITUTE(SUBSTITUTE(SUBSTITUTE(Продажи_исходные!C104," шт.","")," шт",""),"шт.",""),"шт",""))),0) -> 1 | D104: =IF(LEFT(Продажи_исходные!D104,1)="$",VALUE(MID(Продажи_исходные!D104,2,255))*95,IF(LEFT(Продажи_исходные!D104,1)="€",VALUE(MID(Продажи_исходные!D104,2,255))*100,VALUE(SUBSTITUTE(SUBSTITUTE(Продажи_исходные!D104,"₽","")," ","")))) -> 9975 | E104: =Продажи_исходные!E104 -> C0103 | F104: =Продажи_исходные!F104 -> P023 | G104: =IFERROR(VLOOKUP(Продажи_исходные!G104,Справочники!$G$2:$H$50,2,FALSE),Продажи_исходные!G104) -> Завершен | H104: =IFERROR(VLOOKUP(B104,Товары_очищенные!$A$1:$G$1000,6,FALSE),"нет в каталоге") -> 55500 | I104: =IFERROR(VLOOKUP(B104,Товары_очищенные!$A$1:$G$1000,3,FALSE),"нет в каталоге") -> Смартфоны | J104: =IF(D104>0,"OK","Некорректная цена") -> OK
A105: =DATE(RIGHT(Продажи_исходные!A105,4),LEFT(Продажи_исходные!A105,2),MID(Продажи_исходные!A105,4,2)) -> 45723 | B105: ="АРТ-"&LEFT(SUBSTITUTE(SUBSTITUTE(SUBSTITUTE(SUBSTITUTE(Продажи_исходные!B105,"№",""),"АРТ-",""),"АРТ_",""),"/","-"),3) -> АРТ-408 | C105: =IFERROR(VALUE(TRIM(SUBSTITUTE(SUBSTITUTE(SUBSTITUTE(SUBSTITUTE(Продажи_исходные!C105," шт.","")," шт",""),"шт.",""),"шт",""))),0) -> 2 | D105: =IF(LEFT(Продажи_исходные!D105,1)="$",VALUE(MID(Продажи_исходные!D105,2,255))*95,IF(LEFT(Продажи_исходные!D105,1)="€",VALUE(MID(Продажи_исходные!D105,2,255))*100,VALUE(SUBSTITUTE(SUBSTITUTE(Продажи_исходные!D105,"₽","")," ","")))) -> 8500 | E105: =Продажи_исходные!E105 -> C0104 | F105: =Продажи_исходные!F105 -> P045 | G105: =IFERROR(VLOOKUP(Продажи_исходные!G105,Справочники!$G$2:$H$50,2,FALSE),Продажи_исходные!G105) -> Завершен | H105: =IFERROR(VLOOKUP(B105,Товары_очищенные!$A$1:$G$1000,6,FALSE),"нет в каталоге") -> 107500 | I105: =IFERROR(VLOOKUP(B105,Товары_очищенные!$A$1:$G$1000,3,FALSE),"нет в каталоге") -> Телевизоры | J105: =IF(D105>0,"OK","Некорректная цена") -> OK
A106: =DATE(RIGHT(Продажи_исходные!A106,4),LEFT(Продажи_исходные!A106,2),MID(Продажи_исходные!A106,4,2)) -> 45724 | B106: ="АРТ-"&LEFT(SUBSTITUTE(SUBSTITUTE(SUBSTITUTE(SUBSTITUTE(Продажи_исходные!B106,"№",""),"АРТ-",""),"АРТ_",""),"/","-"),3) -> АРТ-315 | C106: =IFERROR(VALUE(TRIM(SUBSTITUTE(SUBSTITUTE(SUBSTITUTE(SUBSTITUTE(Продажи_исходные!C106," шт.","")," шт",""),"шт.",""),"шт",""))),0) -> 3 | D106: =IF(LEFT(Продажи_исходные!D106,1)="$",VALUE(MID(Продажи_исходные!D106,2,255))*95,IF(LEFT(Продажи_исходные!D106,1)="€",VALUE(MID(Продажи_исходные!D106,2,255))*100,VALUE(SUBSTITUTE(SUBSTITUTE(Продажи_исходные!D106,"₽","")," ","")))) -> 8000 | E106: =Продажи_исходные!E106 -> C0105 | F106: =Продажи_исходные!F106 -> P008 | G106: =IFERROR(VLOOKUP(Продажи_исходные!G106,Справочники!$G$2:$H$50,2,FALSE),Продажи_исходные!G106) -> Отменен | H106: =IFERROR(VLOOKUP(B106,Товары_очищенные!$A$1:$G$1000,6,FALSE),"нет в каталоге") -> 72000 | I106: =IFERROR(VLOOKUP(B106,Товары_очищенные!$A$1:$G$1000,3,FALSE),"нет в каталоге") -> Смартфоны | J106: =IF(D106>0,"OK","Некорректная цена") -> OK
A107: =DATE(RIGHT(Продажи_исходные!A107,4),LEFT(Продажи_исходные!A107,2),MID(Продажи_исходные!A107,4,2)) -> 45724 | B107: ="АРТ-"&LEFT(SUBSTITUTE(SUBSTITUTE(SUBSTITUTE(SUBSTITUTE(Продажи_исходные!B107,"№",""),"АРТ-",""),"АРТ_",""),"/","-"),3) -> АРТ-159 | C107: =IFERROR(VALUE(TRIM(SUBSTITUTE(SUBSTITUTE(SUBSTITUTE(SUBSTITUTE(Продажи_исходные!C107," шт.","")," шт",""),"шт.",""),"шт",""))),0) -> -2 | D107: =IF(LEFT(Продажи_исходные!D107,1)="$",VALUE(MID(Продажи_исходные!D107,2,255))*95,IF(LEFT(Продажи_исходные!D107,1)="€",VALUE(MID(Продажи_исходные!D107,2,255))*100,VALUE(SUBSTITUTE(SUBSTITUTE(Продажи_исходные!D107,"₽","")," ","")))) -> 11400 | E107: =Продажи_исходные!E107 -> C0106 | F107: =Продажи_исходные!F107 -> P031 | G107: =IFERROR(VLOOKUP(Продажи_исходные!G107,Справочники!$G$2:$H$50,2,FALSE),Продажи_исходные!G107) -> Отменен | H107: =IFERROR(VLOOKUP(B107,Товары_очищенные!$A$1:$G$1000,6,FALSE),"нет в каталоге") -> 95500 | I107: =IFERROR(VLOOKUP(B107,Товары_очищенные!$A$1:$G$1000,3,FALSE),"нет в каталоге") -> Мониторы | J107: =IF(D107>0,"OK","Некорректная цена") -> OK
A108: =DATE(RIGHT(Продажи_исходные!A108,4),LEFT(Продажи_исходные!A108,2),MID(Продажи_исходные!A108,4,2)) -> 45725 | B108: ="АРТ-"&LEFT(SUBSTITUTE(SUBSTITUTE(SUBSTITUTE(SUBSTITUTE(Продажи_исходные!B108,"№",""),"АРТ-",""),"АРТ_",""),"/","-"),3) -> АРТ-432 | C108: =IFERROR(VALUE(TRIM(SUBSTITUTE(SUBSTITUTE(SUBSTITUTE(SUBSTITUTE(Продажи_исходные!C108," шт.","")," шт",""),"шт.",""),"шт",""))),0) -> 1 | D108: =IF(LEFT(Продажи_исходные!D108,1)="$",VALUE(MID(Продажи_исходные!D108,2,255))*95,IF(LEFT(Продажи_исходные!D108,1)="€",VALUE(MID(Продажи_исходные!D108,2,255))*100,VALUE(SUBSTITUTE(SUBSTITUTE(Продажи_исходные!D108,"₽","")," ","")))) -> 10000 | E108: =Продажи_исходные!E108 -> C0107 | F108: =Продажи_исходные!F108 -> P019 | G108: =IFERROR(VLOOKUP(Продажи_исходные!G108,Справочники!$G$2:$H$50,2,FALSE),Продажи_исходные!G108) -> Завершен | H108: =IFERROR(VLOOKUP(B108,Товары_очищенные!$A$1:$G$1000,6,FALSE),"нет в каталоге") -> 15800 | I108: =IFERROR(VLOOKUP(B108,Товары_очищенные!$A$1:$G$1000,3,FALSE),"нет в каталоге") -> Наушники | J108: =IF(D108>0,"OK","Некорректная цена") -> OK
A109: =DATE(RIGHT(Продажи_исходные!A109,4),LEFT(Продажи_исходные!A109,2),MID(Продажи_исходные!A109,4,2)) -> 45725 | B109: ="АРТ-"&LEFT(SUBSTITUTE(SUBSTITUTE(SUBSTITUTE(SUBSTITUTE(Продажи_исходные!B109,"№",""),"АРТ-",""),"АРТ_",""),"/","-"),3) -> АРТ-067 | C109: =IFERROR(VALUE(TRIM(SUBSTITUTE(SUBSTITUTE(SUBSTITUTE(SUBSTITUTE(Продажи_исходные!C109," шт.","")," шт",""),"шт.",""),"шт",""))),0) -> 2 | D109: =IF(LEFT(Продажи_исходные!D109,1)="$",VALUE(MID(Продажи_исходные!D109,2,255))*95,IF(LEFT(Продажи_исходные!D109,1)="€",VALUE(MID(Продажи_исходные!D109,2,255))*100,VALUE(SUBSTITUTE(SUBSTITUTE(Продажи_исходные!D109,"₽","")," ","")))) -> 8800 | E109: =Продажи_исходные!E109 -> C0108 | F109: =Продажи_исходные!F109 -> P042 | G109: =IFERROR(VLOOKUP(Продажи_исходные!G109,Справочники!$G$2:$H$50,2,FALSE),Продажи_исходные!G109) -> Возврат | H109: =IFERROR(VLOOKUP(B109,Товары_очищенные!$A$1:$G$1000,6,FALSE),"нет в каталоге") -> 109999 | I109: =IFERROR(VLOOKUP(B109,Товары_очищенные!$A$1:$G$1000,3,FALSE),"нет в каталоге") -> Телевизоры | J109: =IF(D109>0,"OK","Некорректная цена") -> OK
A110: =DATE(RIGHT(Продажи_исходные!A110,4),LEFT(Продажи_исходные!A110,2),MID(Продажи_исходные!A110,4,2)) -> 45726 | B110: ="АРТ-"&LEFT(SUBSTITUTE(SUBSTITUTE(SUBSTITUTE(SUBSTITUTE(Продажи_исходные!B110,"№",""),"АРТ-",""),"АРТ_",""),"/","-"),3) -> АРТ-287 | C110: =IFERROR(VALUE(TRIM(SUBSTITUTE(SUBSTITUTE(SUBSTITUTE(SUBSTITUTE(Продажи_исходные!C110," шт.","")," шт",""),"шт.",""),"шт",""))),0) -> 3 | D110: =IF(LEFT(Продажи_исходные!D110,1)="$",VALUE(MID(Продажи_исходные!D110,2,255))*95,IF(LEFT(Продажи_исходные!D110,1)="€",VALUE(MID(Продажи_исходные!D110,2,255))*100,VALUE(SUBSTITUTE(SUBSTITUTE(Продажи_исходные!D110,"₽","")," ","")))) -> 9025 | E110: =Продажи_исходные!E110 -> C0109 | F110: =Продажи_исходные!F110 -> P005 | G110: =IFERROR(VLOOKUP(Продажи_исходные!G110,Справочники!$G$2:$H$50,2,FALSE),Продажи_исходные!G110) -> Завершен | H110: =IFERROR(VLOOKUP(B110,Товары_очищенные!$A$1:$G$1000,6,FALSE),"нет в каталоге") -> 7000 | I110: =IFERROR(VLOOKUP(B110,Товары_очищенные!$A$1:$G$1000,3,FALSE),"нет в каталоге") -> Аксессуары | J110: =IF(D110>0,"OK","Некорректная цена") -> OK
A111: =DATE(RIGHT(Продажи_исходные!A111,4),LEFT(Продажи_исходные!A111,2),MID(Продажи_исходные!A111,4,2)) -> 45726 | B111: ="АРТ-"&LEFT(SUBSTITUTE(SUBSTITUTE(SUBSTITUTE(SUBSTITUTE(Продажи_исходные!B111,"№",""),"АРТ-",""),"АРТ_",""),"/","-"),3) -> АРТ-209 | C111: =IFERROR(VALUE(TRIM(SUBSTITUTE(SUBSTITUTE(SUBSTITUTE(SUBSTITUTE(Продажи_исходные!C111," шт.","")," шт",""),"шт.",""),"шт",""))),0) -> 2 | D111: =IF(LEFT(Продажи_исходные!D111,1)="$",VALUE(MID(Продажи_исходные!D111,2,255))*95,IF(LEFT(Продажи_исходные!D111,1)="€",VALUE(MID(Продажи_исходные!D111,2,255))*100,VALUE(SUBSTITUTE(SUBSTITUTE(Продажи_исходные!D111,"₽","")," ","")))) -> 7500 | E111: =Продажи_исходные!E111 -> C0110 | F111: =Продажи_исходные!F111 -> P036 | G111: =IFERROR(VLOOKUP(Продажи_исходные!G111,Справочники!$G$2:$H$50,2,FALSE),Продажи_исходные!G111) -> Завершен | H111: =IFERROR(VLOOKUP(B111,Товары_очищенные!$A$1:$G$1000,6,FALSE),"нет в каталоге") -> 10500 | I111: =IFERROR(VLOOKUP(B111,Товары_очищенные!$A$1:$G$1000,3,FALSE),"нет в каталоге") -> Аксессуары | J111: =IF(D111>0,"OK","Некорректная цена") -> OK
A112: =DATE(RIGHT(Продажи_исходные!A112,4),LEFT(Продажи_исходные!A112,2),MID(Продажи_исходные!A112,4,2)) -> 45727 | B112: ="АРТ-"&LEFT(SUBSTITUTE(SUBSTITUTE(SUBSTITUTE(SUBSTITUTE(Продажи_исходные!B112,"№",""),"АРТ-",""),"АРТ_",""),"/","-"),3) -> АРТ-382 | C112: =IFERROR(VALUE(TRIM(SUBSTITUTE(SUBSTITUTE(SUBSTITUTE(SUBSTITUTE(Продажи_исходные!C112," шт.","")," шт",""),"шт.",""),"шт",""))),0) -> 1 | D112: =IF(LEFT(Продажи_исходные!D112,1)="$",VALUE(MID(Продажи_исходные!D112,2,255))*95,IF(LEFT(Продажи_исходные!D112,1)="€",VALUE(MID(Продажи_исходные!D112,2,255))*100,VALUE(SUBSTITUTE(SUBSTITUTE(Продажи_исходные!D112,"₽","")," ","")))) -> 5500 | E112: =Продажи_исходные!E112 -> C0111 | F112: =Продажи_исходные!F112 -> P014 | G112: =IFERROR(VLOOKUP(Продажи_исходные!G112,Справочники!$G$2:$H$50,2,FALSE),Продажи_исходные!G112) -> Завершен | H112: =IFERROR(VLOOKUP(B112,Товары_очищенные!$A$1:$G$1000,6,FALSE),"нет в каталоге") -> 42990 | I112: =IFERROR(VLOOKUP(B112,Товары_очищенные!$A$1:$G$1000,3,FALSE),"нет в каталоге") -> Смартфоны | J112: =IF(D112>0,"OK","Некорректная цена") -> OK
... A999: =DATE(RIGHT(Продажи_исходные!A999,4),LEFT(Продажи_исходные!A999,2),MID(Продажи_исходные!A999,4,2)) -> 46170 | B999: ="АРТ-"&LEFT(SUBSTITUTE(SUBSTITUTE(SUBSTITUTE(SUBSTITUTE(Продажи_исходные!B999,"№",""),"АРТ-",""),"АРТ_",""),"/","-"),3) -> АРТ-411 | C999: =IFERROR(VALUE(TRIM(SUBSTITUTE(SUBSTITUTE(SUBSTITUTE(SUBSTITUTE(Продажи_исходные!C999," шт.","")," шт",""),"шт.",""),"шт",""))),0) -> 2 | D999: =IF(LEFT(Продажи_исходные!D999,1)="$",VALUE(MID(Продажи_исходные!D999,2,255))*95,IF(LEFT(Продажи_исходные!D999,1)="€",VALUE(MID(Продажи_исходные!D999,2,255))*100,VALUE(SUBSTITUTE(SUBSTITUTE(Продажи_исходные!D999,"₽","")," ","")))) -> 8500 | E999: =Продажи_исходные!E999 -> C0998 | F999: =Продажи_исходные!F999 -> P022 | G999: =IFERROR(VLOOKUP(Продажи_исходные!G999,Справочники!$G$2:$H$50,2,FALSE),Продажи_исходные!G999) -> Возврат | H999: =IFERROR(VLOOKUP(B999,Товары_очищенные!$A$1:$G$1000,6,FALSE),"нет в каталоге") -> 41500 | I999: =IFERROR(VLOOKUP(B999,Товары_очищенные!$A$1:$G$1000,3,FALSE),"нет в каталоге") -> Наушники | J999: =IF(D999>0,"OK","Некорректная цена") -> OK
A1000: =DATE(RIGHT('Продажи_исходные'!A1000,4),LEFT('Продажи_исходные'!A1000,2),MID('Продажи_исходные'!A1000,4,2)) -> 46171 | B1000: ="АРТ-"&LEFT(SUBSTITUTE(SUBSTITUTE(SUBSTITUTE(SUBSTITUTE('Продажи_исходные'!B1000,"№",""),"АРТ-",""),"АРТ_",""),"/","-"),3) -> АРТ-372 | C1000: =IFERROR(VALUE(TRIM(SUBSTITUTE(SUBSTITUTE(SUBSTITUTE(SUBSTITUTE('Продажи_исходные'!C1000," шт.","")," шт",""),"шт.",""),"шт",""))),0) -> 1 | D1000: =IF(LEFT('Продажи_исходные'!D1000,1)="$",VALUE(MID('Продажи_исходные'!D1000,2,255))*95,IF(LEFT('Продажи_исходные'!D1000,1)="€",VALUE(MID('Продажи_исходные'!D1000,2,255))*100,VALUE(SUBSTITUTE(SUBSTITUTE('Продажи_исходные'!D1000,"₽","")," ","")))) -> 7800 | E1000: ='Продажи_исходные'!E1000 -> C0999 | F1000: ='Продажи_исходные'!F1000 -> P043 | G1000: =IFERROR(VLOOKUP('Продажи_исходные'!G1000,Справочники!$G$2:$H$50,2,FALSE),'Продажи_исходные'!G1000) -> Завершен | H1000: =IFERROR(VLOOKUP(B1000,'Товары_очищенные'!$A$1:$G$1000,6,FALSE),"нет в каталоге") -> 52000 | I1000: =IFERROR(VLOOKUP(B1000,'Товары_очищенные'!$A$1:$G$1000,3,FALSE),"нет в каталоге") -> Мониторы | J1000: =IF(D1000>0,"OK","Некорректная цена") -> OK
A1001: =DATE(RIGHT(Продажи_исходные!A1001,4),LEFT(Продажи_исходные!A1001,2),MID(Продажи_исходные!A1001,4,2)) -> 46171 | B1001: ="АРТ-"&LEFT(SUBSTITUTE(SUBSTITUTE(SUBSTITUTE(SUBSTITUTE(Продажи_исходные!B1001,"№",""),"АРТ-",""),"АРТ_",""),"/","-"),3) -> АРТ-357 | C1001: =IFERROR(VALUE(TRIM(SUBSTITUTE(SUBSTITUTE(SUBSTITUTE(SUBSTITUTE(Продажи_исходные!C1001," шт.","")," шт",""),"шт.",""),"шт",""))),0) -> -3 | D1001: =IF(LEFT(Продажи_исходные!D1001,1)="$",VALUE(MID(Продажи_исходные!D1001,2,255))*95,IF(LEFT(Продажи_исходные!D1001,1)="€",VALUE(MID(Продажи_исходные!D1001,2,255))*100,VALUE(SUBSTITUTE(SUBSTITUTE(Продажи_исходные!D1001,"₽","")," ","")))) -> 11400 | E1001: =Продажи_исходные!E1001 -> C1000 | F1001: =Продажи_исходные!F1001 -> P030 | G1001: =IFERROR(VLOOKUP(Продажи_исходные!G1001,Справочники!$G$2:$H$50,2,FALSE),Продажи_исходные!G1001) -> Завершен | H1001: =IFERROR(VLOOKUP(B1001,Товары_очищенные!$A$1:$G$1000,6,FALSE),"нет в каталоге") -> 88000 | I1001: =IFERROR(VLOOKUP(B1001,Товары_очищенные!$A$1:$G$1000,3,FALSE),"нет в каталоге") -> Смартфоны | J1001: =IF(D1001>0,"OK","Некорректная цена") -> OK

Sheet Клиенты_исходные
A1: ID_клиента | B1: ФИО | C1: Дата_рождения | D1: Телефон | E1: Email | F1: Город | G1: Дата_регистрации
A2: C0001 | B2: Иванов Иван Иванович | C2: 15.05.1990 | D2: 8-903-123-45-67 | E2: ivanov@mail.ru | F2: Москва | G2: 01.01.2022
A3: C0002 | B3: Петров Петр Петрович | C3: 23.08.1985 | D3: +7 903 234-56-78 | E3: petrov@yandex | F3: Санкт-Петербург | G3: 2022-01-15
A4: C0003 | B4: Сидоров Сидор Сидорович | C4: 12.03.1992 | D4: 8 903 345 67 89 | E4: sidorov@gmail.com | F4: Екатеринбург | G4: 15.01.2022
A5: C0004 | B5: Кузнецова Анна Сергеевна | C5: 07.11.1978 | D5: +79034567890 | E5: kuznetsova@mail | F5: Новосибирск | G5: 01.02.2022
A6: C0005 | B6: Смирнов Алексей Владимирович | C6: 30.06.1995 | D6: 8-903-456-78-90 | E6: smirnov@yandex | F6: Казань | G6: 2022-02-10
A7: C0006 | B7: Попова Елена Дмитриевна | C7: 14.09.1982 | D7: 8 903 567 89 01 | E7: popova@gmail | F7: Нижний Новгород | G7: 10.02.2022
A8: C0007 | B8: Васильев Андрей Николаевич | C8: 25.12.1970 | D8: +79035678901 | E8: vasiliev@mail | F8: Челябинск | G8: 01.03.2022
A9: C0008 | B9: Зайцева Ольга Игоревна | C9: 19.04.1988 | D9: 8-903-678-90-12 | E9: zaitceva@yandex | F9: Самара | G9: 2022-03-15
A10: C0009 | B10: Морозов Дмитрий Алексеевич | C10: 02.10.1993 | D10: 8 903 789 01 23 | E10: morozov@gmail | F10: Омск | G10: 15.03.2022
A11: C0010 | B11: Соколова Екатерина Павловна | C11: 16.01.1976 | D11: +79038901234 | E11: sokolova@mail | F11: Ростов-на-Дону | G11: 01.04.2022
A12: C0011 | B12: Михайлов Сергей Иванович | C12: 28.07.1984 | D12: 8-903-890-12-34 | E12: mihailov@yandex | F12: Уфа | G12: 2022-04-10
... A1001: C1000 | B1001: Толстых Андрей Олегович | C1001: 10.08.1984 | D1001: +79039012345 | E1001: tolstyh@mail | F1001: Якутск | G1001: 01.10.2049

Sheet Клиенты_очищенные
A1: ID_клиента | B1: ФИО | C1: Дата_рождения | D1: Телефон | E1: Email | F1: Город | G1: Дата_регистрации | H1: Возраст | I1: Проверка_возраста | J1: Проверка_Email
A2: ='Клиенты_исходные'!A2 -> C0001 | B2: =PROPER(TRIM('Клиенты_исходные'!B2)) -> Иванов Иван Иванович | C2: =IFERROR(IF(ISNUMBER(FIND(".",'Клиенты_исходные'!C2)),DATE(RIGHT('Клиенты_исходные'!C2,4),MID('Клиенты_исходные'!C2,4,2),LEFT('Клиенты_исходные'!C2,2)),DATE(LEFT('Клиенты_исходные'!C2,4),MID('Клиенты_исходные'!C2,6,2),RIGHT('Клиенты_исходные'!C2,2))),'Клиенты_исходные'!C2) -> 33008 | D2: =IF(ISBLANK(Клиенты_исходные!D2),"",IF(LEN(SUBSTITUTE(SUBSTITUTE(SUBSTITUTE(SUBSTITUTE(SUBSTITUTE(Клиенты_исходные!D2," ",""),"-",""),"+",""),"(",""),")",""))=11,"+7 ("&MID(IF(LEFT(SUBSTITUTE(SUBSTITUTE(SUBSTITUTE(SUBSTITUTE(SUBSTITUTE(Клиенты_исходные!D2," ",""),"-",""),"+",""),"(",""),")",""))="8","7"&MID(SUBSTITUTE(SUBSTITUTE(SUBSTITUTE(SUBSTITUTE(SUBSTITUTE(Клиенты_исходные!D2," ",""),"-",""),"+",""),"(",""),")",""),2,10),SUBSTITUTE(SUBSTITUTE(SUBSTITUTE(SUBSTITUTE(SUBSTITUTE(Клиенты_исходные!D2," ",""),"-",""),"+",""),"(",""),")","")),2,3)&") "&MID(IF(LEFT(SUBSTITUTE(SUBSTITUTE(SUBSTITUTE(SUBSTITUTE(SUBSTITUTE(Клиенты_исходные!D2," ",""),"-",""),"+",""),"(",""),")",""))="8","7"&MID(SUBSTITUTE(SUBSTITUTE(SUBSTITUTE(SUBSTITUTE(SUBSTITUTE(Клиенты_исходные!D2," ",""),"-",""),"+",""),"(",""),")",""),2,10),SUBSTITUTE(SUBSTITUTE(SUBSTITUTE(SUBSTITUTE(SUBSTITUTE(Клиенты_исходные!D2," ",""),"-",""),"+",""),"(",""),")","")),5,3)&"-"&MID(IF(LEFT(SUBSTITUTE(SUBSTITUTE(SUBSTITUTE(SUBSTITUTE(SUBSTITUTE(Клиенты_исходные!D2," ",""),"-",""),"+",""),"(",""),")",""))="8","7"&MID(SUBSTITUTE(SUBSTITUTE(SUBSTITUTE(SUBSTITUTE(SUBSTITUTE(Клиенты_исходные!D2," ",""),"-",""),"+",""),"(",""),")",""),2,10),SUBSTITUTE(SUBSTITUTE(SUBSTITUTE(SUBSTITUTE(SUBSTITUTE(Клиенты_исходные!D2," ",""),"-",""),"+",""),"(",""),")","")),8,2)&"-"&MID(IF(LEFT(SUBSTITUTE(SUBSTITUTE(SUBSTITUTE(SUBSTITUTE(SUBSTITUTE(Клиенты_исходные!D2," ",""),"-",""),"+",""),"(",""),")",""))="8","7"&MID(SUBSTITUTE(SUBSTITUTE(SUBSTITUTE(SUBSTITUTE(SUBSTITUTE(Клиенты_исходные!D2," ",""),"-",""),"+",""),"(",""),")",""),2,10),SUBSTITUTE(SUBSTITUTE(SUBSTITUTE(SUBSTITUTE(SUBSTITUTE(Клиенты_исходные!D2," ",""),"-",""),"+",""),"(",""),")","")),10,2),IF(LEN(SUBSTITUTE(SUBSTITUTE(SUBSTITUTE(SUBSTITUTE(SUBSTITUTE(Клиенты_исходные!D2," ",""),"-",""),"+",""),"(",""),")",""))=10,"+7 ("&MID(SUBSTITUTE(SUBSTITUTE(SUBSTITUTE(SUBSTITUTE(SUBSTITUTE(Клиенты_исходные!D2," ",""),"-",""),"+",""),"(",""),")",""),1,3)&") "&MID(SUBSTITUTE(SUBSTITUTE(SUBSTITUTE(SUBSTITUTE(SUBSTITUTE(Клиенты_исходные!D2," ",""),"-",""),"+",""),"(",""),")",""),4,3)&"-"&MID(SUBSTITUTE(SUBSTITUTE(SUBSTITUTE(SUBSTITUTE(SUBSTITUTE(Клиенты_исходные!D2," ",""),"-",""),"+",""),"(",""),")",""),6,2)&"-"&MID(SUBSTITUTE(SUBSTITUTE(SUBSTITUTE(SUBSTITUTE(SUBSTITUTE(Клиенты_исходные!D2," ",""),"-",""),"+",""),"(",""),")",""),8,2),Клиенты_исходные!D2))) -> +7 (903) 123-45-67 | E2: =IF(ISBLANK(Клиенты_исходные!E2),"",IF(ISNUMBER(FIND(".",MID(Клиенты_исходные!E2,FIND("@",Клиенты_исходные!E2)+1,255))),Клиенты_исходные!E2,IF(ISNUMBER(FIND("gmail",Клиенты_исходные!E2)),Клиенты_исходные!E2&".com",Клиенты_исходные!E2&".ru"))) -> ivanov@mail.ru | F2: =IFERROR(VLOOKUP('Клиенты_исходные'!F2,Справочники!$J$2:$K$50,2,FALSE),'Клиенты_исходные'!F2) -> Москва | G2: =IFERROR(IF(ISNUMBER(FIND(".",'Клиенты_исходные'!G2)),DATE(RIGHT('Клиенты_исходные'!G2,4),MID('Клиенты_исходные'!G2,4,2),LEFT('Клиенты_исходные'!G2,2)),DATE(LEFT('Клиенты_исходные'!G2,4),MID('Клиенты_исходные'!G2,6,2),RIGHT('Клиенты_исходные'!G2,2))),'Клиенты_исходные'!G2) -> 44562 | H2: =DATEDIF(C2,TODAY(),"Y") -> 36 | I2: =IF(OR(H2<18,H2>80),"Ошибка даты рождения","OK") -> OK | J2: =IF(AND(ISNUMBER(FIND("@",E2)),ISNUMBER(FIND(".",MID(E2,FIND("@",E2)+1,255)))),"OK","Ошибка Email") -> OK
A3: =Клиенты_исходные!A3 -> C0002 | B3: =PROPER(TRIM(Клиенты_исходные!B3)) -> Петров Петр Петрович | C3: =IFERROR(IF(ISNUMBER(FIND(".",Клиенты_исходные!C3)),DATE(RIGHT(Клиенты_исходные!C3,4),MID(Клиенты_исходные!C3,4,2),LEFT(Клиенты_исходные!C3,2)),DATE(LEFT(Клиенты_исходные!C3,4),MID(Клиенты_исходные!C3,6,2),RIGHT(Клиенты_исходные!C3,2))),Клиенты_исходные!C3) -> 31282 | D3: =IF(ISBLANK(Клиенты_исходные!D3),"",IF(LEN(SUBSTITUTE(SUBSTITUTE(SUBSTITUTE(SUBSTITUTE(SUBSTITUTE(Клиенты_исходные!D3," ",""),"-",""),"+",""),"(",""),")",""))=11,"+7 ("&MID(IF(LEFT(SUBSTITUTE(SUBSTITUTE(SUBSTITUTE(SUBSTITUTE(SUBSTITUTE(Клиенты_исходные!D3," ",""),"-",""),"+",""),"(",""),")",""))="8","7"&MID(SUBSTITUTE(SUBSTITUTE(SUBSTITUTE(SUBSTITUTE(SUBSTITUTE(Клиенты_исходные!D3," ",""),"-",""),"+",""),"(",""),")",""),2,10),SUBSTITUTE(SUBSTITUTE(SUBSTITUTE(SUBSTITUTE(SUBSTITUTE(Клиенты_исходные!D3," ",""),"-",""),"+",""),"(",""),")","")),2,3)&") "&MID(IF(LEFT(SUBSTITUTE(SUBSTITUTE(SUBSTITUTE(SUBSTITUTE(SUBSTITUTE(Клиенты_исходные!D3," ",""),"-",""),"+",""),"(",""),")",""))="8","7"&MID(SUBSTITUTE(SUBSTITUTE(SUBSTITUTE(SUBSTITUTE(SUBSTITUTE(Клиенты_исходные!D3," ",""),"-",""),"+",""),"(",""),")",""),2,10),SUBSTITUTE(SUBSTITUTE(SUBSTITUTE(SUBSTITUTE(SUBSTITUTE(Клиенты_исходные!D3," ",""),"-",""),"+",""),"(",""),")","")),5,3)&"-"&MID(IF(LEFT(SUBSTITUTE(SUBSTITUTE(SUBSTITUTE(SUBSTITUTE(SUBSTITUTE(Клиенты_исходные!D3," ",""),"-",""),"+",""),"(",""),")",""))="8","7"&MID(SUBSTITUTE(SUBSTITUTE(SUBSTITUTE(SUBSTITUTE(SUBSTITUTE(Клиенты_исходные!D3," ",""),"-",""),"+",""),"(",""),")",""),2,10),SUBSTITUTE(SUBSTITUTE(SUBSTITUTE(SUBSTITUTE(SUBSTITUTE(Клиенты_исходные!D3," ",""),"-",""),"+",""),"(",""),")","")),8,2)&"-"&MID(IF(LEFT(SUBSTITUTE(SUBSTITUTE(SUBSTITUTE(SUBSTITUTE(SUBSTITUTE(Клиенты_исходные!D3," ",""),"-",""),"+",""),"(",""),")",""))="8","7"&MID(SUBSTITUTE(SUBSTITUTE(SUBSTITUTE(SUBSTITUTE(SUBSTITUTE(Клиенты_исходные!D3," ",""),"-",""),"+",""),"(",""),")",""),2,10),SUBSTITUTE(SUBSTITUTE(SUBSTITUTE(SUBSTITUTE(SUBSTITUTE(Клиенты_исходные!D3," ",""),"-",""),"+",""),"(",""),")","")),10,2),IF(LEN(SUBSTITUTE(SUBSTITUTE(SUBSTITUTE(SUBSTITUTE(SUBSTITUTE(Клиенты_исходные!D3," ",""),"-",""),"+",""),"(",""),")",""))=10,"+7 ("&MID(SUBSTITUTE(SUBSTITUTE(SUBSTITUTE(SUBSTITUTE(SUBSTITUTE(Клиенты_исходные!D3," ",""),"-",""),"+",""),"(",""),")",""),1,3)&") "&MID(SUBSTITUTE(SUBSTITUTE(SUBSTITUTE(SUBSTITUTE(SUBSTITUTE(Клиенты_исходные!D3," ",""),"-",""),"+",""),"(",""),")",""),4,3)&"-"&MID(SUBSTITUTE(SUBSTITUTE(SUBSTITUTE(SUBSTITUTE(SUBSTITUTE(Клиенты_исходные!D3," ",""),"-",""),"+",""),"(",""),")",""),6,2)&"-"&MID(SUBSTITUTE(SUBSTITUTE(SUBSTITUTE(SUBSTITUTE(SUBSTITUTE(Клиенты_исходные!D3," ",""),"-",""),"+",""),"(",""),")",""),8,2),Клиенты_исходные!D3))) -> +7 (903) 234-56-78 | E3: =IF(ISBLANK(Клиенты_исходные!E3),"",IF(ISNUMBER(FIND(".",MID(Клиенты_исходные!E3,FIND("@",Клиенты_исходные!E3)+1,255))),Клиенты_исходные!E3,IF(ISNUMBER(FIND("gmail",Клиенты_исходные!E3)),Клиенты_исходные!E3&".com",Клиенты_исходные!E3&".ru"))) -> petrov@yandex.ru | F3: =IFERROR(VLOOKUP(Клиенты_исходные!F3,Справочники!$J$2:$K$50,2,FALSE),Клиенты_исходные!F3) -> Санкт-Петербург | G3: =IFERROR(IF(ISNUMBER(FIND(".",Клиенты_исходные!G3)),DATE(RIGHT(Клиенты_исходные!G3,4),MID(Клиенты_исходные!G3,4,2),LEFT(Клиенты_исходные!G3,2)),DATE(LEFT(Клиенты_исходные!G3,4),MID(Клиенты_исходные!G3,6,2),RIGHT(Клиенты_исходные!G3,2))),Клиенты_исходные!G3) -> 44576 | H3: =DATEDIF(C3,TODAY(),"Y") -> 41 | I3: =IF(OR(H3<18,H3>80),"Ошибка даты рождения","OK") -> OK | J3: =IF(AND(ISNUMBER(FIND("@",E3)),ISNUMBER(FIND(".",MID(E3,FIND("@",E3)+1,255)))),"OK","Ошибка Email") -> OK
A4: =Клиенты_исходные!A4 -> C0003 | B4: =PROPER(TRIM(Клиенты_исходные!B4)) -> Сидоров Сидор Сидорович | C4: =IFERROR(IF(ISNUMBER(FIND(".",Клиенты_исходные!C4)),DATE(RIGHT(Клиенты_исходные!C4,4),MID(Клиенты_исходные!C4,4,2),LEFT(Клиенты_исходные!C4,2)),DATE(LEFT(Клиенты_исходные!C4,4),MID(Клиенты_исходные!C4,6,2),RIGHT(Клиенты_исходные!C4,2))),Клиенты_исходные!C4) -> 33675 | D4: =IF(ISBLANK(Клиенты_исходные!D4),"",IF(LEN(SUBSTITUTE(SUBSTITUTE(SUBSTITUTE(SUBSTITUTE(SUBSTITUTE(Клиенты_исходные!D4," ",""),"-",""),"+",""),"(",""),")",""))=11,"+7 ("&MID(IF(LEFT(SUBSTITUTE(SUBSTITUTE(SUBSTITUTE(SUBSTITUTE(SUBSTITUTE(Клиенты_исходные!D4," ",""),"-",""),"+",""),"(",""),")",""))="8","7"&MID(SUBSTITUTE(SUBSTITUTE(SUBSTITUTE(SUBSTITUTE(SUBSTITUTE(Клиенты_исходные!D4," ",""),"-",""),"+",""),"(",""),")",""),2,10),SUBSTITUTE(SUBSTITUTE(SUBSTITUTE(SUBSTITUTE(SUBSTITUTE(Клиенты_исходные!D4," ",""),"-",""),"+",""),"(",""),")","")),2,3)&") "&MID(IF(LEFT(SUBSTITUTE(SUBSTITUTE(SUBSTITUTE(SUBSTITUTE(SUBSTITUTE(Клиенты_исходные!D4," ",""),"-",""),"+",""),"(",""),")",""))="8","7"&MID(SUBSTITUTE(SUBSTITUTE(SUBSTITUTE(SUBSTITUTE(SUBSTITUTE(Клиенты_исходные!D4," ",""),"-",""),"+",""),"(",""),")",""),2,10),SUBSTITUTE(SUBSTITUTE(SUBSTITUTE(SUBSTITUTE(SUBSTITUTE(Клиенты_исходные!D4," ",""),"-",""),"+",""),"(",""),")","")),5,3)&"-"&MID(IF(LEFT(SUBSTITUTE(SUBSTITUTE(SUBSTITUTE(SUBSTITUTE(SUBSTITUTE(Клиенты_исходные!D4," ",""),"-",""),"+",""),"(",""),")",""))="8","7"&MID(SUBSTITUTE(SUBSTITUTE(SUBSTITUTE(SUBSTITUTE(SUBSTITUTE(Клиенты_исходные!D4," ",""),"-",""),"+",""),"(",""),")",""),2,10),SUBSTITUTE(SUBSTITUTE(SUBSTITUTE(SUBSTITUTE(SUBSTITUTE(Клиенты_исходные!D4," ",""),"-",""),"+",""),"(",""),")","")),8,2)&"-"&MID(IF(LEFT(SUBSTITUTE(SUBSTITUTE(SUBSTITUTE(SUBSTITUTE(SUBSTITUTE(Клиенты_исходные!D4," ",""),"-",""),"+",""),"(",""),")",""))="8","7"&MID(SUBSTITUTE(SUBSTITUTE(SUBSTITUTE(SUBSTITUTE(SUBSTITUTE(Клиенты_исходные!D4," ",""),"-",""),"+",""),"(",""),")",""),2,10),SUBSTITUTE(SUBSTITUTE(SUBSTITUTE(SUBSTITUTE(SUBSTITUTE(Клиенты_исходные!D4," ",""),"-",""),"+",""),"(",""),")","")),10,2),IF(LEN(SUBSTITUTE(SUBSTITUTE(SUBSTITUTE(SUBSTITUTE(SUBSTITUTE(Клиенты_исходные!D4," ",""),"-",""),"+",""),"(",""),")",""))=10,"+7 ("&MID(SUBSTITUTE(SUBSTITUTE(SUBSTITUTE(SUBSTITUTE(SUBSTITUTE(Клиенты_исходные!D4," ",""),"-",""),"+",""),"(",""),")",""),1,3)&") "&MID(SUBSTITUTE(SUBSTITUTE(SUBSTITUTE(SUBSTITUTE(SUBSTITUTE(Клиенты_исходные!D4," ",""),"-",""),"+",""),"(",""),")",""),4,3)&"-"&MID(SUBSTITUTE(SUBSTITUTE(SUBSTITUTE(SUBSTITUTE(SUBSTITUTE(Клиенты_исходные!D4," ",""),"-",""),"+",""),"(",""),")",""),6,2)&"-"&MID(SUBSTITUTE(SUBSTITUTE(SUBSTITUTE(SUBSTITUTE(SUBSTITUTE(Клиенты_исходные!D4," ",""),"-",""),"+",""),"(",""),")",""),8,2),Клиенты_исходные!D4))) -> +7 (903) 345-67-89 | E4: =IF(ISBLANK(Клиенты_исходные!E4),"",IF(ISNUMBER(FIND(".",MID(Клиенты_исходные!E4,FIND("@",Клиенты_исходные!E4)+1,255))),Клиенты_исходные!E4,IF(ISNUMBER(FIND("gmail",Клиенты_исходные!E4)),Клиенты_исходные!E4&".com",Клиенты_исходные!E4&".ru"))) -> sidorov@gmail.com | F4: =IFERROR(VLOOKUP(Клиенты_исходные!F4,Справочники!$J$2:$K$50,2,FALSE),Клиенты_исходные!F4) -> Екатеринбург | G4: =IFERROR(IF(ISNUMBER(FIND(".",Клиенты_исходные!G4)),DATE(RIGHT(Клиенты_исходные!G4,4),MID(Клиенты_исходные!G4,4,2),LEFT(Клиенты_исходные!G4,2)),DATE(LEFT(Клиенты_исходные!G4,4),MID(Клиенты_исходные!G4,6,2),RIGHT(Клиенты_исходные!G4,2))),Клиенты_исходные!G4) -> 44576 | H4: =DATEDIF(C4,TODAY(),"Y") -> 34 | I4: =IF(OR(H4<18,H4>80),"Ошибка даты рождения","OK") -> OK | J4: =IF(AND(ISNUMBER(FIND("@",E4)),ISNUMBER(FIND(".",MID(E4,FIND("@",E4)+1,255)))),"OK","Ошибка Email") -> OK
A5: =Клиенты_исходные!A5 -> C0004 | B5: =PROPER(TRIM(Клиенты_исходные!B5)) -> Кузнецова Анна Сергеевна | C5: =IFERROR(IF(ISNUMBER(FIND(".",Клиенты_исходные!C5)),DATE(RIGHT(Клиенты_исходные!C5,4),MID(Клиенты_исходные!C5,4,2),LEFT(Клиенты_исходные!C5,2)),DATE(LEFT(Клиенты_исходные!C5,4),MID(Клиенты_исходные!C5,6,2),RIGHT(Клиенты_исходные!C5,2))),Клиенты_исходные!C5) -> 28801 | D5: =IF(ISBLANK(Клиенты_исходные!D5),"",IF(LEN(SUBSTITUTE(SUBSTITUTE(SUBSTITUTE(SUBSTITUTE(SUBSTITUTE(Клиенты_исходные!D5," ",""),"-",""),"+",""),"(",""),")",""))=11,"+7 ("&MID(IF(LEFT(SUBSTITUTE(SUBSTITUTE(SUBSTITUTE(SUBSTITUTE(SUBSTITUTE(Клиенты_исходные!D5," ",""),"-",""),"+",""),"(",""),")",""))="8","7"&MID(SUBSTITUTE(SUBSTITUTE(SUBSTITUTE(SUBSTITUTE(SUBSTITUTE(Клиенты_исходные!D5," ",""),"-",""),"+",""),"(",""),")",""),2,10),SUBSTITUTE(SUBSTITUTE(SUBSTITUTE(SUBSTITUTE(SUBSTITUTE(Клиенты_исходные!D5," ",""),"-",""),"+",""),"(",""),")","")),2,3)&") "&MID(IF(LEFT(SUBSTITUTE(SUBSTITUTE(SUBSTITUTE(SUBSTITUTE(SUBSTITUTE(Клиенты_исходные!D5," ",""),"-",""),"+",""),"(",""),")",""))="8","7"&MID(SUBSTITUTE(SUBSTITUTE(SUBSTITUTE(SUBSTITUTE(SUBSTITUTE(Клиенты_исходные!D5," ",""),"-",""),"+",""),"(",""),")",""),2,10),SUBSTITUTE(SUBSTITUTE(SUBSTITUTE(SUBSTITUTE(SUBSTITUTE(Клиенты_исходные!D5," ",""),"-",""),"+",""),"(",""),")","")),5,3)&"-"&MID(IF(LEFT(SUBSTITUTE(SUBSTITUTE(SUBSTITUTE(SUBSTITUTE(SUBSTITUTE(Клиенты_исходные!D5," ",""),"-",""),"+",""),"(",""),")",""))="8","7"&MID(SUBSTITUTE(SUBSTITUTE(SUBSTITUTE(SUBSTITUTE(SUBSTITUTE(Клиенты_исходные!D5," ",""),"-",""),"+",""),"(",""),")",""),2,10),SUBSTITUTE(SUBSTITUTE(SUBSTITUTE(SUBSTITUTE(SUBSTITUTE(Клиенты_исходные!D5," ",""),"-",""),"+",""),"(",""),")","")),8,2)&"-"&MID(IF(LEFT(SUBSTITUTE(SUBSTITUTE(SUBSTITUTE(SUBSTITUTE(SUBSTITUTE(Клиенты_исходные!D5," ",""),"-",""),"+",""),"(",""),")",""))="8","7"&MID(SUBSTITUTE(SUBSTITUTE(SUBSTITUTE(SUBSTITUTE(SUBSTITUTE(Клиенты_исходные!D5," ",""),"-",""),"+",""),"(",""),")",""),2,10),SUBSTITUTE(SUBSTITUTE(SUBSTITUTE(SUBSTITUTE(SUBSTITUTE(Клиенты_исходные!D5," ",""),"-",""),"+",""),"(",""),")","")),10,2),IF(LEN(SUBSTITUTE(SUBSTITUTE(SUBSTITUTE(SUBSTITUTE(SUBSTITUTE(Клиенты_исходные!D5," ",""),"-",""),"+",""),"(",""),")",""))=10,"+7 ("&MID(SUBSTITUTE(SUBSTITUTE(SUBSTITUTE(SUBSTITUTE(SUBSTITUTE(Клиенты_исходные!D5," ",""),"-",""),"+",""),"(",""),")",""),1,3)&") "&MID(SUBSTITUTE(SUBSTITUTE(SUBSTITUTE(SUBSTITUTE(SUBSTITUTE(Клиенты_исходные!D5," ",""),"-",""),"+",""),"(",""),")",""),4,3)&"-"&MID(SUBSTITUTE(SUBSTITUTE(SUBSTITUTE(SUBSTITUTE(SUBSTITUTE(Клиенты_исходные!D5," ",""),"-",""),"+",""),"(",""),")",""),6,2)&"-"&MID(SUBSTITUTE(SUBSTITUTE(SUBSTITUTE(SUBSTITUTE(SUBSTITUTE(Клиенты_исходные!D5," ",""),"-",""),"+",""),"(",""),")",""),8,2),Клиенты_исходные!D5))) -> +7 (903) 456-78-90 | E5: =IF(ISBLANK(Клиенты_исходные!E5),"",IF(ISNUMBER(FIND(".",MID(Клиенты_исходные!E5,FIND("@",Клиенты_исходные!E5)+1,255))),Клиенты_исходные!E5,IF(ISNUMBER(FIND("gmail",Клиенты_исходные!E5)),Клиенты_исходные!E5&".com",Клиенты_исходные!E5&".ru"))) -> kuznetsova@mail.ru | F5: =IFERROR(VLOOKUP(Клиенты_исходные!F5,Справочники!$J$2:$K$50,2,FALSE),Клиенты_исходные!F5) -> Новосибирск | G5: =IFERROR(IF(ISNUMBER(FIND(".",Клиенты_исходные!G5)),DATE(RIGHT(Клиенты_исходные!G5,4),MID(Клиенты_исходные!G5,4,2),LEFT(Клиенты_исходные!G5,2)),DATE(LEFT(Клиенты_исходные!G5,4),MID(Клиенты_исходные!G5,6,2),RIGHT(Клиенты_исходные!G5,2))),Клиенты_исходные!G5) -> 44593 | H5: =DATEDIF(C5,TODAY(),"Y") -> 47 | I5: =IF(OR(H5<18,H5>80),"Ошибка даты рождения","OK") -> OK | J5: =IF(AND(ISNUMBER(FIND("@",E5)),ISNUMBER(FIND(".",MID(E5,FIND("@",E5)+1,255)))),"OK","Ошибка Email") -> OK
A6: =Клиенты_исходные!A6 -> C0005 | B6: =PROPER(TRIM(Клиенты_исходные!B6)) -> Смирнов Алексей Владимирович | C6: =IFERROR(IF(ISNUMBER(FIND(".",Клиенты_исходные!C6)),DATE(RIGHT(Клиенты_исходные!C6,4),MID(Клиенты_исходные!C6,4,2),LEFT(Клиенты_исходные!C6,2)),DATE(LEFT(Клиенты_исходные!C6,4),MID(Клиенты_исходные!C6,6,2),RIGHT(Клиенты_исходные!C6,2))),Клиенты_исходные!C6) -> 34880 | D6: =IF(ISBLANK(Клиенты_исходные!D6),"",IF(LEN(SUBSTITUTE(SUBSTITUTE(SUBSTITUTE(SUBSTITUTE(SUBSTITUTE(Клиенты_исходные!D6," ",""),"-",""),"+",""),"(",""),")",""))=11,"+7 ("&MID(IF(LEFT(SUBSTITUTE(SUBSTITUTE(SUBSTITUTE(SUBSTITUTE(SUBSTITUTE(Клиенты_исходные!D6," ",""),"-",""),"+",""),"(",""),")",""))="8","7"&MID(SUBSTITUTE(SUBSTITUTE(SUBSTITUTE(SUBSTITUTE(SUBSTITUTE(Клиенты_исходные!D6," ",""),"-",""),"+",""),"(",""),")",""),2,10),SUBSTITUTE(SUBSTITUTE(SUBSTITUTE(SUBSTITUTE(SUBSTITUTE(Клиенты_исходные!D6," ",""),"-",""),"+",""),"(",""),")","")),2,3)&") "&MID(IF(LEFT(SUBSTITUTE(SUBSTITUTE(SUBSTITUTE(SUBSTITUTE(SUBSTITUTE(Клиенты_исходные!D6," ",""),"-",""),"+",""),"(",""),")",""))="8","7"&MID(SUBSTITUTE(SUBSTITUTE(SUBSTITUTE(SUBSTITUTE(SUBSTITUTE(Клиенты_исходные!D6," ",""),"-",""),"+",""),"(",""),")",""),2,10),SUBSTITUTE(SUBSTITUTE(SUBSTITUTE(SUBSTITUTE(SUBSTITUTE(Клиенты_исходные!D6," ",""),"-",""),"+",""),"(",""),")","")),5,3)&"-"&MID(IF(LEFT(SUBSTITUTE(SUBSTITUTE(SUBSTITUTE(SUBSTITUTE(SUBSTITUTE(Клиенты_исходные!D6," ",""),"-",""),"+",""),"(",""),")",""))="8","7"&MID(SUBSTITUTE(SUBSTITUTE(SUBSTITUTE(SUBSTITUTE(SUBSTITUTE(Клиенты_исходные!D6," ",""),"-",""),"+",""),"(",""),")",""),2,10),SUBSTITUTE(SUBSTITUTE(SUBSTITUTE(SUBSTITUTE(SUBSTITUTE(Клиенты_исходные!D6," ",""),"-",""),"+",""),"(",""),")","")),8,2)&"-"&MID(IF(LEFT(SUBSTITUTE(SUBSTITUTE(SUBSTITUTE(SUBSTITUTE(SUBSTITUTE(Клиенты_исходные!D6," ",""),"-",""),"+",""),"(",""),")",""))="8","7"&MID(SUBSTITUTE(SUBSTITUTE(SUBSTITUTE(SUBSTITUTE(SUBSTITUTE(Клиенты_исходные!D6," ",""),"-",""),"+",""),"(",""),")",""),2,10),SUBSTITUTE(SUBSTITUTE(SUBSTITUTE(SUBSTITUTE(SUBSTITUTE(Клиенты_исходные!D6," ",""),"-",""),"+",""),"(",""),")","")),10,2),IF(LEN(SUBSTITUTE(SUBSTITUTE(SUBSTITUTE(SUBSTITUTE(SUBSTITUTE(Клиенты_исходные!D6," ",""),"-",""),"+",""),"(",""),")",""))=10,"+7 ("&MID(SUBSTITUTE(SUBSTITUTE(SUBSTITUTE(SUBSTITUTE(SUBSTITUTE(Клиенты_исходные!D6," ",""),"-",""),"+",""),"(",""),")",""),1,3)&") "&MID(SUBSTITUTE(SUBSTITUTE(SUBSTITUTE(SUBSTITUTE(SUBSTITUTE(Клиенты_исходные!D6," ",""),"-",""),"+",""),"(",""),")",""),4,3)&"-"&MID(SUBSTITUTE(SUBSTITUTE(SUBSTITUTE(SUBSTITUTE(SUBSTITUTE(Клиенты_исходные!D6," ",""),"-",""),"+",""),"(",""),")",""),6,2)&"-"&MID(SUBSTITUTE(SUBSTITUTE(SUBSTITUTE(SUBSTITUTE(SUBSTITUTE(Клиенты_исходные!D6," ",""),"-",""),"+",""),"(",""),")",""),8,2),Клиенты_исходные!D6))) -> +7 (903) 456-78-90 | E6: =IF(ISBLANK(Клиенты_исходные!E6),"",IF(ISNUMBER(FIND(".",MID(Клиенты_исходные!E6,FIND("@",Клиенты_исходные!E6)+1,255))),Клиенты_исходные!E6,IF(ISNUMBER(FIND("gmail",Клиенты_исходные!E6)),Клиенты_исходные!E6&".com",Клиенты_исходные!E6&".ru"))) -> smirnov@yandex.ru | F6: =IFERROR(VLOOKUP(Клиенты_исходные!F6,Справочники!$J$2:$K$50,2,FALSE),Клиенты_исходные!F6) -> Казань | G6: =IFERROR(IF(ISNUMBER(FIND(".",Клиенты_исходные!G6)),DATE(RIGHT(Клиенты_исходные!G6,4),MID(Клиенты_исходные!G6,4,2),LEFT(Клиенты_исходные!G6,2)),DATE(LEFT(Клиенты_исходные!G6,4),MID(Клиенты_исходные!G6,6,2),RIGHT(Клиенты_исходные!G6,2))),Клиенты_исходные!G6) -> 44602 | H6: =DATEDIF(C6,TODAY(),"Y") -> 31 | I6: =IF(OR(H6<18,H6>80),"Ошибка даты рождения","OK") -> OK | J6: =IF(AND(ISNUMBER(FIND("@",E6)),ISNUMBER(FIND(".",MID(E6,FIND("@",E6)+1,255)))),"OK","Ошибка Email") -> OK
A7: =Клиенты_исходные!A7 -> C0006 | B7: =PROPER(TRIM(Клиенты_исходные!B7)) -> Попова Елена Дмитриевна | C7: =IFERROR(IF(ISNUMBER(FIND(".",Клиенты_исходные!C7)),DATE(RIGHT(Клиенты_исходные!C7,4),MID(Клиенты_исходные!C7,4,2),LEFT(Клиенты_исходные!C7,2)),DATE(LEFT(Клиенты_исходные!C7,4),MID(Клиенты_исходные!C7,6,2),RIGHT(Клиенты_исходные!C7,2))),Клиенты_исходные!C7) -> 30208 | D7: =IF(ISBLANK(Клиенты_исходные!D7),"",IF(LEN(SUBSTITUTE(SUBSTITUTE(SUBSTITUTE(SUBSTITUTE(SUBSTITUTE(Клиенты_исходные!D7," ",""),"-",""),"+",""),"(",""),")",""))=11,"+7 ("&MID(IF(LEFT(SUBSTITUTE(SUBSTITUTE(SUBSTITUTE(SUBSTITUTE(SUBSTITUTE(Клиенты_исходные!D7," ",""),"-",""),"+",""),"(",""),")",""))="8","7"&MID(SUBSTITUTE(SUBSTITUTE(SUBSTITUTE(SUBSTITUTE(SUBSTITUTE(Клиенты_исходные!D7," ",""),"-",""),"+",""),"(",""),")",""),2,10),SUBSTITUTE(SUBSTITUTE(SUBSTITUTE(SUBSTITUTE(SUBSTITUTE(Клиенты_исходные!D7," ",""),"-",""),"+",""),"(",""),")","")),2,3)&") "&MID(IF(LEFT(SUBSTITUTE(SUBSTITUTE(SUBSTITUTE(SUBSTITUTE(SUBSTITUTE(Клиенты_исходные!D7," ",""),"-",""),"+",""),"(",""),")",""))="8","7"&MID(SUBSTITUTE(SUBSTITUTE(SUBSTITUTE(SUBSTITUTE(SUBSTITUTE(Клиенты_исходные!D7," ",""),"-",""),"+",""),"(",""),")",""),2,10),SUBSTITUTE(SUBSTITUTE(SUBSTITUTE(SUBSTITUTE(SUBSTITUTE(Клиенты_исходные!D7," ",""),"-",""),"+",""),"(",""),")","")),5,3)&"-"&MID(IF(LEFT(SUBSTITUTE(SUBSTITUTE(SUBSTITUTE(SUBSTITUTE(SUBSTITUTE(Клиенты_исходные!D7," ",""),"-",""),"+",""),"(",""),")",""))="8","7"&MID(SUBSTITUTE(SUBSTITUTE(SUBSTITUTE(SUBSTITUTE(SUBSTITUTE(Клиенты_исходные!D7," ",""),"-",""),"+",""),"(",""),")",""),2,10),SUBSTITUTE(SUBSTITUTE(SUBSTITUTE(SUBSTITUTE(SUBSTITUTE(Клиенты_исходные!D7," ",""),"-",""),"+",""),"(",""),")","")),8,2)&"-"&MID(IF(LEFT(SUBSTITUTE(SUBSTITUTE(SUBSTITUTE(SUBSTITUTE(SUBSTITUTE(Клиенты_исходные!D7," ",""),"-",""),"+",""),"(",""),")",""))="8","7"&MID(SUBSTITUTE(SUBSTITUTE(SUBSTITUTE(SUBSTITUTE(SUBSTITUTE(Клиенты_исходные!D7," ",""),"-",""),"+",""),"(",""),")",""),2,10),SUBSTITUTE(SUBSTITUTE(SUBSTITUTE(SUBSTITUTE(SUBSTITUTE(Клиенты_исходные!D7," ",""),"-",""),"+",""),"(",""),")","")),10,2),IF(LEN(SUBSTITUTE(SUBSTITUTE(SUBSTITUTE(SUBSTITUTE(SUBSTITUTE(Клиенты_исходные!D7," ",""),"-",""),"+",""),"(",""),")",""))=10,"+7 ("&MID(SUBSTITUTE(SUBSTITUTE(SUBSTITUTE(SUBSTITUTE(SUBSTITUTE(Клиенты_исходные!D7," ",""),"-",""),"+",""),"(",""),")",""),1,3)&") "&MID(SUBSTITUTE(SUBSTITUTE(SUBSTITUTE(SUBSTITUTE(SUBSTITUTE(Клиенты_исходные!D7," ",""),"-",""),"+",""),"(",""),")",""),4,3)&"-"&MID(SUBSTITUTE(SUBSTITUTE(SUBSTITUTE(SUBSTITUTE(SUBSTITUTE(Клиенты_исходные!D7," ",""),"-",""),"+",""),"(",""),")",""),6,2)&"-"&MID(SUBSTITUTE(SUBSTITUTE(SUBSTITUTE(SUBSTITUTE(SUBSTITUTE(Клиенты_исходные!D7," ",""),"-",""),"+",""),"(",""),")",""),8,2),Клиенты_исходные!D7))) -> +7 (903) 567-89-01 | E7: =IF(ISBLANK(Клиенты_исходные!E7),"",IF(ISNUMBER(FIND(".",MID(Клиенты_исходные!E7,FIND("@",Клиенты_исходные!E7)+1,255))),Клиенты_исходные!E7,IF(ISNUMBER(FIND("gmail",Клиенты_исходные!E7)),Клиенты_исходные!E7&".com",Клиенты_исходные!E7&".ru"))) -> popova@gmail.com | F7: =IFERROR(VLOOKUP(Клиенты_исходные!F7,Справочники!$J$2:$K$50,2,FALSE),Клиенты_исходные!F7) -> Нижний Новгород | G7: =IFERROR(IF(ISNUMBER(FIND(".",Клиенты_исходные!G7)),DATE(RIGHT(Клиенты_исходные!G7,4),MID(Клиенты_исходные!G7,4,2),LEFT(Клиенты_исходные!G7,2)),DATE(LEFT(Клиенты_исходные!G7,4),MID(Клиенты_исходные!G7,6,2),RIGHT(Клиенты_исходные!G7,2))),Клиенты_исходные!G7) -> 44602 | H7: =DATEDIF(C7,TODAY(),"Y") -> 44 | I7: =IF(OR(H7<18,H7>80),"Ошибка даты рождения","OK") -> OK | J7: =IF(AND(ISNUMBER(FIND("@",E7)),ISNUMBER(FIND(".",MID(E7,FIND("@",E7)+1,255)))),"OK","Ошибка Email") -> OK
A8: =Клиенты_исходные!A8 -> C0007 | B8: =PROPER(TRIM(Клиенты_исходные!B8)) -> Васильев Андрей Николаевич | C8: =IFERROR(IF(ISNUMBER(FIND(".",Клиенты_исходные!C8)),DATE(RIGHT(Клиенты_исходные!C8,4),MID(Клиенты_исходные!C8,4,2),LEFT(Клиенты_исходные!C8,2)),DATE(LEFT(Клиенты_исходные!C8,4),MID(Клиенты_исходные!C8,6,2),RIGHT(Клиенты_исходные!C8,2))),Клиенты_исходные!C8) -> 25927 | D8: =IF(ISBLANK(Клиенты_исходные!D8),"",IF(LEN(SUBSTITUTE(SUBSTITUTE(SUBSTITUTE(SUBSTITUTE(SUBSTITUTE(Клиенты_исходные!D8," ",""),"-",""),"+",""),"(",""),")",""))=11,"+7 ("&MID(IF(LEFT(SUBSTITUTE(SUBSTITUTE(SUBSTITUTE(SUBSTITUTE(SUBSTITUTE(Клиенты_исходные!D8," ",""),"-",""),"+",""),"(",""),")",""))="8","7"&MID(SUBSTITUTE(SUBSTITUTE(SUBSTITUTE(SUBSTITUTE(SUBSTITUTE(Клиенты_исходные!D8," ",""),"-",""),"+",""),"(",""),")",""),2,10),SUBSTITUTE(SUBSTITUTE(SUBSTITUTE(SUBSTITUTE(SUBSTITUTE(Клиенты_исходные!D8," ",""),"-",""),"+",""),"(",""),")","")),2,3)&") "&MID(IF(LEFT(SUBSTITUTE(SUBSTITUTE(SUBSTITUTE(SUBSTITUTE(SUBSTITUTE(Клиенты_исходные!D8," ",""),"-",""),"+",""),"(",""),")",""))="8","7"&MID(SUBSTITUTE(SUBSTITUTE(SUBSTITUTE(SUBSTITUTE(SUBSTITUTE(Клиенты_исходные!D8," ",""),"-",""),"+",""),"(",""),")",""),2,10),SUBSTITUTE(SUBSTITUTE(SUBSTITUTE(SUBSTITUTE(SUBSTITUTE(Клиенты_исходные!D8," ",""),"-",""),"+",""),"(",""),")","")),5,3)&"-"&MID(IF(LEFT(SUBSTITUTE(SUBSTITUTE(SUBSTITUTE(SUBSTITUTE(SUBSTITUTE(Клиенты_исходные!D8," ",""),"-",""),"+",""),"(",""),")",""))="8","7"&MID(SUBSTITUTE(SUBSTITUTE(SUBSTITUTE(SUBSTITUTE(SUBSTITUTE(Клиенты_исходные!D8," ",""),"-",""),"+",""),"(",""),")",""),2,10),SUBSTITUTE(SUBSTITUTE(SUBSTITUTE(SUBSTITUTE(SUBSTITUTE(Клиенты_исходные!D8," ",""),"-",""),"+",""),"(",""),")","")),8,2)&"-"&MID(IF(LEFT(SUBSTITUTE(SUBSTITUTE(SUBSTITUTE(SUBSTITUTE(SUBSTITUTE(Клиенты_исходные!D8," ",""),"-",""),"+",""),"(",""),")",""))="8","7"&MID(SUBSTITUTE(SUBSTITUTE(SUBSTITUTE(SUBSTITUTE(SUBSTITUTE(Клиенты_исходные!D8," ",""),"-",""),"+",""),"(",""),")",""),2,10),SUBSTITUTE(SUBSTITUTE(SUBSTITUTE(SUBSTITUTE(SUBSTITUTE(Клиенты_исходные!D8," ",""),"-",""),"+",""),"(",""),")","")),10,2),IF(LEN(SUBSTITUTE(SUBSTITUTE(SUBSTITUTE(SUBSTITUTE(SUBSTITUTE(Клиенты_исходные!D8," ",""),"-",""),"+",""),"(",""),")",""))=10,"+7 ("&MID(SUBSTITUTE(SUBSTITUTE(SUBSTITUTE(SUBSTITUTE(SUBSTITUTE(Клиенты_исходные!D8," ",""),"-",""),"+",""),"(",""),")",""),1,3)&") "&MID(SUBSTITUTE(SUBSTITUTE(SUBSTITUTE(SUBSTITUTE(SUBSTITUTE(Клиенты_исходные!D8," ",""),"-",""),"+",""),"(",""),")",""),4,3)&"-"&MID(SUBSTITUTE(SUBSTITUTE(SUBSTITUTE(SUBSTITUTE(SUBSTITUTE(Клиенты_исходные!D8," ",""),"-",""),"+",""),"(",""),")",""),6,2)&"-"&MID(SUBSTITUTE(SUBSTITUTE(SUBSTITUTE(SUBSTITUTE(SUBSTITUTE(Клиенты_исходные!D8," ",""),"-",""),"+",""),"(",""),")",""),8,2),Клиенты_исходные!D8))) -> +7 (903) 567-89-01 | E8: =IF(ISBLANK(Клиенты_исходные!E8),"",IF(ISNUMBER(FIND(".",MID(Клиенты_исходные!E8,FIND("@",Клиенты_исходные!E8)+1,255))),Клиенты_исходные!E8,IF(ISNUMBER(FIND("gmail",Клиенты_исходные!E8)),Клиенты_исходные!E8&".com",Клиенты_исходные!E8&".ru"))) -> vasiliev@mail.ru | F8: =IFERROR(VLOOKUP(Клиенты_исходные!F8,Справочники!$J$2:$K$50,2,FALSE),Клиенты_исходные!F8) -> Челябинск | G8: =IFERROR(IF(ISNUMBER(FIND(".",Клиенты_исходные!G8)),DATE(RIGHT(Клиенты_исходные!G8,4),MID(Клиенты_исходные!G8,4,2),LEFT(Клиенты_исходные!G8,2)),DATE(LEFT(Клиенты_исходные!G8,4),MID(Клиенты_исходные!G8,6,2),RIGHT(Клиенты_исходные!G8,2))),Клиенты_исходные!G8) -> 44621 | H8: =DATEDIF(C8,TODAY(),"Y") -> 55 | I8: =IF(OR(H8<18,H8>80),"Ошибка даты рождения","OK") -> OK | J8: =IF(AND(ISNUMBER(FIND("@",E8)),ISNUMBER(FIND(".",MID(E8,FIND("@",E8)+1,255)))),"OK","Ошибка Email") -> OK
